Workbook
Name furnace_part_scale_y: Shop!$C$98
Name dm_furnace_y: Shop!$C$95
Name uptime_hours_yr: 'P-50 Base'!$C$36
Name build_x: Shop!$C$71
Name dm_furnace_y: #REF!
Name part_x: Shop!$C$5
Name build_z: 'P-1'!$C$73
Name printhead_life: 'P-1'!$C$85
Name avail_hours_yr: Shop!$C$34
Name InnoventX: Inputs!$O$104:$O$125
Name s_model: #REF!
Name z_scale: 'P-50 Base'!$C$63
Name xlink_msrp: 'P-1'!$C$119
Name parts_job: Universal!$C$79
Name weeks_yr: 'P-50 Auto'!$C$32
Name furnace_shelves: 'P-1'!$C$112
Name uptime: Universal!$C$38
Name powder_default_price: 'P-50 Base'!$C$43
Name dm_furnace_hw_consumables: Universal!$C$123
Name dm_furnace_x: Universal!$XFD$99
Name furnace_z_spacing: Shop!$C$101
Name furnace_part_scale_z: Universal!$C$129
Name part_only_vol: 'P-50 Base'!$C$8
Name buildbox_msrp: 'P-50 Auto'!$C$118
Name furnace_part_scale_z: 'P-50 Auto'!$C$94
Name furnace_shelves: 'P-50 Auto'!$C$107
Name print_turnaround: 'P-50 Auto'!$C$75
Name sponge_msrp: Shop!$C$46
Name dm_furnace_consumables_material: Shop!$C$105
Name powder_default_price: 'P-1'!$C$43
Name furnace_part_scale_x: 'P-1'!$C$97
Name furnace_utilities_hr: Universal!$C$125
Name floor_rate: 'P-1'!$C$57
Name uptime_hours_yr: 'P-50 Auto'!$C$35
Name part_y: Universal!$C$6
Name xlink_module_msrp: 'P-1'!$C$120
Name printer_msrp: 'P-50 Base'!$C$118
Name total_builds_yr: 'P-1'!$G$12
Name furnace_part_scale_x: Shop!$C$97
Name ShopPlus_4L: Inputs!$F$104:$F$125
Name printer_msrp: Universal!$C$148
Name nitrogen_rate: Universal!$C$61
Name xlink_floorspace: Universal!$C$142
Name ShopPro_4L: Inputs!$I$104:$I$125
Name part_only_vol: Shop!$C$8
Name blender_msrp: 'P-1'!$C$122
Name support_vol: 'P-50 Auto'!$C$9
Name part_scale_y: Universal!$C$76
Name binder_per_yr: 'P-1'!$C$165
Name avail_hours_yr: 'P-50 Base'!$C$34
Name good_parts_job: Shop!$C$28
Name printer_z_base: 'P-50 Base'!$C$89
Name floor_rate: 'P-50 Auto'!$C$56
Name furnace_gas_cons: 'P-50 Base'!$C$114
Name part_z: 'P-50 Auto'!$C$7
Name p_model: 'P-50 Base'!$C$14
Name total_yield: Universal!$C$30
Name y_scale: Universal!$C$72
Name buildbox_msrp: 'P-50 Base'!$C$123
Name weeks_yr: 'P-1'!$C$33

Sheet Change Log
A1: Version | B1: Date | C1: Description
A2: 13.1.0 | B2: 44627 | C2: - changed ExOne printer names to X-Series nomenclature - corrected cells Y34 and Y35 to display correct information - updated MSRP for all systems to match current pricebook
A3: 13.1.1 | B3: 44629 | C3: - corrected cell C68 invalid reference
A4: 13.1.2 | B4: 44652 | C4: - added SiC cost and density data to lookup tables - corrected error where incorrect printer model was shown in cost summary table
A5: 13.1.3 | B5: 44663 | C5: - added S7
A6: 13.1.4 | B6: 44680 | C6: - fixed ShopPro layer speed to match Shop - fixed ShopPro consumables not calculating
A7: 13.2.0 | B7: 44729 | C7: - added ShopPlus 4L, 8L, 12L - added ShopPro 4L, 8L, 12L - updated Al6061 pricing on Production Series from $10-->$30/kg - updated X25Pro layer time to 50s -updated X160Pro layer time to 45s - corrected furnace XY and Z spacing lookups in tab 'Universal', cells C128 and C129 - removed X160Pro Inert - corrected DM Furnace MSRP
A8: 13.2.1 | B8: 44764 | C8: - corrected z-height for ShopPlus 4L and 8L - corrected cell C68 on "Universal" tab to reflect correct value when Furnace set = 1 - removed formula from cell C40 "Universal"
A9: 13.2.2 | B9: 44791 | C9: - added maximum part quantity produced with single unit configuration - C40 - enter this number into C41 to generate single unit configuration cost analysis - updated MSRPs to pricelist - added material specific gas consumption to DM Furnace - added IN625 to Shop material availability
A10: 13.2.3 | B10: 44915 | C10: - fixed P-50 Auto material selection - fixed powder pricing reference in notes - added IN718 for Shop System models
A11: 13.2.4 | B11: 44923 | C11: - added CM Furnace Tube Furnace 1630-20 - added output section without depreciated part cost - removed "Shop_4L" from donut chart title block - added "DM HH Stainless", "440C," "CrMnMoN," and "WC-12Co" to Production Series - verified MSRP hardware pricing to Q4-22 Price List - updated InnoventX DIMMs to match datasheet
A12: 13.2.5 | B12: 44958 | C12: - Corrected InnoventX y-dim from 125 to 160 - adjusted locked cell permissions for override nesting - adjusted locked cell permissions for parts required/ year
A13: 13.2.6 | B13: 45296 | C13: - Modified X-series binder/cleaner/crosslink times based on process team (max Inks) spreadsheet - auto calculate setter raft volume for TurboFuse with X-series - added binder picklist for each printer - updated material availability based on binder selection - updated raw powder pricing based on available market data - Updated DM Furnace to include insulation pack consumable - added PureSinter draft specifications – Updated Elnik furnaces with latest spec data
... A15: 13.2.6 | B15: 45372 | C15: - Updated 3rd party furnace costs

Sheet Inputs
B1: 1 | C1: =B1+1 -> 2 | D1: =C1+1 -> 3 | E1: =D1+1 -> 4 | F1: =E1+1 -> 5 | G1: =F1+1 -> 6 | H1: =G1+1 -> 7 | I1: =H1+1 -> 8 | J1: =I1+1 -> 9 | ... Q1: =P1+1 -> 16
B2: Material
C4: Shop_4L | D4: Shop_8L | E4: Shop_12L | F4: ShopPlus_4L | G4: ShopPlus_8L | H4: ShopPlus_12L | I4: ShopPro_4L | J4: ShopPro_8L | K4: ShopPro_12L | L4: P_1 | M4: P_50_Base | N4: P_50_Auto | O4: InnoventX | P4: X25Pro | Q4: X160Pro
A5: x | B5: Part inputs | S5: =IF(Universal!printer_index<13,"","AquaFuse")
B6: X-scale | C6: 1.167 | D6: 1.167 | E6: 1.167 | F6: 1.167 | G6: 1.167 | H6: 1.167 | I6: 1.167 | J6: 1.167 | K6: 1.167 | L6: =VLOOKUP(Universal!material_sel,Layer_defaults!$A$2:$E$22,3,FALSE) -> 1.16 | M6: =VLOOKUP(Universal!material_sel,Layer_defaults!$A$2:$E$22,3,FALSE) -> 1.16 | N6: =VLOOKUP(Universal!material_sel,Layer_defaults!$A$2:$E$22,3,FALSE) -> 1.16 | O6: 1.18 | P6: 1.18 | Q6: 1.18 | S6: =IF(Universal!printer_index<13,"","CleanFuse")
B7: Y-scale | C7: 1.174 | D7: 1.174 | E7: 1.174 | F7: 1.174 | G7: 1.174 | H7: 1.174 | I7: 1.174 | J7: 1.174 | K7: 1.174 | L7: =VLOOKUP(Universal!material_sel,Layer_defaults!$A$2:$E$22,4,FALSE) -> 1.165 | M7: =VLOOKUP(Universal!material_sel,Layer_defaults!$A$2:$E$22,4,FALSE) -> 1.165 | N7: =VLOOKUP(Universal!material_sel,Layer_defaults!$A$2:$E$22,4,FALSE) -> 1.165 | O7: 1.18 | P7: 1.18 | Q7: 1.18 | S7: =IF(Universal!printer_index<13,"","FluidFuse")
B8: Z-scale | C8: 1.21 | D8: 1.21 | E8: 1.21 | F8: 1.21 | G8: 1.21 | H8: 1.21 | I8: 1.21 | J8: 1.21 | K8: 1.21 | L8: =VLOOKUP(Universal!material_sel,Layer_defaults!$A$2:$E$22,5,FALSE) -> 1.18 | M8: =VLOOKUP(Universal!material_sel,Layer_defaults!$A$2:$E$22,5,FALSE) -> 1.18 | N8: =VLOOKUP(Universal!material_sel,Layer_defaults!$A$2:$E$22,5,FALSE) -> 1.18 | O8: 1.18 | P8: 1.18 | Q8: 1.18 | S8: =IF(Universal!printer_index<13,"","PhenolFuse")
A9: x | B9: Printer inputs | S9: =IF(Universal!printer_index<13,"","TurboFuse")
B10: Layer speed | C10: 26 | D10: 26 | E10: 26 | F10: 26 | G10: 26 | H10: 26 | I10: 26 | J10: 26 | K10: 26 | L10: 2.63 | M10: 2.98 | N10: 2.98 | O10: 22.23 | P10: 46 | Q10: 46 | R10: sec | S10: =IF(Universal!printer_index<10,"SS01","") -> SS01
B11: X-Series Layer speed with TurboFuse | F11: 26 | G11: 26 | H11: 26 | I11: 26 | J11: 26 | K11: 26 | L11: 2.63 | M11: 2.98 | N11: 2.98 | O11: 22.23 | P11: 24 | Q11: 46 | S11: =IF(Universal!printer_index<10,"",IF(Universal!printer_index>12,"","SPJ04"))
B12: Build box X-dim | C12: 350 | D12: 350 | E12: 350 | F12: 350 | G12: 350 | H12: 350 | I12: 350 | J12: 350 | K12: 350 | L12: 200 | M12: 490 | N12: 490 | O12: 75 | P12: 270 | Q12: 500 | R12: mm
B13: Build box Y-dim | C13: 220 | D13: 220 | E13: 220 | F13: 220 | G13: 220 | H13: 220 | I13: 220 | J13: 220 | K13: 220 | L13: 100 | M13: 380 | N13: 380 | O13: 170 | P13: 420 | Q13: 800 | R13: mm
B14: Build box Z-dim | C14: 50 | D14: 100 | E14: 150 | F14: 50 | G14: 100 | H14: 150 | I14: 50 | J14: 50 | K14: 150 | L14: 40 | M14: 260 | N14: 260 | O14: 75 | P14: 270 | Q14: 400 | R14: mm
B15: Bed density | C15: 0.56 | D15: 0.56 | E15: 0.56 | F15: 0.56 | G15: 0.56 | H15: 0.56 | I15: 0.56 | J15: 0.56 | K15: 0.56 | L15: 0.6 | M15: 0.6 | N15: 0.6 | O15: 0.59 | P15: 0.59 | Q15: 0.59
B16: Powder + overflow ratio | C16: 1.8 | D16: 1.8 | E16: 1.8 | F16: 1.8 | G16: 1.8 | H16: 1.8 | I16: 1.8 | J16: 1.8 | K16: 1.8 | L16: 6 | M16: 6 | N16: 6 | O16: 4 | P16: 4 | Q16: 4
B17: Powder loss percentage | C17: 0.005 | D17: 0.005 | E17: 0.005 | F17: 0.005 | G17: 0.005 | H17: 0.005 | I17: 0.005 | J17: 0.005 | K17: 0.005 | L17: 0.005 | M17: 0.001 | N17: 0.001 | O17: 0.001 | P17: 0.001 | Q17: 0.001
B18: Binder void ratio | C18: 0.68181818 | D18: 0.68181818 | E18: 0.68181818 | F18: 0.68181818 | G18: 0.68181818 | H18: 0.68181818 | I18: 0.68181818 | J18: 0.68181818 | K18: 0.68181818 | L18: 0.8 | M18: 0.7 | N18: 0.7 | O18: 0.8 | P18: 0.8 | Q18: 0.8
B19: Purge frequency | C19: 16 | D19: 16 | E19: 16 | F19: 16 | G19: 16 | H19: 16 | I19: 16 | J19: 16 | K19: 16 | L19: 50 | M19: 100 | N19: 100 | O19: 2 | P19: 2 | Q19: 2 | R19: layers
B20: Binder purge volume | C20: 1.5 | D20: 1.5 | E20: 1.5 | F20: 1.5 | G20: 1.5 | H20: 1.5 | I20: 1.5 | J20: 1.5 | K20: 1.5 | L20: 5 | M20: 20 | N20: 20 | O20: 1.25 | P20: 1.5 | Q20: 10 | R20: mL
B21: Binder purge btwn parts | C21: Yes | D21: Yes | E21: Yes | F21: Yes | G21: Yes | H21: Yes | I21: Yes | J21: Yes | K21: Yes | L21: Yes | M21: Yes | N21: Yes | O21: No | P21: No | Q21: No
B22: Printer XY border | C22: 4 | D22: 4 | E22: 4 | F22: 4 | G22: 4 | H22: 4 | I22: 4 | J22: 4 | K22: 4 | L22: 8.5 | M22: 20 | N22: 20 | O22: 5 | P22: 10 | Q22: 10 | R22: mm
B23: Printer Z base plate | C23: 3 | D23: 3 | E23: 3 | F23: 3 | G23: 3 | H23: 3 | I23: 3 | J23: 3 | K23: 3 | L23: 4 | M23: 10 | N23: 10 | O23: 1 | P23: 4 | Q23: 1 | R23: mm
B24: Printer XY spacing | C24: 1 | D24: 1 | E24: 1 | F24: 1 | G24: 1 | H24: 1 | I24: 1 | J24: 1 | K24: 1 | L24: 1 | M24: 1 | N24: 1 | O24: 1 | P24: 5 | Q24: 1 | R24: mm
B25: Printer Z spacing | C25: 1 | D25: 1 | E25: 1 | F25: 1 | G25: 1 | H25: 1 | I25: 1 | J25: 1 | K25: 1 | L25: 0.4 | M25: 0.4 | N25: 0.4 | O25: 0.5 | P25: 5 | Q25: 0.5 | R25: mm
A26: x | B26: Printer layer thickness
B27: Min layer thickness | C27: 50 | D27: 50 | E27: 50 | F27: 50 | G27: 50 | H27: 50 | I27: 50 | J27: 50 | K27: 50 | L27: 35 | M27: 35 | N27: 35 | O27: 30 | P27: 30 | Q27: 30 | R27: um
B28: Max layer thickness | C28: 100 | D28: 100 | E28: 100 | F28: 100 | G28: 100 | H28: 100 | I28: 100 | J28: 100 | K28: 100 | L28: 150 | M28: 150 | N28: 150 | O28: 200 | P28: 200 | Q28: 200 | R28: um
B29: Increment | C29: 25 | D29: 25 | E29: 25 | F29: 25 | G29: 25 | H29: 25 | I29: 25 | J29: 25 | K29: 25 | L29: 5 | M29: 5 | N29: 5 | O29: 5 | P29: 5 | Q29: 5 | R29: um
B30: Default | C30: 75 | D30: 75 | E30: 75 | F30: 75 | G30: 75 | H30: 75 | I30: 75 | J30: 75 | K30: 75 | L30: 65 | M30: 65 | N30: 65 | O30: 50 | P30: 50 | Q30: 50 | R30: um
A31: x | B31: Auxiliary equipment inputs
B32: Crosslink time | C32: =IF(OR(Shop!s_model="4L",Shop!s_model="8L"),20,26) -> 26 | D32: =IF(OR(Shop!s_model="4L",Shop!s_model="8L"),20,26) -> 26 | E32: =IF(OR(Shop!s_model="4L",Shop!s_model="8L"),20,26) -> 26 | F32: =IF(OR(Shop!s_model="4L",Shop!s_model="8L"),20,26) -> 26 | G32: =IF(OR(Shop!s_model="4L",Shop!s_model="8L"),20,26) -> 26 | H32: =IF(OR(Shop!s_model="4L",Shop!s_model="8L"),20,26) -> 26 | I32: 20 | J32: 20 | K32: 20 | L32: 4.5 | M32: 40 | N32: 40 | O32: =12+(((Universal!build_height-25.4)/25.4)*4) -> 25.937008 | P32: =12+(((Universal!build_height-25.4)/25.4)*4) -> 25.937008 | Q32: =12+(((Universal!build_height-25.4)/25.4)*4) -> 25.937008 | R32: hrs | S32: SPJ = (build height / 30 * 6) + (build height / 30 * 2) + 10 + 10 = hours
B33: X-Series Crosslink time with TurboFuse | L33: 4.5 | M33: 40 | N33: 40 | O33: =(Universal!build_height/30*6)+(Universal!build_height/30*2)+10+10 -> 50.373333 | P33: =(Universal!build_height/30*6)+(Universal!build_height/30*2)+10+10 -> 50.373333 | Q33: =(Universal!build_height/30*6)+(Universal!build_height/30*2)+10+10 -> 50.373333
B34: Printer builds / oven run | C34: 2 | D34: 2 | E34: 2 | F34: 2 | G34: 2 | H34: 2 | I34: 2 | J34: 2 | K34: 2 | L34: 6 | M34: 2 | N34: 2 | O34: 4 | P34: =IF(Universal!$C$14="TurboFuse",1,2) -> 2 | Q34: 1 | S34: all X-series Metal Fuse = 12+(((build height - 25.4)/25.4)*4)
B35: Powder blender capacity | C35: 45 | D35: 45 | E35: 45 | F35: 45 | G35: 45 | H35: 45 | I35: 45 | J35: 45 | K35: 45 | L35: 45 | M35: 0 | N35: 0 | O35: 45 | P35: 500 | Q35: 0 | R35: kg
B36: Printers / PPU auto | C36: 0 | D36: 0 | E36: 0 | F36: 0 | G36: 0 | H36: 0 | I36: 0 | J36: 0 | K36: 0 | L36: 0 | M36: 1 | N36: 1 | O36: 0 | P36: 0 | Q36: 2
B37: Depowders / PPU auto | C37: 0 | D37: 0 | E37: 0 | F37: 0 | G37: 0 | H37: 0 | I37: 0 | J37: 0 | K37: 0 | L37: 0 | M37: 2 | N37: 2 | O37: 0 | P37: 0 | Q37: 2
A38: x | B38: Consumables inputs
B39: Printhead life | C39: 4000 | D39: 4000 | E39: 4000 | F39: 4000 | G39: 4000 | H39: 4000 | I39: 4000 | J39: 4000 | K39: 4000 | L39: 2500 | M39: 2500 | N39: 2500 | O39: 2500 | P39: 2500 | Q39: 2500 | R39: layers / L
B40: Wiper cartridge life | C40: 8000 | D40: 8000 | E40: 8000 | F40: 8000 | G40: 8000 | H40: 8000 | I40: 8000 | J40: 8000 | K40: 8000 | L40: 0 | M40: 0 | N40: 0 | O40: 120000 | P40: 0 | Q40: 0 | R40: layers
B41: Binder sponge life | C41: 10 | D41: 10 | E41: 10 | F41: 10 | G41: 10 | H41: 10 | I41: 10 | J41: 10 | K41: 10 | L41: 0 | M41: 0 | N41: 0 | O41: 80000 | P41: 0 | Q41: 0 | R41: L
B42: Cleaner frequency | C42: 0 | D42: 0 | E42: 0 | F42: 0 | G42: 0 | H42: 0 | I42: 0 | J42: 0 | K42: 0 | L42: 0 | M42: 0 | N42: 0 | O42: 1 | P42: 2 | Q42: 1 | R42: layers
B43: Cleaner volume | C43: 0 | D43: 0 | E43: 0 | F43: 0 | G43: 0 | H43: 0 | I43: 0 | J43: 0 | K43: 0 | L43: 0 | M43: 0 | N43: 0 | O43: 0.2 | P43: 11.55 | Q43: 19.6 | R43: mL
A44: x | B44: Turnaround labor inputs
B45: Print turnaround time | C45: 0.5 | D45: 0.5 | E45: 0.5 | F45: 0.5 | G45: 0.5 | H45: 0.5 | I45: 0.5 | J45: 0.5 | K45: 0.5 | L45: 0.5 | M45: 0.5 | N45: 0.5 | O45: 0.25 | P45: 1 | Q45: 2 | R45: hrs
B46: Crosslink turnaround time | C46: 0.5 | D46: 0.5 | E46: 0.5 | F46: 0.5 | G46: 0.5 | H46: 0.5 | I46: 0.5 | J46: 0.5 | K46: 0.5 | L46: 0.5 | M46: 0.5 | N46: 0.5 | O46: 0.5 | P46: 0.5 | Q46: 0.5 | R46: hrs
B47: Depowder turnaround time | C47: 0.5 | D47: 0.5 | E47: 0.5 | F47: 0.5 | G47: 0.5 | H47: 0.5 | I47: 0.5 | J47: 0.5 | K47: 0.5 | L47: 0.5 | M47: 0.5 | N47: 0.5 | O47: 0.5 | P47: 0.5 | Q47: 0.5 | R47: hrs
B48: Powder blender turnaround time | C48: 0.25 | D48: 0.25 | E48: 0.25 | F48: 0.25 | G48: 0.25 | H48: 0.25 | I48: 0.25 | J48: 0.25 | K48: 0.25 | L48: 0.5 | M48: 1 | N48: 0 | O48: 0.25 | P48: 0 | Q48: 0 | R48: hrs
B49: PPU auto turnaround time | C49: 0 | D49: 0 | E49: 0 | F49: 0 | G49: 0 | H49: 0 | I49: 0 | J49: 0 | K49: 0 | L49: 0 | M49: 2 | N49: 0.25 | O49: 0 | P49: 0.25 | Q49: 0.25 | R49: hrs
A50: x | B50: Equipment floorspace
B51: Printer floorspace | C51: =2*0.8+0.56*0.57 -> 1.9192 | D51: =2*0.8+0.56*0.57 -> 1.9192 | E51: =2*0.8+0.56*0.57 -> 1.9192 | F51: =2*0.8+0.56*0.57 -> 1.9192 | G51: =2*0.8+0.56*0.57 -> 1.9192 | H51: =2*0.8+0.56*0.57 -> 1.9192 | I51: =2*0.8+0.56*0.57 -> 1.9192 | J51: =2*0.8+0.56*0.57 -> 1.9192 | K51: =2*0.8+0.56*0.57 -> 1.9192 | L51: 0 | M51: 0 | N51: 0 | O51: 0 | P51: 0 | Q51: 0 | R51: m2
B52: Crosslink floorspace | C52: =1*0.8 -> 0.8 | D52: =1*0.8 -> 0.8 | E52: =1*0.8 -> 0.8 | F52: =1*0.8 -> 0.8 | G52: =1*0.8 -> 0.8 | H52: =1*0.8 -> 0.8 | I52: =1*0.8 -> 0.8 | J52: =1*0.8 -> 0.8 | K52: =1*0.8 -> 0.8 | L52: 0 | M52: 0 | N52: 0 | O52: 0 | P52: 0 | Q52: 0 | R52: m2
B53: Depowder floorspace | C53: =1.6*1+0.56*0.57 -> 1.9192 | D53: =1.6*1+0.56*0.57 -> 1.9192 | E53: =1.6*1+0.56*0.57 -> 1.9192 | F53: =1.6*1+0.56*0.57 -> 1.9192 | G53: =1.6*1+0.56*0.57 -> 1.9192 | H53: =1.6*1+0.56*0.57 -> 1.9192 | I53: =1.6*1+0.56*0.57 -> 1.9192 | J53: =1.6*1+0.56*0.57 -> 1.9192 | K53: =1.6*1+0.56*0.57 -> 1.9192 | L53: 0 | M53: 0 | N53: 0 | O53: 0 | P53: 0 | Q53: 0 | R53: m2
B54: Powder processing floorspace | C54: =0.8*0.8 -> 0.64 | D54: =0.8*0.8 -> 0.64 | E54: =0.8*0.8 -> 0.64 | F54: =0.8*0.8 -> 0.64 | G54: =0.8*0.8 -> 0.64 | H54: =0.8*0.8 -> 0.64 | I54: =0.8*0.8 -> 0.64 | J54: =0.8*0.8 -> 0.64 | K54: =0.8*0.8 -> 0.64 | L54: 0 | M54: 0 | N54: 0 | O54: 0 | P54: 0 | Q54: 0 | R54: m2
A55: x | B55: Equipment power
B56: Printer power | C56: 5 | D56: 5 | E56: 5 | F56: 5 | G56: 5 | H56: 5 | I56: 5 | J56: 5 | K56: 5 | L56: 9 | M56: 13 | N56: 13 | O56: 1.9 | P56: 4.5 | Q56: 20 | R56: kW
B57: Crosslink power | C57: 2.97 | D57: 2.97 | E57: 2.97 | F57: 2.97 | G57: 2.97 | H57: 2.97 | I57: 2.97 | J57: 2.97 | K57: 2.97 | L57: 5 | M57: 5 | N57: 5 | O57: 1.5 | P57: 11 | Q57: 45 | R57: kW
B58: Depowder power | C58: 0.34 | D58: 0.34 | E58: 0.34 | F58: 0.34 | G58: 0.34 | H58: 0.34 | I58: 0.34 | J58: 0.34 | K58: 0.34 | L58: 5 | M58: 5 | N58: 5 | O58: 0 | P58: 1 | Q58: 1.4 | R58: kW
B59: Powder processing power | C59: 0.66 | D59: 0.66 | E59: 0.66 | F59: 0.66 | G59: 0.66 | H59: 0.66 | I59: 0.66 | J59: 0.66 | K59: 0.66 | L59: 0.66 | M59: 50 | N59: 50 | O59: 0 | P59: 1 | Q59: 15 | R59: kW
A60: x | B60: Equipment MSRPs
B61: Printer MSRP | C61: =189000+7995 -> 196995 | D61: =C61+25000 -> 221995 | E61: =C61+50000 -> 246995 | F61: =C61+60000 -> 256995 | G61: =F61+25000 -> 281995 | H61: =G61+25000 -> 306995 | I61: =C61+110000 -> 306995 | J61: =I61+25000 -> 331995 | K61: =I61+50000 -> 356995 | L61: 471500 | M61: 1095000 | N61: =M61 -> 1095000 | O61: =246750+4335 -> 251085 | P61: =530145+5775+P75 -> 570570 | Q61: =924000+23100+Q76 -> 1033725
B62: Kegs MSRP | C62: =1065*6 -> 6390 | D62: =C62 -> 6390 | E62: =D62 -> 6390 | F62: =E62 -> 6390 | G62: =F62 -> 6390 | H62: =G62 -> 6390 | I62: =H62 -> 6390 | J62: =I62 -> 6390 | K62: =J62 -> 6390 | L62: 0 | M62: 0 | N62: 0 | O62: 0 | P62: 0 | Q62: 0
B63: Crosslink MSRP | C63: 23540 | D63: =C63 -> 23540 | E63: =D63 -> 23540 | F63: =E63 -> 23540 | G63: =F63 -> 23540 | H63: =G63 -> 23540 | I63: =H63 -> 23540 | J63: =I63 -> 23540 | K63: =J63 -> 23540 | L63: 20000 | M63: 55000 | N63: =M63 -> 55000 | O63: 2760 | P63: 20790 | Q63: 231000
B64: Crosslink module MSRP | C64: 0 | D64: 0 | E64: 0 | F64: 0 | G64: 0 | H64: 0 | L64: 0 | M64: 0 | N64: 40000 | O64: 0 | P64: 0 | Q64: 0 | S64: cost $429 ea oven - watlow P/N PM6R1CJ-BAAAPWP
B65: Depowder station MSRP | C65: 35845 | D65: =C65 -> 35845 | E65: =D65 -> 35845 | F65: =E65 -> 35845 | G65: =F65 -> 35845 | H65: =G65 -> 35845 | I65: =H65 -> 35845 | J65: =I65 -> 35845 | K65: =J65 -> 35845 | L65: 120000 | M65: 200000 | N65: =M65 -> 200000 | O65: 12735 | P65: 38695 | Q65: 115500
B66: Powder processing MSRP | C66: 9795 | D66: =C66 -> 9795 | E66: =D66 -> 9795 | F66: =E66 -> 9795 | G66: =F66 -> 9795 | H66: =G66 -> 9795 | I66: =H66 -> 9795 | J66: =I66 -> 9795 | K66: =J66 -> 9795 | L66: =9795+1065 -> 10860 | M66: 400000 | N66: =M66 -> 400000 | O66: 0 | P66: 167525 | Q66: 404250
B67: DM Furnace MSRP | C67: =IF(Universal!printer_index<13,IF(Universal!furnace_sel="DM PureSinter",210000,125000),"") -> 210000 | D67: =IF(Universal!printer_index<13,IF(Universal!furnace_sel="DM PureSinter",210000,125000),"") -> 210000 | E67: =IF(Universal!printer_index<13,IF(Universal!furnace_sel="DM PureSinter",210000,125000),"") -> 210000 | F67: =IF(Universal!printer_index<13,IF(Universal!furnace_sel="DM PureSinter",210000,125000),"") -> 210000 | G67: =IF(Universal!printer_index<13,IF(Universal!furnace_sel="DM PureSinter",210000,125000),"") -> 210000 | H67: =IF(Universal!printer_index<13,IF(Universal!furnace_sel="DM PureSinter",210000,125000),"") -> 210000 | I67: =IF(Universal!printer_index<13,IF(Universal!furnace_sel="DM PureSinter",210000,125000),"") -> 210000 | J67: =IF(Universal!printer_index<13,IF(Universal!furnace_sel="DM PureSinter",210000,125000),"") -> 210000 | ... Q67: =IF(Universal!printer_index<13,IF(Universal!furnace_sel="DM PureSinter",210000,125000),"") -> 210000
B68: DM vacuum MSRP | C68: 7995 | D68: =C68 -> 7995 | E68: =D68 -> 7995 | F68: =E68 -> 7995 | G68: =F68 -> 7995 | H68: =G68 -> 7995 | I68: =H68 -> 7995 | J68: =I68 -> 7995 | K68: =J68 -> 7995 | L68: 0 | M68: 0 | N68: 0 | O68: 5380 | P68: 5380 | Q68: 0
B69: Transfer cart MSRP | C69: 8995 | D69: 8995 | E69: 8995 | F69: 8995 | G69: 8995 | H69: 8995 | I69: 8995 | J69: 8995 | K69: 8995 | L69: 0 | M69: 27500 | N69: =M69 -> 27500 | O69: 0 | P69: 40425 | Q69: 86625
B70: Build box MSRP | C70: 1600 | D70: =C70 -> 1600 | E70: =D70 -> 1600 | F70: =E70 -> 1600 | G70: =F70 -> 1600 | H70: =G70 -> 1600 | I70: =H70 -> 1600 | J70: =I70 -> 1600 | K70: =J70 -> 1600 | L70: 4140 | M70: 25000 | N70: =M70 -> 25000 | O70: 1575 | P70: 11550 | Q70: 28875
A71: x | B71: Consumable MSRPs
B72: Binder MSRP | C72: 300 | D72: 300 | E72: 300 | F72: 150 | G72: 150 | H72: 150 | I72: 150 | J72: 150 | K72: 150 | L72: 200 | M72: 200 | N72: 200 | O72: 150 | P72: 150 | Q72: 150
B73: Binder Tier 2 MSRP | L73: 150 | M73: 150 | N73: 150 | O73: 125 | P73: 125 | Q73: 125
B74: Binder Tier 3 MSRP | L74: 100 | M74: 100 | N74: 100 | O74: 100 | P74: 100 | Q74: 100
B75: Printheads MSRP | C75: 695 | D75: 695 | E75: 695 | F75: 695 | G75: 695 | H75: 695 | I75: 695 | J75: 695 | K75: 695 | L75: =6615*2 -> 13230 | M75: =6000*8 -> 48000 | N75: =6000*8 -> 48000 | O75: 7615 | P75: 34650
B76: Wiper cartridge MSRP | C76: 231 | D76: 231 | E76: 231 | F76: 231 | G76: 231 | H76: 231 | I76: 231 | J76: 231 | K76: 231 | Q76: 86625
B77: Binder sponge MSRP | C77: 81 | D77: 81 | E77: 81 | F77: 81 | G77: 81 | H77: 81 | I77: 81 | J77: 81 | K77: 81
B78: Binder MSRP | C78: =C72 -> 300 | D78: =D72 -> 300 | E78: =E72 -> 300 | F78: =F72 -> 150 | G78: =G72 -> 150 | H78: =H72 -> 150 | I78: =I72 -> 150 | J78: =J72 -> 150 | ... Q78: =Q72 -> 150
B79: Cleaner MSRP | O79: 3.6 | P79: 3.6 | Q79: 3.6
A80: x | B80: Material MSRPs ($/kg)
B81: 420 | L81: 22 | M81: 22 | N81: 22
B82: 4140 | L82: 29.5 | M82: 29.5 | N82: 29.5 | O82: 29.5 | P82: 29.5 | Q82: 29.5
B83: 17-4PH | C83: 50 | D83: 50 | E83: 50 | F83: 78 | G83: 78 | H83: 78 | I83: 40 | J83: 40 | K83: 40 | L83: 50 | M83: 50 | N83: 50 | O83: 34.65 | P83: 34.65 | Q83: 34.65
B84: DM HH Stainless | L84: 34 | M84: 34 | N84: 34
B85: 304L | C85: 99 | D85: 99 | E85: 99 | F85: =C85*0.7 -> 69.3 | G85: =D85*0.7 -> 69.3 | H85: =E85*0.7 -> 69.3 | I85: =C85*0.7 -> 69.3 | J85: =D85*0.7 -> 69.3 | K85: =E85*0.7 -> 69.3 | O85: 27 | P85: 27 | Q85: 27
B86: 316L | C86: 50 | D86: 50 | E86: 50 | F86: 78 | G86: 78 | H86: 78 | I86: 40 | J86: 40 | K86: 40 | L86: 88 | M86: 88 | N86: 88 | O86: 34.65 | P86: 34.65 | Q86: 34.65
B87: 440C | L87: 34 | M87: 34 | N87: 34
B88: CrMnMoN | L88: 56 | M88: 56 | N88: 56
B89: Al 6061 | L89: 78 | M89: 78 | N89: 78 | O89: 78 | P89: 78 | Q89: 78
B90: CoCrMo | C90: 325 | D90: 325 | E90: 325 | F90: =C90*0.7 -> 227.5 | G90: =D90*0.7 -> 227.5 | H90: =E90*0.7 -> 227.5 | I90: =C90*0.7 -> 227.5 | J90: =D90*0.7 -> 227.5 | K90: =E90*0.7 -> 227.5 | P90: 105 | Q90: 105
B91: Cu | L91: 57 | M91: 57 | N91: 57 | O91: 47 | P91: 47 | Q91: 47
B92: D2 | L92: 26.6 | M92: 26.6 | N92: 26.6
B93: Gold | I93: 58407 | J93: 58407 | K93: 58407 | L93: 58407 | M93: 58407 | N93: 58407 | O93: 58407 | P93: 58407 | Q93: 58407
B94: H13 | L94: 80 | M94: 80 | N94: 80 | O94: 80 | P94: 80 | Q94: 80
B95: IN625 | C95: 299 | D95: 299 | E95: 299 | F95: =C95*0.7 -> 209.3 | G95: =D95*0.7 -> 209.3 | H95: =E95*0.7 -> 209.3 | I95: =C95*0.7 -> 209.3 | J95: =D95*0.7 -> 209.3 | K95: =E95*0.7 -> 209.3 | L95: 145 | M95: 145 | N95: 145 | O95: 145 | P95: 145 | Q95: 145
B96: IN718 | C96: 249 | D96: 249 | E96: 249 | F96: =C96*0.7 -> 174.3 | G96: =D96*0.7 -> 174.3 | H96: =E96*0.7 -> 174.3 | I96: =C96*0.7 -> 174.3 | J96: =D96*0.7 -> 174.3 | K96: =E96*0.7 -> 174.3 | L96: 145 | M96: 145 | N96: 145 | O96: 145 | P96: 145 | Q96: 145
B97: M2 | O97: 20 | P97: 20 | Q97: 20
B98: S7 | L98: 100 | M98: 100 | N98: 100
B99: Silver | L99: 1084 | M99: 1084 | N99: 1084 | O99: 1084 | P99: 1084 | Q99: 1084
B100: Ti-64 | L100: 363 | M100: 363 | N100: 363 | O100: 363 | P100: 363 | Q100: 363
B101: WC-12Co | L101: 36 | M101: 36 | N101: 36 | O101: 36 | P101: 36 | Q101: 36
...

Sheet Universal
A2: x | B2: =MID(CELL("filename",A1),SEARCH("[",CELL("filename",A1))+1,LEN(CELL("filename",A1))-SEARCH("[",CELL("filename",A1))-15) -> #VALUE! | F2: =IF(Universal!printer_index<10,"SHOP SYSTEM",IF(Universal!printer_index<13,"PRODUCTION SYSTEM","X-SERIES")) -> SHOP SYSTEM | K2: Privileged & DM Confidential | M2: x | N2: =Universal!printer_sel&" part cost outputs with depreciation" -> Shop_12L part cost outputs with depreciation | AD2: x | AE2: =Universal!printer_sel&" part cost outputs without depreciation" -> Shop_12L part cost outputs without depreciation
N3: Printer & aux MSRP | P3: =G20+G35+G47+K34 -> 345955 | R3: ="Printed parts / build" -> Printed parts / build | T3: =Universal!parts_job -> 135 | AE3: Printer & aux MSRP | AG3: =G20+G35+G47+K34 -> 345955 | AI3: ="Printed parts / build" -> Printed parts / build | AK3: =Universal!parts_job -> 135
A4: x | B4: Part inputs (pre-scaling) | E4: x | F4: Printer usage calculation | I4: x | J4: Furnace part cost calculation | N4: Furnace MSRP | P4: =K17 -> 210000 | R4: Part nesting density | T4: =G17 -> 0.51568461 | AE4: Furnace MSRP | AG4: =K17 -> 210000 | AI4: Part nesting density | AK4: =G17 -> 0.51568461
B5: X-dim (incl. supports) | C5: 30 | D5: mm | F5: Powder volume / part | G5: =Universal!part_vol_scale*Universal!bed_density -> 18760.866 | H5: mm3 | J5: Furnace selection | K5: =Universal!furnace_sel -> DM PureSinter | N5: Total equipment MSRP | P5: =SUM(P3:P4) -> 555955 | AE5: Total equipment MSRP | AG5: =SUM(AG3:AG4) -> 555955
B6: Y-dim (incl. supports) | C6: 30 | D6: mm | F6: Powder mass / part | G6: =G5*Universal!density_selected*10^3 -> 145.2091 | H6: g | J6: Furnace X-dim | K6: =Universal!furnace_x_dim -> 244 | L6: mm | N6: =Universal!printer_sel&" printers req." -> Shop_12L printers req. | P6: =G11 -> 1 | R6: Printer builds / week | T6: =T8/Universal!weeks_yr -> 3.2921811 | AE6: =Universal!printer_sel&" printers req." -> Shop_12L printers req. | AG6: =G11 -> 1 | AI6: Printer builds / week | AK6: =AK8/Universal!weeks_yr -> 3.2921811
B7: Z-dim (incl. supports) | C7: 30 | D7: mm | F7: Powder mass / build | G7: =(G6*Universal!parts_job)/10^3+((Universal!build_vol*Universal!bed_density*Universal!density_selected*Universal!powder_ratio)-(G6*Universal!parts_job)/1000)*Universal!powder_loss_percentage -> 19.847338 | H7: kg | J7: Furnace Y-dim | K7: =Universal!furnace_y_dim -> 270 | L7: mm | N7: Furnaces req. | P7: =K15 -> 1 | R7: Printer builds / month | T7: =T6*4 -> 13.168724 | AE7: Furnaces req. | AG7: =K15 -> 1 | AI7: Printer builds / month | AK7: =T6*4 -> 13.168724
B8: Part volume | C8: 20208.8 | D8: mm3 | F8: Binder volume / part | G8: =Universal!part_vol_scale*(1-Universal!bed_density)*Universal!binder_void_ratio -> 10050.464 | H8: mm3 | J8: Furnace Z-dim | K8: =Universal!furnace_z_dim -> 265 | L8: mm | R8: Printer builds / year | T8: =Universal!total_builds_yr -> 164.60905 | AI8: Printer builds / year | AK8: =Universal!total_builds_yr -> 164.60905
B9: Support volume | C9: =IF(Universal!printer_index<13,"0",IF(C14="TurboFuse",(Universal!part_scale_x*Universal!part_scale_y),"0")) -> 0 | D9: mm3 | F9: Binder volume / build | G9: =IF(Universal!printer_index<12,((Universal!parts_job*G8)/10^6)+((Universal!binder_purge_vol*(Universal!build_layers/Universal!binder_purge_freq))/10^3),(G8*Universal!parts_job/10^6+(Universal!build_layers/Universal!binder_purge_freq+2)*Universal!binder_purge_vol/10^3-IF(VLOOKUP(Inputs!$B$20,Inputs!$B:$Q,Universal!printer_index+1,0)="No",((C20-1)*Universal!printer_z_spacing+Universal!printer_z_base)/Universal!layer_thickness_sel/Universal!binder_purge_freq*Universal!binder_purge_vol/10^3,0))) -> 1.4992189 | H9: L | J9: Furnace parts / run | K9: =IF(Universal!furnace_sel="Continuous",Universal!part_req,ROUNDDOWN((Universal!furnace_x_dim+Universal!furnace_xy_spacing)/(Universal!furnace_part_scale_x+Universal!furnace_xy_spacing),0)*ROUNDDOWN((Universal!furnace_y_dim+Universal!furnace_xy_spacing)/(Universal!furnace_part_scale_y+Universal!furnace_xy_spacing),0)*MIN(Universal!furnace_shelves,ROUNDDOWN(Universal!furnace_z_dim/(Universal!furnace_part_scale_z+Universal!furnace_rack_thickness+Universal!furnace_z_spacing),0))) -> 216 | N9: Operating (i.e. "running") part costs
B10: Part + support volume | C10: =Universal!part_only_vol+Universal!support_vol -> 20208.8 | D10: mm3 | F10: Cleaner volume / build | G10: =IF(Universal!printer_index<13,"",(Universal!build_layers/Universal!cleaner_freq)*Universal!cleaner_cycle_vol/10^3) | H10: L | J10: Furnace loading parts / hour | K10: =C58 -> 500 | N10: Printed part cost | P10: =P32+P33+P35+P36 -> 14.641018 | R10: =IF($C$15="Yes","Sintered","Green")&" parts / week" -> Sintered parts / week | T10: =T12/Universal!weeks_yr -> 400 | AI10: =IF($C$15="Yes","Sintered","Green")&" parts / week" -> Sintered parts / week | AK10: =T12/Universal!weeks_yr -> 400
F11: Printers required (rounded) | G11: =ROUNDUP(Universal!part_req/Universal!part_capacity,0) -> 1 | J11: Run time + turnaround | K11: =Universal!furnace_time_cycle+K9/K10*2 -> 23.864 | L11: hrs | N11: =IF(C15="Yes","Sintered","Green")&" part cost" -> Sintered part cost | P11: =T38-T34-T37 -> 17.324828 | R11: =IF($C$15="Yes","Sintered","Green")&" parts / month" -> Sintered parts / month | T11: =T10*4 -> 1600 | AE11: Operating (i.e. "running") part costs | AI11: =IF($C$15="Yes","Sintered","Green")&" parts / month" -> Sintered parts / month | AK11: =T10*4 -> 1600
A12: x | B12: Build inputs & process capacity | F12: Printer utilization | G12: =Universal!part_req/Universal!good_parts_job*Universal!print_time_trn -> 1888.1573 | H12: hrs | J12: Time per printer build | K12: =IFERROR(Universal!good_parts_job/K9*K11,"N.A.") -> 13.4235 | L12: hrs | N12: =N10&" / cc" -> Printed part cost / cc | P12: =P10/Universal!part_only_vol*10^3 -> 0.72448724 | R12: =IF($C$15="Yes","Sintered","Green")&" parts / year" -> Sintered parts / year | T12: =Universal!part_req -> 20000 | AE12: Printed part cost | AG12: =P32+P33+P35+P36 -> 14.641018 | AI12: =IF($C$15="Yes","Sintered","Green")&" parts / year" -> Sintered parts / year | AK12: =Universal!part_req -> 20000
B13: Printer model | C13: Shop_12L | F13: Builds / year | G13: =Universal!part_req/Universal!good_parts_job -> 164.60905 | J13: Build capacity / year | K13: =IF(Universal!furnace_sel="Continuous",(240000/2.2)/(Universal!good_parts_job*Universal!part_vol*Universal!density_selected),ROUNDDOWN(Universal!total_hours_yr/K12,0)) -> 625 | N13: =N11&" / cc" -> Sintered part cost / cc | P13: =P11/Universal!part_only_vol*10^3 -> 0.85729126 | AE13: =IF(C15="Yes","Sintered","Green")&" part cost" -> Sintered part cost | AG13: =T38-T34-T37 -> 17.324828
B14: Binder Used | F14: Builds / month | G14: =G13/12 -> 13.717421 | J14: Runs / year | K14: =IFERROR(ROUNDUP(Universal!part_req/K9,0),"N.A.") -> 93 | R14: ="Printer util (QTY: "&G11&")" -> Printer util (QTY: 1) | T14: =G15 -> 0.33717095 | AE14: =AE12&" / cc" -> Printed part cost / cc | AG14: =AG12/Universal!part_only_vol*10^3 -> 0.72448724 | AI14: ="Printer util (QTY: "&X11&")" -> Printer util (QTY: ) | AK14: =G15 -> 0.33717095
B15: Include sintering? | C15: Yes | F15: Printer utilization (% of available) | G15: =G12/(Universal!avail_hours_yr*Universal!printers_req) -> 0.33717095 | J15: Furnaces required (rounded) | K15: =IFERROR(ROUNDUP(Universal!total_builds_yr/K13,0),"N.A.") -> 1 | N15: Burdened (i.e. "depreciated") part costs | R15: ="Oven util (QTY: "&G33&")" -> Oven util (QTY: 1) | T15: =G34/(G33*Universal!total_hours_yr) -> 0.19834085 | AE15: =AE13&" / cc" -> Sintered part cost / cc | AG15: =AG13/Universal!part_only_vol*10^3 -> 0.85729126 | AI15: ="Oven util (QTY: "&X33&")" -> Oven util (QTY: ) | AK15: =G34/(G33*Universal!total_hours_yr) -> 0.19834085
B16: Furnace selection | C16: DM PureSinter | D16: =IF(OR(Universal!furnace_sel="DM",Universal!furnace_sel="Continuous"),,"ft3") -> ft3 | F16: Printer utilization (% 24x7) | G16: =G12/(Universal!total_hours_yr*Universal!printers_req) -> 0.22478063 | J16: Furnace utilization | K16: =IFERROR(K11*K14,"N.A.") -> 2219.352 | L16: hrs | N16: Printed part cost | P16: =SUM(P32:P36) -> 15.293515 | R16: ="Depowder util (QTY: "&G45&")" -> Depowder util (QTY: 1) | T16: =G46/(G45*Universal!uptime_hours_yr) -> 0.1010435 | AI16: ="Depowder util (QTY: "&X45&")" -> Depowder util (QTY: ) | AK16: =G46/(G45*Universal!uptime_hours_yr) -> 0.1010435
B17: Debind + Sinter | C17: Integrated | F17: Build box nesting density | G17: =Universal!part_vol_scale*Universal!parts_job/Universal!build_vol -> 0.51568461 | J17: Furnace investment | K17: =IF(C15="No",0,Universal!furnace_msrp*K15) -> 210000 | N17: =IF(C15="Yes","Sintered","Green")&" part cost" -> Sintered part cost | P17: =T46 -> 18.464743 | R17: ="Furnace util (QTY: "&IF(Universal!furnace_sel="DM",K15,K15)&")" -> Furnace util (QTY: 1) | T17: =K16/(Universal!total_hours_yr*K15) -> 0.26420857 | AI17: ="Furnace util (QTY: "&IF(Universal!furnace_sel="DM",AB15,AB15)&")" -> Furnace util (QTY: ) | AK17: =K16/(Universal!total_hours_yr*K15) -> 0.26420857
B18: Limit furnace to QTY 1 | C18: No | J18: ="Annual depreciation (@ "&Universal!furnace_depr&" yrs)" -> Annual depreciation (@ 7 yrs) | K18: =K17/Universal!furnace_depr+Universal!floor_rate*K15*Universal!furnace_floorspace -> 30152 | N18: Printed part cost / cc | P18: =P16/Universal!part_only_vol*10^3 -> 0.756775
B19: Calculated nested parts / job | C19: =ROUNDDOWN((Universal!build_x-Universal!printer_xy_border*2+Universal!printer_xy_spacing)/(Universal!part_scale_x+Universal!printer_xy_spacing),0)*ROUNDDOWN((Universal!build_y-Universal!printer_xy_border*2+Universal!printer_xy_spacing)/(Universal!part_scale_y+Universal!printer_xy_spacing),0)*ROUNDDOWN((Universal!build_z-Universal!printer_z_base+Universal!printer_z_spacing)/(Universal!part_scale_z+Universal!printer_z_spacing),0) -> 135 | E19: x | F19: Printer part cost calculation | J19: Depreciation / part | K19: =K18*K16/(Universal!total_hours_yr*K15)/Universal!part_req -> 0.39832084 | N19: =IF(C15="Yes","Sintered","Green")&" part cost / cc" -> Sintered part cost / cc | P19: =P17/Universal!part_only_vol*10^3 -> 0.91369814 | R19: Labor hrs / year | T19: =Universal!total_builds_yr*(Universal!print_trnaround+Universal!xlink_trnaround+G43+IF(Universal!ppu_auto_on,Universal!ppu_auto_trnaround,K26/K27*Universal!powder_trnaround))+K14*K9/K10*2 -> 742.06013 | AI19: Labor hrs / year | AK19: =Universal!total_builds_yr*(Universal!print_trnaround+Universal!xlink_trnaround+G43+IF(Universal!ppu_auto_on,Universal!ppu_auto_trnaround,K26/K27*Universal!powder_trnaround))+K14*K9/K10*2 -> 742.06013
B20: Calculated build height | C20: =Universal!printer_z_base+(Universal!part_scale_z)*ROUNDDOWN((Universal!build_z-Universal!printer_z_base+Universal!printer_z_spacing)/(Universal!part_scale_z+Universal!printer_z_spacing),0)+Universal!printer_z_spacing*(ROUNDDOWN((Universal!build_z-Universal!printer_z_base+Universal!printer_z_spacing)/(Universal!part_scale_z+Universal!printer_z_spacing),0)-1) -> 113.9 | D20: mm | F20: Printer investment (incl. build box) | G20: =(Universal!printer_msrp+kegs_msrp)*Universal!printers_req+Universal!buildbox_msrp*build_box_qty+Universal!transfer_cart_msrp -> 268780 | J20: Consumables / part | K20: =Universal!furnace_consumables_run/K9 -> 0.27777778 | N20: Notes & assumptions: | AE20: Notes & assumptions:
B21: Calculated part layers | C21: =ROUNDDOWN((Universal!build_z-Universal!printer_z_base+Universal!printer_z_spacing)/(Universal!part_scale_z+Universal!printer_z_spacing),0) -> 3 | F21: ="Annual depreciation (@ "&Universal!dm_depr&" yrs)" -> Annual depreciation (@ 7 yrs) | G21: =G20/Universal!dm_depr+Universal!floor_rate*Universal!printers_req*Universal!printer_floorspace -> 38704.215 | J21: Labor $ / part | K21: =IF(C15="No",0,Universal!labor_rate*(K9/K10*2)/K9) -> 0.08 | N21: 1. Pricing is not final unless on an official DM quote and is subject to change. Does not include installation, training, shipping, or taxes. | AE21: 1. Pricing is not final unless on an official DM quote and is subject to change. Does not include installation, training, shipping, or taxes.
B22: Override nesting | C22: No | F22: Powder $ / part | G22: =IF(C46<>"",C46,Universal!powder_price)*G7/Universal!good_parts_job -> 8.167629 | J22: Utilities / part | K22: =IF(Universal!furnace_sel="Continuous",Universal!furnace_utilities_hr*Universal!total_hours_yr/Universal!part_req,IF(Universal!furnace_sel="DM",(Universal!furnace_power_cons*Universal!power_rate*Universal!furnace_time_cycle+Universal!forming_gas_rate*Universal!furnace_gas_cons)/K9,(Universal!argon_rate*Universal!furnace_gas_cons+Universal!power_rate*Universal!furnace_power_cons)*Universal!furnace_time_cycle/K9)) -> 1.7590741 | N22: ="2. DM Equipment MSRP includes printer build boxes ("&MAX(2*G11,G33*G30+ROUNDUP(G31/Universal!print_time_trn,0))&"x), powder kegs, and transfer cart." -> 2. DM Equipment MSRP includes printer build boxes (4x), powder kegs, and transfer cart. | AE22: ="2. DM Equipment MSRP includes printer build boxes ("&MAX(2*X11,X33*X30+ROUNDUP(X31/Universal!print_time_trn,0))&"x), powder kegs, and transfer cart." -> 2. DM Equipment MSRP includes printer build boxes (0x), powder kegs, and transfer cart.
B23: Override parts / job | C23: 2578 | F23: Binder $ / part | G23: =Universal!binder_price*G9/Universal!good_parts_job -> 3.701775 | N23: 3. Consumables includes printer items (e.g. printheads, wiper cartridges, etc.) and, if applicable, Desktop Metal Furnace items (e.g. setter plates, shelving, oil, liners, etc.). | AE23: 3. Consumables includes printer items (e.g. printheads, wiper cartridges, etc.) and, if applicable, Desktop Metal Furnace items (e.g. setter plates, shelving, oil, liners, etc.).
B24: Override build height | C24: 125 | D24: mm | F24: Depreciation $ / part | G24: =G21*G12/(Universal!avail_hours_yr*Universal!printers_req)/Universal!part_req -> 0.65249684 | I24: x | J24: Powder processing part cost calculation | N24: 4. Includes utilities costs for gas (as required), electricity, and floorspace. | AE24: ="5. "&T43&" powder at "&TEXT(IF($C$46="",Universal!powder_price,$C$46),"$0.00")&"/kg and binder at "&TEXT(Universal!binder_price,"$0.00")&"/L. Volume pricing may be available." -> 5. 0.480075345595028 powder at $50.00/kg and binder at $300.00/L. Volume pricing may be available.
B25: Override part layers | C25: 8 | F25: Consumables $ / part | G25: =IF(Universal!printer_index<14,Universal!printhead_msrp*Universal!build_layers/Universal!printhead_life+Universal!wiper_msrp*Universal!build_layers/Universal!wiper_life+Universal!sponge_msrp*G9/Universal!sponge_life,Universal!printhead_msrp*G9/Universal!printhead_life+IF(Universal!printer_index>=14,Universal!cleaner_msrp*G10))/Universal!good_parts_job -> 2.6331773 | J25: PPU auto? | K25: =IF(C104<>0,TRUE,FALSE) -> FALSE | N25: ="5. "&C45&" powder at "&TEXT(IF($C$46="",Universal!powder_price,$C$46),"$0.00")&"/kg and "&C14&" binder at "&TEXT(Universal!binder_price,"$0.00")&"/L. Volume pricing may be available." -> 5. 17-4PH powder at $50.00/kg and binder at $300.00/L. Volume pricing may be available. | AE25: ="6. Key process assumptions: (i) "&T24*1000&" micron printed layer height; (ii) $"&Universal!labor_rate&"/hr labor rate; (iii) Printer, depowdering, and powder handling equipment @ "&T32&" x "&T33&" x "&Universal!weeks_yr&" x "&Universal!uptime*100&"% uptime" -> 6. Key process assumptions: (i) 0 micron printed layer height; (ii) $20/hr labor rate; (iii) Printer, depowdering, and powder handling equipment @ 11.8694039397328 x 2.91095512588277 x 50 x 80% uptime
B26: Layer thickness | C26: 0.075 | D26: mm | F26: Labor $ / part | G26: =Universal!print_trnaround*Universal!labor_rate/Universal!good_parts_job -> 0.082304527 | J26: Loose powder / build | K26: =(Universal!build_vol*Universal!bed_density*Universal!powder_ratio*Universal!density_selected-G7) -> 48.577841 | L26: kg | N26: ="6. Key process assumptions: (i) "&C26*1000&" micron printed layer height; (ii) $"&Universal!labor_rate&"/hr labor rate; (iii) Printer, depowdering, and powder handling equipment @ "&C34&" x "&C35&" x "&Universal!weeks_yr&" x "&Universal!uptime*100&"% uptime" -> 6. Key process assumptions: (i) 75 micron printed layer height; (ii) $20/hr labor rate; (iii) Printer, depowdering, and powder handling equipment @ 16 x 7 x 50 x 80% uptime | AF26: =" (iv) "&X41&" parts/hr depowdering rate; (v) "&Universal!total_yield*100&"% overall process yield; (vi) "&Universal!dm_depr&"yr DM equipment depreciation;" -> (iv) parts/hr depowdering rate; (v) 90% overall process yield; (vi) 7yr DM equipment depreciation;
B27: Layer thickness default | C27: =VLOOKUP("Default",$B$217:$C$251,2,0) -> 0.075 | D27: mm | F27: Utilities $ / part | G27: =(Universal!power_rate*Universal!printer_pwr*(Universal!print_time_trn-Universal!print_trnaround))*Universal!printers_req/Universal!good_parts_job+(Universal!floor_rate*Universal!printer_floorspace*Universal!printers_req/Universal!part_capacity) -> 0.056131891 | J27: Powder blender capacity | K27: =IF(NOT(Universal!ppu_auto_on),C103,"N.A.") -> 45 | L27: kg | O27: =" (iv) "&G42&" parts/hr depowdering rate; (v) "&Universal!total_yield*100&"% overall process yield; (vi) "&Universal!dm_depr&"yr DM equipment depreciation;" -> (iv) 60 parts/hr depowdering rate; (v) 90% overall process yield; (vi) 7yr DM equipment depreciation; | AF27: =" (vii) Drying oven "&IF(T13="Yes","& sintering ",)&"equipment @ 24 x 7 x "&Universal!weeks_yr&" x "&Universal!uptime*100&"% uptime; (viii) "&IF(T13="Yes",Universal!furnace_depr&"yr MIM furnace depreciation; (iv) ",)&Universal!total_yield*100&"% overall process yield" -> (vii) Drying oven equipment @ 24 x 7 x 50 x 80% uptime; (viii) 90% overall process yield
B28: Printed layers | C28: =ROUNDUP(Universal!build_height/Universal!layer_thickness_sel,0) -> 1519 | J28: ="Blend time + "&Universal!powder_trnaround&"hrs turnaround" -> Blend time + 0.25hrs turnaround | K28: =IF(NOT(Universal!ppu_auto_on),Universal!print_time_trn+Universal!powder_trnaround,"N.A.") -> 11.720556 | L28: hrs | O28: =" (vii) Drying oven "&IF(C15="Yes","& sintering ",)&"equipment @ 24 x 7 x "&Universal!weeks_yr&" x "&Universal!uptime*100&"% uptime; (viii) "&IF(C15="Yes",Universal!furnace_depr&"yr MIM furnace depreciation; (iv) ",)&Universal!total_yield*100&"% overall process yield" -> (vii) Drying oven & sintering equipment @ 24 x 7 x 50 x 80% uptime; (viii) 7yr MIM furnace depreciation; (iv) 90% overall process yield
B29: ="Print time + "&Universal!print_trnaround&"hrs turnaround" -> Print time + 0.5hrs turnaround | C29: =C28*Universal!layer_speed/(60*60)+Universal!print_trnaround -> 11.470556 | D29: hrs | E29: x | F29: Drying oven part cost calculation | J29: Powder capacity / year | K29: =IF(NOT(Universal!ppu_auto_on),K27*Universal!uptime_hours_yr/K28,"N.A.") -> 17200.55 | L29: kg
B30: Overall process yield | C30: 0.9 | F30: Printer builds / oven run | G30: =VLOOKUP($F$30,Inputs!$B:$Q,Universal!printer_index+1,0) -> 2 | J30: Blenders required (rounded) | K30: =IF(NOT(Universal!ppu_auto_on),ROUNDUP(Universal!total_builds_yr*K26/K29,0),"N.A.") -> 1
B31: Good parts / job | C31: =IF(Universal!override_nesting="Yes",IF(C23=0,C19,C23),C19)*C30 -> 121.5 | F31: ="Dry time + "&Universal!xlink_trnaround&"hrs turnaround" -> Dry time + 0.5hrs turnaround | G31: =C101*Universal!build_height/Universal!build_z+Universal!xlink_trnaround -> 20.242667 | H31: hrs | J31: Powder blender utilization (hrs) | K31: =IF(NOT(Universal!ppu_auto_on),Universal!total_builds_yr*K26/K27*K28,"N.A.") -> 2082.7043 | L31: hrs | N31: =Universal!printer_sel&" "&LOWER(N11)&" allocation" -> Shop_12L sintered part cost allocation | V31: Cost model template output | AE31: =Universal!printer_sel&" "&LOWER(AE13)&" allocation" -> Shop_12L sintered part cost allocation | AM31: Cost model template output
A32: x | F32: Build capacity / year | G32: =ROUNDDOWN(G30*Universal!total_hours_yr/G31,0) -> 829 | J32: PPU autos required (rounded) | K32: =IFERROR(MAX(ROUNDUP(G11/C104,0),ROUNDUP(G45/C105,0)),"N.A. ") -> N.A. | N32: Printer | O32: Raw materials | P32: =G22+G23 -> 11.869404 | R32: Total | S32: Raw Materials | T32: =SUMIF($O$32:$O$50,S32,$P$32:$P$50) -> 11.869404 | V32: Parts per build | Y32: =Universal!parts_job -> 135 | AE32: Printer | AF32: Raw materials | AG32: =G22+G23 -> 11.869404 | AI32: Total | AJ32: Raw Materials | AK32: =SUMIF($O$32:$O$50,S32,$P$32:$P$50) -> 11.869404 | AM32: Parts per build | AP32: =Universal!parts_job -> 135
B33: Printer operations inputs | F33: Ovens required (rounded) | G33: =ROUNDUP(Universal!total_builds_yr/G32,0) -> 1 | J33: PPU utilization (hrs) | K33: =IFERROR(ROUNDUP(MAX(G12/G11,G46/G45)*K32,0),"N.A. ") -> N.A. | L33: hrs | N33: Printer | O33: Consumables | P33: =G25 -> 2.6331773 | S33: Consumables | T33: =SUMIF($O$32:$O$50,S33,$P$32:$P$50) -> 2.9109551 | V33: Nesting density | Y33: =G17 -> 0.51568461 | AE33: Printer | AF33: Consumables | AG33: =G25 -> 2.6331773 | AJ33: Consumables | AK33: =SUMIF($O$32:$O$50,S33,$P$32:$P$50) -> 2.9109551 | AM33: Nesting density | AP33: =X17
B34: Hours / day | C34: 16 | F34: Drying oven utilization | G34: =Universal!total_builds_yr*G31/G30 -> 1666.0631 | H34: hrs | J34: Powder processing investment | K34: =Universal!powder_process_msrp*IF(Universal!ppu_auto_on,K32,K30) -> 9795 | N34: Printer | O34: Depreciation | P34: =G24 -> 0.65249684 | S34: Depreciation | T34: =SUMIF($O$32:$O$50,S34,$P$32:$P$50) -> 1.1399153 | V34: Parts per furnace run | Y34: =IF(Universal!furnace_sel="DM",K9,K9) -> 216 | AE34: Printer | AF34: Labor | AG34: =G26 -> 0.082304527 | AJ34: Labor | AK34: =T35 -> 0.70055587 | AM34: Parts per furnace run | AP34: =IF(Universal!furnace_sel="DM",AB9,AB9)
B35: Days / week | C35: 7 | F35: Drying oven investment | G35: =IF(C14="TurboFuse",(Universal!xlink_msrp+1200)*G33,Universal!xlink_msrp*G33) -> 23540 | J35: ="Annual depreciation (@ "&Universal!dm_depr&" yrs)" -> Annual depreciation (@ 7 yrs) | K35: =K34/Universal!dm_depr+Universal!floor_rate*IF(Universal!ppu_auto_on,K32,K30)*Universal!powder_floorspace -> 1501.6857 | N35: Printer | O35: Labor | P35: =G26 -> 0.082304527 | S35: Labor | T35: =SUMIF($O$32:$O$50,S35,$P$32:$P$50) -> 0.70055587 | V35: Builds per furnace run | Y35: =Y34/Universal!parts_job -> 1.6 | AE35: Printer | AF35: Utilities | AG35: =G27 -> 0.056131891 | AJ35: Utilities | AK35: =T36 -> 1.8439126 | AM35: Builds per furnace run | AP35: =AP34/Universal!parts_job -> 0
B36: Weeks / year | C36: 50 | F36: ="Annual depreciation (@ "&Universal!dm_depr&" yrs)" -> Annual depreciation (@ 7 yrs) | G36: =G35/Universal!dm_depr+Universal!floor_rate*G33*Universal!xlink_floorspace -> 3490.8571 | J36: Depreciation $ / part | K36: =K35*IF(Universal!ppu_auto_on,K33,K31)/(Universal!avail_hours_yr*IF(Universal!ppu_auto_on,K32,K30))/Universal!part_req -> 0.027924708 | N36: Printer | O36: Utilities | P36: =G27 -> 0.056131891 | S36: Utilities | T36: =SUMIF($O$32:$O$50,S36,$P$32:$P$50) -> 1.8439126 | V36: Parts per week | Y36: =Y37/Universal!weeks_yr -> 400 | AE36: Drying Oven | AF36: Labor | AG36: =G38 -> 0.041152263 | AJ36: 3Yr Items | AK36: =T37 -> 0 | AM36: Parts per week | AP36: =AP37/Universal!weeks_yr -> 400
B37: Available hours / year | C37: =C34*C35*Universal!weeks_yr -> 5600 | F37: Depreciation $ / part | G37: =G36*G34/(Universal!total_hours_yr*G33)/Universal!part_req -> 0.034618978 | J37: Labor $ / part | K37: =Universal!labor_rate*Universal!total_builds_yr*IF(Universal!ppu_auto_on,Universal!ppu_auto_trnaround,K26/K27*Universal!powder_trnaround)/Universal!part_req -> 0.04442418 | N37: Drying Oven | O37: Depreciation | P37: =G37 -> 0.034618978 | S37: 3Yr Items | T37: =SUMIF($O$32:$O$50,S37,$P$32:$P$50) -> 0 | V37: Parts per year | Y37: =Universal!part_req -> 20000 | AE37: Drying Oven | AF37: Utilities | AG37: =G39 -> 0.027215141 | AJ37: Total | AK37: =SUM(AK32:AK36) -> 17.324828 | AM37: Parts per year | AP37: =Universal!part_req -> 20000
B38: Uptime | C38: 0.8 | F38: Labor $ / part | G38: =Universal!labor_rate*Universal!xlink_trnaround/G30*Universal!total_builds_yr/Universal!part_req -> 0.041152263 | J38: Utilities / part | K38: =Universal!power_rate*Universal!powder_pwr*IF(Universal!ppu_auto_on,G12,Universal!total_builds_yr*K26/K27)/Universal!part_req -> 0.00064503909 | N38: Drying Oven | O38: Labor | P38: =G38 -> 0.041152263 | S38: Total | T38: =SUM(T32:T37) -> 18.464743 | V38: Operating part cost | Y38: =P11 -> 17.324828 | AE38: Depowder | AF38: Labor | AG38: =G50 -> 0.4526749 | AM38: Operating part cost | AP38: =AG13 -> 17.324828
B39: Uptime hours / year | C39: =Universal!avail_hours_yr*Universal!uptime -> 4480 | F39: Utilities $ / part | G39: =Universal!power_rate*Universal!xlink_pwr*G34/Universal!part_req -> 0.027215141 | N39: Drying Oven | O39: Utilities | P39: =G39 -> 0.027215141 | V39: Operating cost / cc | Y39: =P13 -> 0.85729126 | AE39: Depowder | AF39: Utilities | AG39: =G51 -> 0.00084650206 | AI39: Total | AJ39: Raw Materials | AK39: =T32 -> 11.869404 | AM39: Operating cost / cc | AP39: =AG15 -> 0.85729126
B40: Good parts / printer / year | C40: =ROUND(Universal!good_parts_job/Universal!print_time_trn*Universal!uptime_hours_yr,0) -> 47454 | N40: Depowder | O40: Depreciation | P40: =G49 -> 0.026553946 | R40: Total | S40: Raw Materials | T40: =P32 -> 11.869404 | V40: Fully burdened part cost | Y40: =P17 -> 18.464743 | AE40: Furnace | AF40: Consumables | AG40: =IF(C15="No",0,K20) -> 0.27777778 | AJ40: Printer | AK40: =SUM(P33,P35,P36) -> 2.7716138 | AM40: Printer utilization | AP40: =AK14 -> 0.33717095
B41: Minimum config max capability | C41: =IF((MAX((C40/C31)/G32,(C40/C31)/G44))>1,Universal!part_capacity/(MAX((C40/C31)/G32,(C40/C31)/G44)),Universal!part_capacity) -> 47454 | E41: x | F41: Depowder part cost calculation | N41: Depowder | O41: Labor | P41: =G50 -> 0.4526749 | S41: Printer | T41: =SUMIF($N$33:$N$50,S41,$P$33:$P$50) -> 3.4241106 | V41: Fully burdened cost / cc | Y41: =P19 -> 0.91369814 | AE41: Furnace | AF41: Labor | AG41: =IF(C15="No",0,K21) -> 0.08 | AJ41: Drying Oven | AK41: =SUM(P38,P39) -> 0.068367404 | AM41: Furnace utilization | AP41: =AK17 -> 0.26420857
B42: Parts required / year | C42: 20000 | F42: Depowdered parts / hour | G42: =C57 -> 60 | N42: Depowder | O42: Utilities | P42: =G51 -> 0.00084650206 | S42: Drying Oven | T42: =SUMIF($N$33:$N$50,S42,$P$33:$P$50) -> 0.10298638 | V42: Printer utilization | Y42: =T14 -> 0.33717095 | AE42: Furnace | AF42: Utilities | AG42: =IF(C15="No",0,K22) -> 1.7590741 | AJ42: Depowder | AK42: =SUM(P41,P42) -> 0.4535214
A43: x | F43: ="Depowder time + "&Universal!depowder_trnaround&"hrs turnaround" -> Depowder time + 0.5hrs turnaround | G43: =Universal!parts_job/G42+Universal!depowder_trnaround -> 2.75 | H43: hrs | N43: Furnace | O43: Consumables | P43: =IF(C15="No",0,K20) -> 0.27777778 | S43: Depowder | T43: =SUMIF($N$33:$N$50,S43,$P$33:$P$50) -> 0.48007535 | V43: Furnace utilization | Y43: =T17 -> 0.26420857 | AE43: Furnace | AF43: 3Yr Items | AG43: =IF(C15="No",0,IF(Universal!furnace_sel="DM",VLOOKUP("Furnace equipment / run",Inputs!$B$178:$N$235,Universal!furnace_index+1,0)/K9,0)) -> 0 | AJ43: Furnace | AK43: =SUM(P43,P45,P46,P47) -> 2.1168519
B44: Cost & other inputs | F44: Build capacity / year | G44: =ROUNDDOWN(Universal!uptime_hours_yr/G43,0) -> 1629 | N44: Furnace | O44: Depreciation | P44: =IF(C15="No",0,K19) -> 0.39832084 | S44: Furnace | T44: =SUMIF($N$33:$N$50,S44,$P$33:$P$50) -> 2.5151727 | AE44: Blender | AF44: Labor | AG44: =K37 -> 0.04442418 | AJ44: Blender | AK44: =SUM(P49,P50) -> 0.045069219
B45: Material selection | C45: 17-4PH | F45: Depowders required (rounded) | G45: =ROUNDUP(Universal!total_builds_yr/G44,0) -> 1 | N45: Furnace | O45: Labor | P45: =IF(C15="No",0,K21) -> 0.08 | S45: Blender | T45: =SUMIF($N$33:$N$50,S45,$P$33:$P$50) -> 0.072993926 | AE45: Blender | AF45: Utilities | AG45: =K38 -> 0.00064503909 | AJ45: Total | AK45: =SUM(AK39:AK44) -> 17.324828
B46: Powder MSRP override | D46: $/kg | F46: Depowder utilization | G46: =Universal!total_builds_yr*G43 -> 452.6749 | H46: hrs | N46: Furnace | O46: Utilities | P46: =IF(C15="No",0,K22) -> 1.7590741 | S46: Total | T46: =SUM(T40:T45) -> 18.464743
B47: Powder MSRP default | C47: {=INDEX($C$188:$C$209,Universal!material_index)} -> 50 | D47: $/kg | F47: Depowder investment | G47: =(Universal!depowder_msrp+Universal!vacuum_msrp)*G45 -> 43840 | N47: Furnace | O47: 3Yr Items | P47: =IF(C15="No",0,IF(Universal!furnace_sel="DM",VLOOKUP("Furnace equipment / run",Inputs!$B$178:$N$235,Universal!furnace_index+1,0)/K9,0)) -> 0 | AF47: Total | AG47: =SUM(AG32:AG46) -> 17.324828
B48: Binder MSRP | C48: =IF(Universal!printer_index>10,IF(Universal!binder_per_yr>G213,C214,IF(Universal!binder_per_yr>G212,C213,C212)),C212) -> 300 | D48: $/L | F48: ="Annual depreciation (@ "&Universal!dm_depr&" yrs)" -> Annual depreciation (@ 7 yrs) | G48: =G47/Universal!dm_depr+Universal!floor_rate*G45*Universal!depowder_floorspace -> 6569.9291 | N48: Blender | O48: Depreciation | P48: =K36 -> 0.027924708
B49: Cleaner MSRP | C49: =VLOOKUP($B49,Inputs!$B:$Q,Universal!printer_index+1,0) | D49: $/L | F49: Depreciation $ / part | G49: =G48*G46/(Universal!avail_hours_yr*G45)/Universal!part_req -> 0.026553946 | N49: Blender | O49: Labor | P49: =K37 -> 0.04442418
B50: Printheads MSRP | C50: =VLOOKUP($B50,Inputs!$B:$Q,Universal!printer_index+1,0) -> 695 | F50: Labor $ / part | G50: =Universal!labor_rate*G43*Universal!total_builds_yr/Universal!part_req -> 0.4526749 | N50: Blender | O50: Utilities | P50: =K38 -> 0.00064503909
B51: Wiper cartridge MSRP | C51: =VLOOKUP($B51,Inputs!$B:$Q,Universal!printer_index+1,0) -> 231 | F51: Utilities $ / part | G51: =Universal!power_rate*Universal!depowder_pwr*G46/Universal!part_req -> 0.00084650206
B52: Binder sponge MSRP | C52: =VLOOKUP($B52,Inputs!$B:$Q,Universal!printer_index+1,0) -> 81 | O52: Total | P52: =SUM(P32:P51) -> 18.464743
B53: Region (currency) | C53: NAM
A54: x
B55: Labor, equipment, facilities inputs
B56: Labor rate | C56: 20 | D56: $/hr
B57: Depowdering parts / hour | C57: 60
B58: Furnace loading parts / hour | C58: 500
B59: Printer depreciation | C59: 7 | D59: yrs
B60: Furnace depreciation | C60: 7 | D60: yrs
B61: Nitrogen gas rate | C61: 0.001 | D61: $/L
B62: Hydrogen gas rate | C62: 0.0043 | D62: $/L
B63: Argon gas rate | C63: 0.0025 | D63: $/L
B64: Forming gas rate | C64: 0.011 | D64: $/L
B65: Power rate | C65: 0.11 | D65: $/kWh
B66: Floorspace rate / year | C66: 160 | D66: $/m2
A67: x
B68: Printer & aux equipment inputs
B69: Printer index | C69: =MATCH(Universal!printer_sel,Inputs!$C$4:$Q$4,0) -> 3
B70: Parts required / year | C70: =IF(C18="No",IF(C42<>"",C42,Universal!part_capacity),MIN(C42,Universal!part_capacity,IF(Universal!furnace_sel="Shop",K13,K13)*Universal!good_parts_job)) -> 20000
B71: X-scale | C71: =VLOOKUP($B71,Inputs!$B:$Q,Universal!printer_index+1,0) -> 1.167
B72: Y-scale | C72: =VLOOKUP($B72,Inputs!$B:$Q,Universal!printer_index+1,0) -> 1.174
B73: Z-scale | C73: =VLOOKUP($B73,Inputs!$B:$Q,Universal!printer_index+1,0) -> 1.21
B74: =IF(Universal!printer_index<11,"Layer speed",IF(C14="TurboFuse","X-Series Layer speed with TurboFuse","Layer speed")) -> Layer speed | C74: =VLOOKUP($B74,Inputs!$B:$Q,Universal!printer_index+1,0) -> 26 | D74: sec
B75: X-dim scaled | C75: =Universal!part_x*Universal!x_scale -> 35.01 | D75: mm
B76: Y-dim scaled | C76: =Universal!part_y*Universal!y_scale -> 35.22 | D76: mm
B77: Z-dim scaled | C77: =Universal!part_z*Universal!z_scale -> 36.3 | D77: mm
B78: Volume scaled | C78: =Universal!part_vol*Universal!x_scale*Universal!y_scale*Universal!z_scale -> 33501.546 | D78: mm3
B79: Parts / job | C79: =IF(Universal!override_nesting="Yes",IF(OR(C23=0,C24=0),C19,C23),C19) -> 135
B80: Bed density | C80: =VLOOKUP($B80,Inputs!$B:$Q,Universal!printer_index+1,0) -> 0.56
B81: Build box X-dim | C81: =VLOOKUP($B81,Inputs!$B:$Q,Universal!printer_index+1,0) -> 350 | D81: mm
B82: Build box Y-dim | C82: =VLOOKUP($B82,Inputs!$B:$Q,Universal!printer_index+1,0) -> 220 | D82: mm
B83: Build box Z-dim | C83: =VLOOKUP($B83,Inputs!$B:$Q,Universal!printer_index+1,0) -> 150 | D83: mm
B84: Build height | C84: =IF(Universal!override_nesting="Yes",IF(OR(C23=0,C24=0),C20,C24),C20) -> 113.9 | D84: mm
B85: Build box volume | C85: =Universal!build_x*Universal!build_y*Universal!build_height -> 8770300 | D85: mm3
B86: Build box quantity | C86: =IF(Universal!printer_index<=10,MAX(2*G11,G33*G30+ROUNDUP(G31/Universal!print_time_trn,0)),ROUNDUP((Universal!print_time_trn+G31+G43)/(Universal!avail_hours_yr/Universal!total_builds_yr),0)) -> 4
B87: Powder + overflow ratio | C87: =VLOOKUP($B87,Inputs!$B:$Q,Universal!printer_index+1,0) -> 1.8
B88: Powder loss percentage | C88: =VLOOKUP($B88,Inputs!$B:$Q,Universal!printer_index+1,0) -> 0.005
B89: Binder void ratio | C89: =VLOOKUP($B89,Inputs!$B:$Q,Universal!printer_index+1,0) -> 0.68181818
B90: Binder purge volume | C90: =VLOOKUP($B90,Inputs!$B:$Q,Universal!printer_index+1,0) -> 1.5 | D90: mL
B91: Purge frequency | C91: =VLOOKUP($B91,Inputs!$B:$Q,Universal!printer_index+1,0) -> 16 | D91: layers
B92: Printhead life | C92: =VLOOKUP($B92,Inputs!$B:$Q,Universal!printer_index+1,0) -> 4000 | D92: layers
B93: Wiper cartridge life | C93: =VLOOKUP($B93,Inputs!$B:$Q,Universal!printer_index+1,0) -> 8000 | D93: layers
B94: Binder sponge life | C94: =VLOOKUP($B94,Inputs!$B:$Q,Universal!printer_index+1,0) -> 10 | D94: L
B95: Cleaner frequency | C95: =VLOOKUP($B95,Inputs!$B:$Q,Universal!printer_index+1,0) -> 0 | D95: layers
B96: Cleaner volume | C96: =VLOOKUP($B96,Inputs!$B:$Q,Universal!printer_index+1,0) -> 0 | D96: mL
B97: Printer XY border | C97: =VLOOKUP($B97,Inputs!$B:$Q,Universal!printer_index+1,0) -> 4 | D97: mm
B98: Printer Z base plate | C98: =VLOOKUP($B98,Inputs!$B:$Q,Universal!printer_index+1,0) -> 3 | D98: mm
B99: Printer XY spacing | C99: =VLOOKUP($B99,Inputs!$B:$Q,Universal!printer_index+1,0) -> 1 | D99: mm
B100: Printer Z spacing | C100: =VLOOKUP($B100,Inputs!$B:$Q,Universal!printer_index+1,0) -> 1 | D100: mm
B101: =IF(Universal!printer_index<11,"Crosslink time",IF(C14="TurboFuse","X-Series Crosslink time with TurboFuse","Crosslink time")) -> Crosslink time | C101: =VLOOKUP($B101,Inputs!$B:$Q,Universal!printer_index+1,0) -> 26 | D101: hrs
...

Sheet Layer_defaults
B1: P-1/P-50 Default Layer Thickness | C1: X shrink | D1: Y shrink | E1: Z shrink
A2: 17-4PH | B2: 0.065 | C2: 1.16 | D2: 1.165 | E2: 1.18
A3: 316L | B3: 0.065 | C3: 1.157 | D3: 1.153 | E3: 1.174
A4: 420 | B4: 0.05 | C4: 1.177 | D4: 1.18 | E4: 1.192
A5: 440C | B5: 0.05 | C5: 1.177 | D5: 1.18 | E5: 1.192
A6: DM HH Stainless | B6: 0.065 | C6: 1.157 | D6: 1.153 | E6: 1.174
A7: IN625 | B7: 0.05 | C7: 1.17 | D7: 1.173 | E7: 1.196
A8: IN718 | B8: 0.05 | C8: 1.17 | D8: 1.173 | E8: 1.196
A9: D2 | B9: 0.065 | C9: 1.157 | D9: 1.159 | E9: 1.203
A10: H13 | B10: 0.05 | C10: 1.157 | D10: 1.159 | E10: 1.203
A11: 4140 | B11: 0.05 | C11: 1.157 | D11: 1.157 | E11: 1.19
A12: Cu | B12: 0.05 | C12: 1.172 | D12: 1.181 | E12: 1.186
A13: Silver | B13: 0.04 | C13: 1.1424 | D13: 1.1433 | E13: 1.15
A14: Gold | B14: 0.04 | C14: 1.1424 | D14: 1.1433 | E14: 1.15
A15: Al 6061 | B15: 0.1 | C15: 1.13 | D15: 1.13 | E15: 1.15
A16: Ti-64 | B16: 0.065 | C16: 1.13 | D16: 1.13 | E16: 1.15
A17: M2 | B17: 0.065 | C17: 1.157 | D17: 1.159 | E17: 1.203
A18: S7 | B18: 0.065 | C18: 1.157 | D18: 1.159 | E18: 1.203
A19: 304L | B19: 0.065 | C19: 1.157 | D19: 1.153 | E19: 1.174
A20: CrMnMoN | B20: 0.065 | C20: 1.157 | D20: 1.153 | E20: 1.174
A21: WC-12Co | B21: 0.065 | C21: 1.157 | D21: 1.153 | E21: 1.174
A22: SiC

Sheet Shop
A2: x | B2: =MID(CELL("filename",A1),SEARCH("[",CELL("filename",A1))+1,LEN(CELL("filename",A1))-SEARCH("[",CELL("filename",A1))-16) -> #VALUE! | F2: SHOP SYSTEM | K2: Privileged & DM Confidential | M2: x | N2: Shop System part cost outputs
N3: DM equipment MSRP | P3: =G19+G34+G46+K47 -> #N/A | R3: ="Printed parts / "&C14&" build" -> Printed parts / 12L build | T3: =parts_job -> 360
A4: x | B4: Part inputs (pre-scaling) | E4: x | F4: Printer usage calculation | I4: x | J4: DM furnace part cost calculation | N4: =IF(C16="Shop","DM",C16&" cu ft MIM")&" furnace MSRP" -> DM furnace MSRP | P4: =IF(C16="Shop",K13,K33) -> N.A. | R4: Part nesting density | T4: =G16 -> 0.69668439
B5: X-dim (incl. supports) | C5: 15 | D5: mm | F5: Powder volume / part | G5: =part_vol_scale*Shop!bed_density -> 3564.869 | H5: mm3 | J5: Furnace parts / run | K5: =ROUNDDOWN((dm_furnace_x+furnace_xy_spacing)/(furnace_part_scale_x+furnace_xy_spacing),0)*ROUNDDOWN((dm_furnace_y+furnace_xy_spacing)/(furnace_part_scale_y+furnace_xy_spacing),0)*MIN(5,ROUNDDOWN(dm_furnace_z/(furnace_part_scale_z+furnace_z_spacing),0)) -> #N/A | N5: Total equipment MSRP | P5: =SUM(P3:P4) -> #N/A
B6: Y-dim (incl. supports) | C6: 16 | D6: mm | F6: Powder mass / part | G6: =G5*Shop!density_selected*1000 -> 28.518952 | H6: g | J6: Furnace loading parts / hour | K6: =C52 -> 240 | N6: =C14&" printers required" -> 12L printers required | P6: =G10 -> 1 | R6: Printer builds / week | T6: =T8/weeks_yr -> 17.32853
B7: Z-dim (incl. supports) | C7: 16 | D7: mm | F7: Powder mass / build | G7: =(G6*parts_job)/1000+((build_vol*Shop!bed_density*Shop!density_selected*powder_ratio)-(G6*parts_job)/1000)*powder_loss_percentage -> 10.348119 | H7: kg | J7: Run time + turnaround | K7: =43+K5/K6*2 -> #N/A | L7: hrs | N7: Furnaces required | P7: =IF(furnace_sel="Shop",K11,K31) -> N.A. | R7: Printer builds / month | T7: =T6*4 -> 69.31412
B8: Part volume | C8: =+part_x*part_y*part_z -> 3840 | D8: mm3 | F8: Binder volume / part | G8: =part_vol_scale*binder_ratio -> #N/A | H8: mm3 | J8: Time per printer build | K8: =IFERROR((good_parts_job/K5*K7),"N.A.") -> N.A. | L8: hrs | R8: Printer builds / year | T8: =total_builds_yr -> 831.76944
B9: Support volume | D9: mm3 | F9: Binder volume / build | G9: =G8*parts_job/10^6+(build_layers/C84+2)*binder_purge_vol/1000 -> #N/A | H9: L | J9: Build capacity / year | K9: =IFERROR(ROUNDDOWN(avail_hours_yr/K8,0),"N.A.") -> N.A. | N9: Operating (i.e. "running") part costs
B10: Part + support volume | C10: =Shop!part_only_vol+Shop!support_vol -> 3840 | D10: mm3 | F10: Printers required (rounded) | G10: =ROUNDUP(part_req/part_capacity,0) -> 1 | J10: Runs / year | K10: =IFERROR(ROUNDUP(part_req/K5,0),"N.A.") -> N.A. | N10: Printed part cost | P10: =P32+P33+P35+P36 -> #N/A | R10: =IF($C$15="Yes","Sintered","Green")&" parts / week" -> Sintered parts / week | T10: =T12/weeks_yr -> 6238.2708
F11: Printer utilization | G11: =part_req/good_parts_job*print_time_trn -> 3840.0023 | H11: hrs | J11: DM furnaces required (rounded) | K11: =IFERROR(ROUNDUP(total_builds_yr/K9,0),"N.A.") -> N.A. | N11: =IF(C15="Yes","Sintered","Green")&" part cost" -> Sintered part cost | P11: =T38-T34-T37 -> #N/A | R11: =IF($C$15="Yes","Sintered","Green")&" parts / month" -> Sintered parts / month | T11: =T10*4 -> 24953.083
A12: x | B12: Build inputs & process capacity | F12: Builds / year | G12: =part_req/good_parts_job -> 831.76944 | J12: DM furnace utilization | K12: =IFERROR(K7*K10,"N.A.") -> N.A. | L12: hrs | N12: =N10&" / cc" -> Printed part cost / cc | P12: =P10/Shop!part_only_vol*10^3 -> #N/A | R12: =IF($C$15="Yes","Sintered","Green")&" parts / year" -> Sintered parts / year | T12: =part_req -> 299437
B13: Pricing model | C13: Base | F13: Builds / month | G13: =G12/12 -> 69.31412 | J13: DM furnace investment | K13: =IFERROR(K11*dm_furnace_msrp,"N.A.") -> N.A. | N13: =N11&" / cc" -> Sintered part cost / cc | P13: =P11/Shop!part_only_vol*10^3 -> #N/A
B14: Build box size | C14: 12L | F14: Printer utilization (% of available) | G14: =G11/(avail_hours_yr*G10) -> 1.0000006 | J14: ="Annual depreciation (@ "&Shop!dm_depr&" yrs)" -> Annual depreciation (@ 5 yrs) | K14: =IFERROR(K13/Shop!dm_depr+(1.6*1.4)*K11*Shop!floor_rate,"N.A.") -> N.A. | R14: ="Printer util (QTY: "&G10&")" -> Printer util (QTY: 1) | T14: =G14 -> 1.0000006
B15: Include sintering? | C15: Yes | F15: Printer utilization (% 24x7) | G15: =G11/(24*7*52*G10) -> 0.4395607 | J15: Consumables $ / part | K15: =IFERROR(dm_furnace_consumables_run/K5+dm_furnace_consumables_material*(G6/1000),"N.A.") -> N.A. | N15: Burdened (i.e. "depreciated") part costs | R15: ="Oven util (QTY: "&G32&")" -> #N/A | T15: =G33/(total_hours_yr*G32*Shop!uptime) -> #N/A
B16: Furnace selection | C16: Shop | D16: =IF(OR(furnace_sel="Shop",furnace_sel="Continuous"),,"ft3") | F16: Nesting density | G16: =part_vol_scale*parts_job/build_vol -> 0.69668439 | J16: Depreciation $ / part | K16: =IFERROR(K12/(total_hours_yr*K11)*K14/part_req,"N.A.") -> N.A. | N16: Printed part cost | P16: =SUM(P32:P36) -> #N/A | R16: ="Depowder util (QTY: "&G44&")" -> Depowder util (QTY: 2) | T16: =G45/(avail_hours_yr*G44*Shop!uptime) -> 0.70397153
B17: Debind | C17: Integrated | J17: Labor $ / part | K17: =IFERROR(labor_rate*(K7-43)/K5,"N.A.") -> N.A. | N17: =IF(C15="Yes","Sintered","Green")&" part cost" -> Sintered part cost | P17: =T46 -> #N/A | R17: ="Furnace util (QTY: "&IF(furnace_sel="Shop",K11,K31)&")" -> Furnace util (QTY: N.A.) | T17: =IF(C16="Shop",K12/(total_hours_yr*K11*Shop!uptime),K32/(total_hours_yr*K31*Shop!uptime)) -> #VALUE!
B18: Limit furnace to QTY 1 | C18: No | E18: x | F18: Printer part cost calculation | J18: Utilities / part | K18: =IFERROR((1.25*power_rate*43+0.011*2400)/K5,"N.A.") -> N.A. | N18: Printed part cost / cc | P18: =P16/Shop!part_only_vol*10^3 -> #N/A
B19: Nested parts / job | C19: =ROUNDDOWN((Shop!build_x-Shop!printer_xy_border*2+Shop!printer_xy_spacing)/(part_scale_x+Shop!printer_xy_spacing),0)*ROUNDDOWN((Shop!build_y-Shop!printer_xy_border*2+Shop!printer_xy_spacing)/(part_scale_y+Shop!printer_xy_spacing),0)*ROUNDDOWN((Shop!build_z-Shop!printer_z_base+Shop!printer_z_spacing)/(part_scale_z+Shop!printer_z_spacing),0) -> 360 | F19: Printer investment (incl. build box) | G19: =G10*(printer_msrp+(C73/50-1)*printer_module_msrp)+G10*Shop!vacuum_msrp+MAX(2*G10,G32*G29+ROUNDUP(G30/print_time_trn,0))*Shop!buildbox_msrp+800*G10*2*3+1500+8000 -> #N/A | N19: =IF(C15="Yes","Sintered","Green")&" part cost / cc" -> Sintered part cost / cc | P19: =P17/Shop!part_only_vol*10^3 -> #N/A | R19: Labor hrs / year | T19: =1*total_builds_yr+0.5*total_builds_yr/2+G45+IF(C16="Shop",K5/K6*K10*2,K25/K26*K30*2)+0.25*(K46/K42) -> #N/A
B20: Build height | C20: =Shop!printer_z_base+(part_scale_z)*ROUNDDOWN((Shop!build_z-Shop!printer_z_base+Shop!printer_z_spacing)/(part_scale_z+Shop!printer_z_spacing),0)+Shop!printer_z_spacing*(ROUNDDOWN((Shop!build_z-Shop!printer_z_base+Shop!printer_z_spacing)/(part_scale_z+Shop!printer_z_spacing),0)-1) -> 42.72 | D20: mm | F20: ="Annual depreciation (@ "&Shop!dm_depr&" yrs)" -> Annual depreciation (@ 5 yrs) | G20: =G19/Shop!dm_depr+(2*0.8+0.56*0.57)*G10*Shop!floor_rate -> #N/A | I20: x | J20: MIM furnace part cost calculation | N20: Notes & assumptions:
B21: Override nesting | C21: No | F21: Powder $ / part | G21: =(G7*powder_price)/good_parts_job -> 2.3570715 | J21: Furnace selection | K21: =C16 -> Shop | L21: =IF(OR(furnace_sel="Shop",furnace_sel="Continuous"),,"ft3") | N21: 1. Pricing is not final unless on an official DM quote and is subject to change. Does not include installation, training, shipping, or taxes.
B22: Override parts / job | C22: 12 | F22: Binder $ / part | G22: =G9*binder_price/good_parts_job -> #N/A | J22: Furnace X-dim | K22: =C109 -> N.A. | L22: mm | N22: ="2. DM Equipment MSRP includes printer build boxes ("&MAX(2*G10,G32*G29+ROUNDUP(G30/print_time_trn,0))&"x), powder kegs, and transfer cart." -> #N/A
B23: Override build height | C23: 147 | D23: mm | F23: Depreciation $ / part | G23: =G11/(avail_hours_yr*G10)*G20/part_req -> #N/A | J23: Furnace Y-dim | K23: =C110 -> N.A. | L23: mm | N23: 3. Consumables includes printer items (e.g. printheads, wiper cartridges, etc.) and, if applicable, Desktop Metal Furnace items (e.g. setter plates, shelving, oil, liners, etc.).
B24: Layer thickness | C24: 0.075 | D24: mm | F24: Consumables $ / part | G24: =((build_layers/printhead_life*printhead_msrp)+(build_layers/Shop!wiper_life*Shop!wiper_msrp)+(G9/Shop!sponge_life*Shop!sponge_msrp))/good_parts_job -> #N/A | J24: Furnace Z-dim | K24: =C111 -> N.A. | L24: mm | N24: 4. Includes utilities costs for gas (as required), electricity, and floorspace.
B25: Layers | C25: =ROUNDUP(build_height/C24,0) -> 570 | F25: Labor $ / part | G25: =print_trnaround*labor_rate/good_parts_job -> 0.027777778 | J25: Furnace parts / run | K25: =IF(furnace_sel="Continuous",part_req,ROUNDDOWN((Shop!mim_furnace_x+furnace_xy_spacing)/(furnace_part_scale_x+furnace_xy_spacing),0)*ROUNDDOWN((Shop!mim_furnace_y+furnace_xy_spacing)/(furnace_part_scale_y+furnace_xy_spacing),0)*MIN(furnace_shelves,ROUNDDOWN(Shop!mim_furnace_z/(furnace_part_scale_z+Shop!Furnace_rack_thickness+furnace_z_spacing),0))) -> #VALUE! | N25: ="5. "&C41&" powder at "&TEXT(powder_price,"$0.00")&"/kg and binder at "&TEXT(binder_price,"$0.00")&"/L. Volume pricing may be available." -> 5. 17-4PH SS powder at $82.00/kg and binder at $300.00/L. Volume pricing may be available.
B26: ="Print time + "&print_trnaround&"hrs turnaround" -> Print time + 0.5hrs turnaround | C26: =C25*Shop!layer_speed/(60*60)+print_trnaround -> 4.6166667 | D26: hrs | F26: Utilities $ / part | G26: =power_rate*5*(print_time_trn-print_trnaround)/good_parts_job -> 0.0068611111 | J26: Furnace loading parts / hour | K26: =C52 -> 240 | N26: ="6. Key process assumptions: (i) "&C24*1000&" micron printed layer height; (ii) $"&labor_rate&"/hr labor rate; (iii) Printer, depowdering, and powder handling equipment @ "&C31&" x "&C32&" x "&weeks_yr&" x "&Shop!uptime*100&"% uptime" -> 6. Key process assumptions: (i) 75 micron printed layer height; (ii) $20/hr labor rate; (iii) Printer, depowdering, and powder handling equipment @ 16 x 5 x 48 x 100% uptime
B27: Overall process yield | C27: 1 | J27: Run time + turnaround | K27: =Shop!furnace_time_cycle+K25/K26*2 -> #VALUE! | L27: hrs | O27: =" (iv) "&G41&" parts/hr depowdering rate; (v) "&total_yield*100&"% overall process yield; (vi) "&Shop!dm_depr&"yr DM equipment depreciation;" -> (iv) 60 parts/hr depowdering rate; (v) 100% overall process yield; (vi) 5yr DM equipment depreciation;
B28: Good parts / job | C28: =IF(override_nesting="Yes",IF(C22=0,C19,C22),C19)*C27 -> 360 | E28: x | F28: Drying oven part cost calculation | J28: Time per printer build | K28: =IFERROR(good_parts_job/K25*K27,"N.A.") -> N.A. | L28: hrs | O28: =" (vii) Drying oven "&IF(C15="Yes","& sintering ",)&"equipment @ 24 x 7 x "&weeks_yr&" x "&Shop!uptime*100&"% uptime; (viii) "&IF(C15="Yes",Shop!furnace_depr&"yr MIM furnace depreciation; (iv) ",)&total_yield*100&"% overall process yield" -> (vii) Drying oven & sintering equipment @ 24 x 7 x 48 x 100% uptime; (viii) 10yr MIM furnace depreciation; (iv) 100% overall process yield
F29: Printer builds / oven run | G29: =IF(OR(Shop!s_model="4L",Shop!s_model="8L"),2,1) -> 1 | J29: Build capacity / year | K29: =IF(furnace_sel="Continuous",(240000/2.2)/(good_parts_job*part_vol*Shop!density_selected),ROUNDDOWN(avail_hours_yr/K28,0)) -> #VALUE!
A30: x | B30: Printer operations inputs | F30: ="Dry time + "&Shop!xlink_trnaround&"hrs turnaround" -> #N/A | G30: =C92*build_height/Shop!build_z+Shop!xlink_trnaround -> #N/A | H30: hrs | J30: Runs / year | K30: =IFERROR(ROUNDUP(part_req/K25,0),"N.A.") -> N.A.
B31: Hours / day | C31: 16 | F31: Build capacity / year | G31: =ROUNDDOWN(G29*total_hours_yr/G30,0) -> #N/A | J31: MIM furnaces required (rounded) | K31: =IFERROR(ROUNDUP(total_builds_yr/K29,0),"N.A.") -> N.A. | N31: ="Shop System "&C14&" "&LOWER(N11)&" allocation" -> Shop System 12L sintered part cost allocation | V31: Cost model template output
B32: Days / week | C32: 5 | F32: Ovens required (rounded) | G32: =ROUNDUP(total_builds_yr/G31,0) -> #N/A | J32: MIM furnace utilization | K32: =IFERROR(K27*K30,"N.A.") -> N.A. | L32: hrs | N32: Printer | O32: Raw materials | P32: =G21+G22 -> #N/A | R32: Total | S32: Raw Materials | T32: =SUMIF($O$32:$O$50,S32,$P$32:$P$50) -> #N/A | V32: Parts per build | Y32: =parts_job -> 360
B33: Weeks / year | C33: 48 | F33: Drying oven utilization | G33: =total_builds_yr*G30/G29 -> #N/A | H33: hrs | J33: MIM furnace investment | K33: =IFERROR(OFFSET(C126,furnace_index-1,)*K31,"N.A.") -> N.A. | N33: Printer | O33: Consumables | P33: =G24 -> #N/A | S33: Consumables | T33: =SUMIF($O$32:$O$50,S33,$P$32:$P$50) -> #N/A | V33: Nesting density | Y33: =G16 -> 0.69668439
B34: Printer available hours / year | C34: =C31*C32*weeks_yr -> 3840 | F34: Drying oven investment | G34: =G32*curing_msrp -> #N/A | J34: ="Annual depreciation (@ "&Shop!furnace_depr&" yrs)" -> Annual depreciation (@ 10 yrs) | K34: =IFERROR(K33/Shop!furnace_depr+OFFSET(C136,furnace_index-1,)*K31*Shop!floor_rate,"N.A.") -> N.A. | N34: Printer | O34: Depreciation | P34: =G23 -> #N/A | S34: Depreciation | T34: =SUMIF($O$32:$O$50,S34,$P$32:$P$50) -> #N/A | V34: Parts per furnace run | Y34: =IF(furnace_sel="Shop",K5,K25) -> #N/A
B35: Printer & furnace uptime | C35: 1 | F35: ="Annual depreciation (@ "&Shop!dm_depr&" yrs)" -> Annual depreciation (@ 5 yrs) | G35: =G34/Shop!dm_depr+(1*0.8)*G32*Shop!floor_rate -> #N/A | J35: Depreciation / part | K35: =IFERROR(K32/(IF(furnace_sel="Continuous",total_hours_yr,avail_hours_yr)*K31)*K34/part_req,"N.A.") -> N.A. | N35: Printer | O35: Labor | P35: =G25 -> 0.027777778 | S35: Labor | T35: =SUMIF($O$32:$O$50,S35,$P$32:$P$50) -> #N/A | V35: Builds per furnace run | Y35: =Y34/parts_job -> #N/A
B36: Printer uptime hours / year | C36: =avail_hours_yr*Shop!uptime -> 3840 | F36: Depreciation $ / part | G36: =G33/(total_hours_yr*G32)*G35/part_req -> #N/A | J36: Consumables / part | K36: =IF(furnace_sel="Continuous",Shop!furnace_power_cons*total_hours_yr/part_req,0) -> 0 | N36: Printer | O36: Utilities | P36: =G26 -> 0.0068611111 | S36: Utilities | T36: =SUMIF($O$32:$O$50,S36,$P$32:$P$50) -> #N/A | V36: Parts per week | Y36: =Y37/weeks_yr -> 6238.2708
B37: Good parts / printer / year | C37: =ROUND(good_parts_job/print_time_trn*Shop!uptime_hours_yr,0) -> 299437 | F37: Labor $ / part | G37: =(Shop!xlink_trnaround/G29*labor_rate*total_builds_yr)/part_req -> #N/A | J37: Labor $ / part | K37: =IFERROR(labor_rate*(K25/K26*2)/K25,"N.A.") -> N.A. | N37: Drying Oven | O37: Depreciation | P37: =G36 -> #N/A | S37: 3Yr Items | T37: =SUMIF($O$32:$O$50,S37,$P$32:$P$50) -> #N/A | V37: Parts per year | Y37: =part_req -> 299437
B38: Parts required / year | C38: =part_capacity -> 299437 | F38: Utilities $ / part | G38: =power_rate*2.97*G33/part_req -> #N/A | J38: Utilities / part | K38: =IF(furnace_sel="Continuous",Shop!furnace_gas_cons*total_hours_yr,(Shop!argon_rate*Shop!furnace_gas_cons+power_rate*Shop!furnace_power_cons)*(K27-K25/K26*2)*K30)/part_req -> #VALUE! | N38: Drying Oven | O38: Labor | P38: =G37 -> #N/A | S38: Total | T38: =SUM(T32:T37) -> #N/A | V38: Operating part cost | Y38: =P11 -> #N/A
N39: Drying Oven | O39: Utilities | P39: =G38 -> #N/A | V39: Operating cost / cc | Y39: =P13 -> #N/A
A40: x | B40: Cost & other inputs | E40: x | F40: Depowder part cost calculation | I40: x | J40: Powder blender part cost calculation | N40: Depowder | O40: Depreciation | P40: =G48 -> #N/A | R40: Total | S40: Raw Materials | T40: =P32 -> #N/A | V40: Fully burdened part cost | Y40: =P17 -> #N/A
B41: Material selection | C41: 17-4PH SS | F41: Depowdered parts / hour | G41: =C51 -> 60 | J41: Powder blender capacity | K41: 45 | L41: kg | N41: Depowder | O41: Labor | P41: =G49 -> 0.36111111 | S41: Printer | T41: =SUMIF($N$33:$N$50,S41,$P$33:$P$50) -> #N/A | V41: Fully burdened cost / cc | Y41: =P19 -> #N/A
B42: Powder MSRP | C42: {=INDEX(C154:C163,VLOOKUP(C41,B141:F151,5,0))} -> 82 | D42: $/kg | F42: ="Depowder time + "&Shop!depowder_trnaround&"hrs turnaround" -> Depowder time + 0.5hrs turnaround | G42: =parts_job/G41+Shop!depowder_trnaround -> 6.5 | H42: hrs | J42: ="Blend time + "&Shop!powder_trnaround&"hrs turnaround" -> Blend time + 0.25hrs turnaround | K42: =1+Shop!powder_trnaround -> 1.25 | L42: hrs | N42: Depowder | O42: Utilities | P42: =G50 -> 0.00073666667 | S42: Drying Oven | T42: =SUMIF($N$33:$N$50,S42,$P$33:$P$50) -> #N/A | V42: Printer utilization | Y42: =T14 -> 1.0000006
B43: Binder MSRP | C43: =VLOOKUP(B43,Inputs!$B$6:$M$311,Inputs!C$1,0) -> 300 | D43: $/L | F43: Build capacity / year | G43: =ROUNDDOWN(Shop!uptime_hours_yr/G42,0) -> 590 | J43: Powder capacity / year | K43: =K41*Shop!uptime_hours_yr/K42 -> 138240 | L43: kg | N43: Furnace | O43: Consumables | P43: =IF(C15="No",0,IF(furnace_sel="Shop",K15,)) -> N.A. | S43: Depowder | T43: =SUMIF($N$33:$N$50,S43,$P$33:$P$50) -> #N/A | V43: Furnace utilization | Y43: =T17 -> #VALUE!
B44: Printheads MSRP | C44: =VLOOKUP(B44,Inputs!$B$6:$M$311,Inputs!C$1,0) -> 695 | F44: Depowders required (rounded) | G44: =ROUNDUP(total_builds_yr/G43,0) -> 2 | J44: Loose powder / build | K44: =(build_vol*Shop!bed_density*powder_ratio*Shop!density_selected-G7) -> 16.177925 | L44: kg | N44: Furnace | O44: Depreciation | P44: =IF(C15="No",0,IF(furnace_sel="Shop",K16,K35)) -> N.A. | S44: Furnace | T44: =SUMIF($N$33:$N$50,S44,$P$33:$P$50) -> #N/A
B45: Wiper cartridge MSRP | C45: =VLOOKUP(B45,Inputs!$B$6:$M$311,Inputs!C$1,0) -> 231 | F45: Depowder utilization | G45: =total_builds_yr*G42 -> 5406.5014 | H45: hrs | J45: Blenders required (rounded) | K45: =ROUNDUP(total_builds_yr*K44/K43,0) -> 1 | N45: Furnace | O45: Labor | P45: =IF(C15="No",0,IF(furnace_sel="Shop",K17,K37)) -> N.A. | S45: Blender | T45: =SUMIF($N$33:$N$50,S45,$P$33:$P$50) -> #N/A
B46: Binder sponge MSRP | C46: =VLOOKUP(B46,Inputs!$B$6:$M$311,Inputs!C$1,0) -> 81 | F46: Depowder investment | G46: =G44*(depowder_msrp+Shop!vacuum_msrp) -> #N/A | J46: Powder blender utilization (hrs) | K46: =total_builds_yr*K44/K41*K42 -> 373.78622 | L46: hrs | N46: Furnace | O46: Utilities | P46: =IF(C15="No",0,IF(furnace_sel="Shop",K18,K38)) -> N.A. | S46: Total | T46: =SUM(T40:T45) -> #N/A
B47: Region (currency) | C47: NAM | F47: ="Annual depreciation (@ "&Shop!dm_depr&" yrs)" -> Annual depreciation (@ 5 yrs) | G47: =G46/Shop!dm_depr+(1.6*1+0.56*0.57)*G44*Shop!floor_rate -> #N/A | J47: Powder blender investment | K47: =Shop!blender_msrp*K45 -> #N/A | N47: Furnace | O47: 3Yr Items | P47: =IF(C15="No",0,IF(furnace_sel="Shop",dm_furnace_hw_consumables/K5,0)) -> #N/A
F48: Depreciation $ / part | G48: =G45/(avail_hours_yr*G44)*G47/part_req -> #N/A | J48: ="Annual depreciation (@ "&Shop!dm_depr&" yrs)" -> Annual depreciation (@ 5 yrs) | K48: =K47/Shop!dm_depr+(0.8*0.8)*K45*Shop!floor_rate -> #N/A | N48: Blender | O48: Depreciation | P48: =K49 -> #N/A
A49: x | B49: Labor, equipment, facilities inputs | F49: Labor $ / part | G49: =G42*labor_rate*total_builds_yr/part_req -> 0.36111111 | J49: Depreciation $ / part | K49: =K46/(avail_hours_yr*K45)*K48/part_req -> #N/A | N49: Blender | O49: Labor | P49: =K50 -> 0.0049931868
B50: Labor rate | C50: 20 | D50: $/hr | F50: Utilities $ / part | G50: =power_rate*0.34*G45/part_req -> 0.00073666667 | J50: Labor $ / part | K50: =total_builds_yr*K44/K41*Shop!powder_trnaround*labor_rate/part_req -> 0.0049931868 | N50: Blender | O50: Utilities | P50: =K51 -> 7.9092079e-05
B51: Depowdering parts / hour | C51: 60 | J51: Utilities / part | K51: =0.66*power_rate*(total_builds_yr*K44/K41)/part_req -> 7.9092079e-05
B52: Furnace loading parts / hour | C52: 240
B53: DM equipment depreciation | C53: 5 | D53: yrs
B54: MIM furnace depreciation | C54: 10 | D54: yrs
B55: Nitrogen rate | C55: 0.001 | D55: $/L
B56: Argon rate | C56: 0.0025 | D56: $/L
B57: Power rate | C57: 0.12 | D57: $/kWh
B58: Floorspace rate / year | C58: 160 | D58: $/m2
A60: x | B60: Parts required / year | C60: =IF(C18="No",IF(C38<>"",C38,part_capacity),MIN(part_capacity,IF(furnace_sel="Shop",K9,K29)*good_parts_job)) -> 299437
B61: X-scale | C61: =VLOOKUP($B61,Inputs!$B$6:$M$309,Inputs!C$1,0) -> 1.167
B62: Y-scale | C62: =VLOOKUP($B62,Inputs!$B$6:$M$309,Inputs!C$1,0) -> 1.174
B63: Z-scale | C63: =VLOOKUP($B63,Inputs!$B$6:$M$309,Inputs!C$1,0) -> 1.21
B64: Layer speed | C64: =VLOOKUP($B64,Inputs!$B$6:$M$309,Inputs!C$1,0) -> 26 | D64: sec
B65: X-dim scaled | C65: =part_x*Shop!x_scale -> 17.505 | D65: mm
B66: Y-dim scaled | C66: =part_y*Shop!y_scale -> 18.784 | D66: mm
B67: Z-dim scaled | C67: =part_z*Shop!z_scale -> 19.36 | D67: mm
B68: Volume scaled | C68: =part_vol*Shop!x_scale*Shop!y_scale*Shop!z_scale -> 6365.8375 | D68: mm3
B69: Parts / job | C69: =IF(override_nesting="Yes",IF(OR(C22=0,C23=0),C19,C22),C19) -> 360
B70: Bed density | C70: =VLOOKUP($B70,Inputs!$B$6:$M$309,Inputs!C$1,0) -> 0.56
B71: Build box X-dim | C71: =VLOOKUP($B71,Inputs!$B$6:$M$309,Inputs!C$1,0) -> 350 | D71: mm
B72: Build box Y-dim | C72: =VLOOKUP($B72,Inputs!$B$6:$M$309,Inputs!C$1,0) -> 220 | D72: mm
B73: Build box Z-dim | C73: =VLOOKUP($B73,Inputs!$B$6:$M$309,Inputs!C$1,0) -> 50 | D73: mm
B74: Build height | C74: =IF(override_nesting="Yes",IF(OR(C22=0,C23=0),C20,C23),C20) -> 42.72 | D74: mm
B75: Build box volume | C75: =Shop!build_x*Shop!build_y*build_height -> 3289440 | D75: mm3
B76: Print turnaround time | C76: =VLOOKUP($B76,Inputs!$B$6:$M$309,Inputs!C$1,0) -> 0.5 | D76: hrs
B77: Drying oven turnaround time | C77: =VLOOKUP($B77,Inputs!$B$6:$M$309,Inputs!C$1,0) -> #N/A | D77: hrs
B78: Depowder turnaround time | C78: =VLOOKUP($B78,Inputs!$B$6:$M$309,Inputs!C$1,0) -> 0.5 | D78: hrs
B79: Powder blender turnaround time | C79: =VLOOKUP($B79,Inputs!$B$6:$M$309,Inputs!C$1,0) -> 0.25 | D79: hrs
B80: Powder + overflow ratio | C80: =VLOOKUP($B80,Inputs!$B$6:$M$309,Inputs!C$1,0) -> 1.8
B81: Powder loss percentage | C81: =VLOOKUP($B81,Inputs!$B$6:$M$309,Inputs!C$1,0) -> 0.005
B82: Binder ratio | C82: =VLOOKUP($B82,Inputs!$B$6:$M$309,Inputs!C$1,0) -> #N/A
B83: Binder purge volume | C83: =VLOOKUP($B83,Inputs!$B$6:$M$309,Inputs!C$1,0) -> 1.5 | D83: mL
B84: Purge frequency | C84: =VLOOKUP($B84,Inputs!$B$6:$M$309,Inputs!C$1,0) -> 16 | D84: layers
B85: Printhead life | C85: =VLOOKUP($B85,Inputs!$B$6:$M$309,Inputs!C$1,0) -> 4000 | D85: layers
B86: Wiper cartridge life | C86: =VLOOKUP($B86,Inputs!$B$6:$M$309,Inputs!C$1,0) -> 8000 | D86: layers
B87: Binder sponge life | C87: =VLOOKUP($B87,Inputs!$B$6:$M$309,Inputs!C$1,0) -> 10 | D87: L
B88: Printer XY border | C88: =VLOOKUP($B88,Inputs!$B$6:$M$309,Inputs!C$1,0) -> 4 | D88: mm
B89: Printer Z base plate | C89: =VLOOKUP($B89,Inputs!$B$6:$M$309,Inputs!C$1,0) -> 3 | D89: mm
B90: Printer XY spacing | C90: =VLOOKUP($B90,Inputs!$B$6:$M$309,Inputs!C$1,0) -> 1 | D90: mm
B91: Printer Z spacing | C91: =VLOOKUP($B91,Inputs!$B$6:$M$309,Inputs!C$1,0) -> 1 | D91: mm
B92: Crosslink time | C92: =VLOOKUP($B92,Inputs!$B$6:$M$309,Inputs!C$1,0) -> 26 | D92: hrs
B93: Printer builds / oven run | C93: =VLOOKUP($B93,Inputs!$B$6:$M$309,Inputs!C$1,0) -> 2
B94: DM furnace X-dim | C94: =VLOOKUP($B94,Inputs!$B$6:$M$309,Inputs!C$1,0) -> #N/A | D94: mm
B95: DM furnace Y-dim | C95: =VLOOKUP($B95,Inputs!$B$6:$M$309,Inputs!C$1,0) -> #N/A | D95: mm
B96: DM furnace Z-dim | C96: =VLOOKUP($B96,Inputs!$B$6:$M$309,Inputs!C$1,0) -> #N/A | D96: mm
B97: Furnace X-dim scaled | C97: =IF(furnace_sel="Shop",IF(OR(part_scale_x>dm_furnace_x,part_scale_y>dm_furnace_y),IF(AND(part_scale_y<=dm_furnace_x,part_scale_x<=dm_furnace_y),part_scale_y,"N.A."),part_scale_x),IF(OR(part_scale_x>Shop!mim_furnace_x,part_scale_y>Shop!mim_furnace_y),IF(AND(part_scale_y<=Shop!mim_furnace_x,part_scale_x<=Shop!mim_furnace_y),part_scale_y,"N.A."),part_scale_x)) -> #N/A
B98: Furnace Y-dim scaled | C98: =IF(C97=part_scale_x,part_scale_y,IF(C97=part_scale_y,part_scale_x,"N.A.")) -> #N/A
B99: Furnace Z-dim scaled | C99: =IF(OR(C97="N.A.",C98="N.A."),"N.A.",part_scale_z) -> #N/A
B100: Furnace XY spacing | C100: =VLOOKUP($B100,Inputs!$B$6:$M$309,Inputs!C$1,0) -> 5 | D100: mm
B101: Furnace Z spacing | C101: =VLOOKUP($B101,Inputs!$B$6:$M$309,Inputs!C$1,0) -> 2 | D101: mm
B102: Furnace rack + setter thickness | C102: =VLOOKUP($B102,Inputs!$B$6:$M$309,Inputs!C$1,0) -> 0 | D102: mm
...

Sheet P-1
A2: x | B2: =Shop!B2 -> #VALUE! | F2: PRODUCTION SYSTEM | K2: Privileged & DM Confidential | M2: x | N2: Production System part cost outputs
N3: DM equipment MSRP | P3: =G19+G34+G46+K47 -> #N/A | R3: ="Printed parts / "&C14&" build" -> Printed parts / P-1 build | T3: ='P-1'!parts_job -> 27
A4: x | B4: Part inputs (pre-scaling) | E4: x | F4: Printer usage calculation | I4: x | J4: Debind furnace part cost calculation | N4: =IF(C16="Shop","DM",IF('P-1'!furnace_sel<>"Continuous",C16&" cu ft MIM","Continuous"))&" furnace MSRP" -> 4 cu ft MIM furnace MSRP | P4: =K33+K14 -> #N/A | R4: Part nesting density | T4: =G16 -> 0.23023834
B5: X-dim (incl. supports) | C5: 22.1 | D5: mm | F5: Powder volume / part | G5: ='P-1'!part_vol_scale*'P-1'!bed_density -> 2341.2681 | H5: mm3 | J5: Debind furnace selection | K5: =K21 -> 4 | L5: ft3 | N5: Total equipment MSRP | P5: =SUM(P3:P4) -> #N/A
B6: Y-dim (incl. supports) | C6: 16 | D6: mm | F6: Powder mass / part | G6: =G5*density_selected*1000 -> 20.977762 | H6: g | J6: Furnace parts / run | K6: =K25 -> 3718 | N6: =C14&" printers required" -> P-1 printers required | P6: =G10 -> 1 | R6: Printer builds / week | T6: =T8/'P-1'!weeks_yr -> 105.65895
B7: Z-dim (incl. supports) | C7: 16 | D7: mm | F7: Powder mass / build | G7: =(G6*'P-1'!parts_job)/1000+(('P-1'!build_vol*'P-1'!bed_density*density_selected*'P-1'!powder_ratio)-(G6*'P-1'!parts_job)/1000)*'P-1'!powder_loss_percentage -> 0.6373693 | H7: kg | J7: Furnace loading parts / hour | K7: =K26 -> 240 | N7: Furnaces required | P7: =IF('P-1'!furnace_sel="Shop",K11,K31) -> 1 | R7: Printer builds / month | T7: =T6*4 -> 422.6358
B8: Part volume | C8: 2447 | D8: mm3 | F8: Binder volume / part | G8: ='P-1'!part_vol_scale*(1-'P-1'!bed_density)*'P-1'!binder_void_ratio -> 1248.6763 | H8: mm3 | J8: Run time + turnaround | K8: =6+K6/K7*1 -> 21.491667 | L8: hrs | R8: Printer builds / year | T8: ='P-1'!total_builds_yr -> 5071.6296
B9: Support volume | D9: mm3 | F9: Binder volume / build | G9: =G8*'P-1'!parts_job/10^6+('P-1'!build_layers/C84)*'P-1'!binder_purge_vol/1000 -> 0.06891426 | H9: L | J9: Time per printer build | K9: =('P-1'!good_parts_job/K6*K8) -> 0.15607181 | L9: hrs | N9: Operating part costs
B10: Part + support volume | C10: =part_only_vol+support_vol -> 2447 | D10: mm3 | F10: Printers required (rounded) | G10: =ROUNDUP('P-1'!part_req/'P-1'!part_capacity,0) -> 1 | J10: Build capacity / year | K10: =ROUNDDOWN('P-1'!total_hours_yr/K9,0) -> 51668 | N10: Printed part cost | P10: =P32+P33+P35+P36 -> 1.6835833 | R10: =IF($C$15="Yes","Sintered","Green")&" parts / week" -> Sintered parts / week | T10: =T12/'P-1'!weeks_yr -> 2852.7917
F11: Printer utilization | G11: ='P-1'!part_req/'P-1'!good_parts_job*'P-1'!print_time_trn -> 3840.0125 | H11: hrs | J11: Runs / year | K11: =K30 -> 37 | N11: =IF(C15="Yes","Sintered","Green")&" part cost" -> Sintered part cost | P11: =T37-T34 -> #N/A | R11: =IF($C$15="Yes","Sintered","Green")&" parts / month" -> Sintered parts / month | T11: =T10*4 -> 11411.167
A12: x | B12: Build inputs & process capacity | F12: Builds / year | G12: ='P-1'!part_req/'P-1'!good_parts_job -> 5071.6296 | J12: Debind furnaces required (rounded) | K12: =ROUNDUP('P-1'!total_builds_yr/K10,0) -> 1 | N12: =N10&" / cc" -> Printed part cost / cc | P12: =P10/part_only_vol*10^3 -> 0.68801935 | R12: =IF($C$15="Yes","Sintered","Green")&" parts / year" -> Sintered parts / year | T12: ='P-1'!part_req -> 136934
B13: Configuration | C13: Flex | F13: Builds / month | G13: =G12/12 -> 422.6358 | J13: Debind furnace utilization | K13: =K8*K11 -> 795.19167 | L13: hrs | N13: =N11&" / cc" -> Sintered part cost / cc | P13: =P11/part_only_vol*10^3 -> #N/A
B14: Build box size | C14: P-1 | F14: Printer utilization (% of available) | G14: =G11/('P-1'!avail_hours_yr*G10) -> 1.0000033 | J14: Debind furnace investment | K14: =OFFSET(C131,'P-1'!furnace_index-1,)*K12 -> #N/A | R14: ="Printer util (QTY: "&G10&")" -> Printer util (QTY: 1) | T14: =G14 -> 1.0000033
B15: Include sintering? | C15: Yes | F15: Printer utilization (% 24x7) | G15: =G11/(24*7*52*G10) -> 0.43956188 | J15: Annual depreciation (@ 7 yrs) | K15: =K14/furnace_depr+OFFSET(C136,'P-1'!furnace_index-1,)*K12*floor_rate -> #N/A | N15: Fully burdened part costs | R15: ="Crosslink util (QTY: "&1&")" -> Crosslink util (QTY: 1) | T15: =G33/('P-1'!total_hours_yr*uptime) -> 0.32221787
B16: Furnace selection | C16: 4 | D16: =IF(C16="Shop",,"ft3") -> ft3 | F16: Nesting density | G16: ='P-1'!part_vol_scale*'P-1'!parts_job/'P-1'!build_vol -> 0.23023834 | J16: Depreciation $ / part | K16: =IF('P-1'!furnace_sel="Continuous",0,K13/('P-1'!total_hours_yr*K12)*K15/'P-1'!part_req) -> #N/A | N16: Printed part cost | P16: =SUM(P32:P36) -> #N/A | R16: ="Depowder util (QTY: "&G44&")" -> Depowder util (QTY: 2) | T16: =G45/('P-1'!avail_hours_yr*G44*uptime) -> 0.68678318
B17: Debind | C17: Integrated | J17: Labor $ / part | K17: =IF('P-1'!furnace_sel="Continuous",0,'P-1'!labor_rate*K11*(K8-6)/'P-1'!part_req) -> 0.083717947 | N17: =IF(C15="Yes","Sintered","Green")&" part cost" -> Sintered part cost | P17: =T45 -> #N/A | R17: ="Furnace util (QTY: "&IF('P-1'!furnace_sel="Shop",K11,K31)&")" -> Furnace util (QTY: 1) | T17: =K32/('P-1'!total_hours_yr*K31*uptime) -> 0.16284619
B18: Limit furnace to QTY 1 | C18: No | E18: x | F18: Printer part cost calculation | J18: Utilities / part | K18: =IF('P-1'!furnace_sel="Continuous",0,(furnace_gas_cons*'P-1'!nitrogen_rate+furnace_power_cons*'P-1'!power_rate)*(K13-K6/K7*2*K11))/'P-1'!part_req -> -0.027954994 | N18: Printed part cost / cc | P18: =P16/part_only_vol*10^3 -> #N/A
B19: Nested parts / job | C19: =MAX(ROUNDDOWN(('P-1'!build_x-'P-1'!printer_xy_border*2+'P-1'!printer_xy_spacing)/('P-1'!part_scale_x+'P-1'!printer_xy_spacing),0)*ROUNDDOWN(('P-1'!build_y-'P-1'!printer_xy_border*2+'P-1'!printer_xy_spacing)/('P-1'!part_scale_y+'P-1'!printer_xy_spacing),0),ROUNDDOWN(('P-1'!build_x-'P-1'!printer_xy_border*2+'P-1'!printer_xy_spacing)/('P-1'!part_scale_y+'P-1'!printer_xy_spacing),0)*ROUNDDOWN(('P-1'!build_y-'P-1'!printer_xy_border*2+'P-1'!printer_xy_spacing)/('P-1'!part_scale_x+'P-1'!printer_xy_spacing),0))*ROUNDDOWN(('P-1'!build_z-'P-1'!printer_z_base+'P-1'!printer_z_spacing)/('P-1'!part_scale_z+'P-1'!printer_z_spacing),0) -> 27 | F19: Printer investment (incl. build box) | G19: =G10*'P-1'!printer_msrp+ROUNDUP(('P-1'!print_time_trn+G30+G42)/('P-1'!avail_hours_yr/'P-1'!total_builds_yr),0)*'P-1'!buildbox_msrp -> #N/A | N19: =IF(C15="Yes","Sintered","Green")&" part cost / cc" -> Sintered part cost / cc | P19: =P17/part_only_vol*10^3 -> #N/A | R19: Labor hrs / year | T19: =print_trnaround*'P-1'!total_builds_yr+0.5*'P-1'!total_builds_yr/2+G45+(K27-'P-1'!furnace_time_cycle)*K30+IF('P-1'!furnace_sel<>"Continuous",(K8-6)*K11,0) -> 10224.6
B20: Build height | C20: ='P-1'!printer_z_base+('P-1'!part_scale_z)*ROUNDDOWN(('P-1'!build_z-'P-1'!printer_z_base+'P-1'!printer_z_spacing)/('P-1'!part_scale_z+'P-1'!printer_z_spacing),0)+'P-1'!printer_z_spacing*(ROUNDDOWN(('P-1'!build_z-'P-1'!printer_z_base+'P-1'!printer_z_spacing)/('P-1'!part_scale_z+'P-1'!printer_z_spacing),0)-1) -> 22.88 | D20: mm | F20: ="Annual depreciation (@ "&dm_depr&" yrs)" -> Annual depreciation (@ 7 yrs) | G20: =G19/dm_depr+(5*1.9+1.4*1)*G10*floor_rate -> #N/A | I20: x | J20: MIM furnace part cost calculation | N20: Notes & assumptions:
B21: Override nesting | C21: No | F21: Powder $ / part | G21: =(G7*IF(OR('P-1'!powder_price="",'P-1'!powder_price=0),powder_default_price,'P-1'!powder_price)/'P-1'!good_parts_job) -> 0.89703828 | J21: MIM furnace selection | K21: =C16 -> 4 | L21: =IF(OR('P-1'!furnace_sel="Shop",'P-1'!furnace_sel="Continuous"),,"ft3") -> ft3 | N21: 1. Pricing is not final unless on an official DM quote and is subject to change. Does not include installation, training, shipping, or taxes.
B22: Override parts / job | C22: 0 | F22: Binder $ / part | G22: =G9*binder_weighted_price/'P-1'!good_parts_job -> 0.382857 | J22: Furnace X-dim | K22: =IF('P-1'!furnace_sel="Continuous","N.A.",C109) -> 420 | L22: mm | N22: ="2. DM Equipment MSRP includes "&ROUNDUP(('P-1'!print_time_trn+G30+G42)/('P-1'!avail_hours_yr/'P-1'!total_builds_yr),0)&" build boxes & transfer cart." -> 2. DM Equipment MSRP includes 7 build boxes & transfer cart.
B23: Override build height | C23: 0 | D23: mm | F23: Depreciation $ / part | G23: =G11/('P-1'!avail_hours_yr*G10)*G20/'P-1'!part_req -> #N/A | J23: Furnace Y-dim | K23: =IF('P-1'!furnace_sel="Continuous","N.A.",C110) -> 610 | L23: mm | N23: ="3. Consumables includes printheads"&IF('P-1'!furnace_sel="Continuous"," and continuous furnace items.",".") -> 3. Consumables includes printheads.
B24: Layer thickness | C24: 0.065 | D24: mm | F24: Consumables $ / part | G24: =(G9/'P-1'!printhead_life*'P-1'!printhead_msrp)/'P-1'!good_parts_job -> 0.013507195 | J24: Furnace Z-dim | K24: =IF('P-1'!furnace_sel="Continuous","N.A.",C111) -> 460 | L24: mm | N24: 4. Includes utilities costs for gas (as required), electricity, and floorspace.
B25: Layers | C25: =ROUNDUP('P-1'!build_height/C24,0) -> 352 | F25: Labor $ / part | G25: =print_trnaround*'P-1'!labor_rate/'P-1'!good_parts_job -> 0.37037037 | J25: Furnace parts / run | K25: =IF('P-1'!furnace_sel="Continuous",'P-1'!part_req,ROUNDDOWN(('P-1'!mim_furnace_x+'P-1'!furnace_xy_spacing)/('P-1'!furnace_part_scale_x+'P-1'!furnace_xy_spacing),0)*ROUNDDOWN(('P-1'!mim_furnace_y+'P-1'!furnace_xy_spacing)/('P-1'!furnace_part_scale_y+'P-1'!furnace_xy_spacing),0)*MIN('P-1'!furnace_shelves,ROUNDDOWN('P-1'!mim_furnace_z/('P-1'!furnace_part_scale_z+furnace_rack_thickness+'P-1'!furnace_z_spacing),0))) -> 3718 | N25: ="5. "&C41&" powder priced at "&TEXT(IF('P-1'!powder_price="",C43,'P-1'!powder_price),"$0.00")&"/kg and binder priced at "&TEXT('P-1'!binder_price,"$0.00")&"/L. Pricing may be volume dependent." -> 5. Cu powder priced at $38.00/kg and binder priced at $150.00/L. Pricing may be volume dependent.
B26: ="Print time + "&print_trnaround&"hrs turnaround" -> Print time + 0.5hrs turnaround | C26: =C25*'P-1'!layer_speed/(60*60)+print_trnaround -> 0.75715556 | D26: hrs | F26: Utilities $ / part | G26: =('P-1'!power_rate*IF('P-1'!p_model="P-1",9,13)*('P-1'!print_time_trn-print_trnaround))/'P-1'!good_parts_job+'P-1'!nitrogen_rate*1000*('P-1'!print_time_trn-print_trnaround)/'P-1'!good_parts_job -> 0.019810502 | J26: Furnace loading parts / hour | K26: =C51 -> 240 | N26: ="6. Key process assumptions: (i) "&C24*1000&" micron printed layer height; (ii) $"&'P-1'!labor_rate&"/hr labor rate; (iii) Printer, depowdering, and powder handling equipment @ "&C31&" x "&C32&" x "&'P-1'!weeks_yr&" x "&uptime*100&"% uptime" -> 6. Key process assumptions: (i) 65 micron printed layer height; (ii) $20/hr labor rate; (iii) Printer, depowdering, and powder handling equipment @ 16 x 5 x 48 x 100% uptime
B27: Overall process yield | C27: 1 | J27: Run time + turnaround | K27: =IF('P-1'!furnace_sel="Continuous",'P-1'!furnace_time_cycle+K25/K26*2,'P-1'!furnace_time_cycle+K25/K26*1) -> 35.491667 | L27: hrs | O27: =" (iv) "&G41&" parts/hr depowdering rate; (v) "&'P-1'!total_yield*100&"% overall process yield; (vi) "&dm_depr&"yr DM equipment depreciation;" -> (iv) 50 parts/hr depowdering rate; (v) 100% overall process yield; (vi) 7yr DM equipment depreciation;
B28: Good parts / job | C28: =IF('P-1'!override_nesting="Yes",IF(C22=0,C19,C22),C19)*C27 -> 27 | E28: x | F28: Crosslink part cost calculation | J28: Time per printer build | K28: ='P-1'!good_parts_job/K25*K27 -> 0.25773938 | L28: hrs | O28: =" (vii) Crosslink station "&IF(C15="Yes","& sintering ",)&"equipment @ 24 x 7 x "&'P-1'!weeks_yr&" x "&uptime*100&"% uptime; (viii) "&IF(C15="Yes",furnace_depr&"yr MIM furnace depreciation; (iv) ",)&'P-1'!total_yield*100&"% overall process yield" -> (vii) Crosslink station & sintering equipment @ 24 x 7 x 48 x 100% uptime; (viii) 10yr MIM furnace depreciation; (iv) 100% overall process yield
F29: =IF('P-1'!p_model="P-50","Printer builds / day","Printer builds / oven run") -> Printer builds / oven run | G29: =C93 -> 6 | J29: Build capacity / year | K29: =IF('P-1'!furnace_sel="Continuous",(240000/2.2)/('P-1'!good_parts_job*'P-1'!part_vol*density_selected),ROUNDDOWN('P-1'!total_hours_yr/K28,0)) -> 31287
A30: x | B30: Printer operations inputs | F30: ="Dry time + "&'P-1'!xlink_trnaround&"hrs turnaround" -> Dry time + 0.5hrs turnaround | G30: =C92*'P-1'!build_height/'P-1'!build_z+'P-1'!xlink_trnaround -> 3.074 | H30: hrs | J30: Runs / year | K30: =ROUNDUP('P-1'!part_req/K25,0) -> 37
B31: Hours / day | C31: 16 | F31: Build capacity / year | G31: =ROUNDDOWN(G29*'P-1'!total_hours_yr/G30,0) -> 15739 | J31: MIM furnaces required (rounded) | K31: =ROUNDUP('P-1'!total_builds_yr/K29,0) -> 1 | N31: ="Production System "&'P-1'!p_model&" "&LOWER(N11)&" allocation" -> Production System P-1 sintered part cost allocation | V31: Cost model template output
B32: Days / week | C32: 5 | F32: Ovens required (rounded) | G32: =ROUNDUP('P-1'!total_builds_yr/G31,0) -> 1 | J32: MIM furnace utilization | K32: =IF('P-1'!furnace_sel="Continuous",'P-1'!total_hours_yr,K27*K30) -> 1313.1917 | L32: hrs | N32: Printer | O32: Raw materials | P32: =G21+G22 -> 1.2798953 | R32: Total | S32: Raw Materials | T32: =SUMIF($O$32:$O$49,S32,$P$32:$P$49) -> 1.2798953 | V32: Parts per build | Y32: ='P-1'!parts_job -> 27
B33: Weeks / year | C33: 48 | F33: Crosslink utilization | G33: ='P-1'!total_builds_yr*G30/G29 -> 2598.3649 | H33: hrs | J33: MIM furnace investment | K33: =IFERROR(OFFSET(C126,'P-1'!furnace_index-1,)*K31,"N.A.") -> N.A. | N33: Printer | O33: Consumables | P33: =G24 -> 0.013507195 | S33: Consumables | T33: =SUMIF($O$32:$O$49,S33,$P$32:$P$49) -> 0.013507195 | V33: Nesting density | Y33: =G16 -> 0.23023834
B34: Printer available hours / year | C34: =C31*C32*'P-1'!weeks_yr -> 3840 | F34: Crosslink investment | G34: =G32*'P-1'!xlink_msrp -> #N/A | J34: ="Annual depreciation (@ "&furnace_depr&" yrs)" -> Annual depreciation (@ 10 yrs) | K34: =IFERROR(K33/furnace_depr+OFFSET(C136,'P-1'!furnace_index-1,)*K31*floor_rate,"N.A.") -> N.A. | N34: Printer | O34: Depreciation | P34: =G23 -> #N/A | S34: Depreciation | T34: =SUMIF($O$32:$O$49,S34,$P$32:$P$49) -> #N/A | V34: Parts per furnace run | Y34: =IF('P-1'!furnace_sel="Continuous","N.A.",K25) -> 3718
B35: Printer & furnace uptime | C35: 1 | F35: ="Annual depreciation (@ "&dm_depr&" yrs)" -> Annual depreciation (@ 7 yrs) | G35: =G34/dm_depr -> #N/A | J35: Depreciation / part | K35: =IFERROR(K32/('P-1'!total_hours_yr*K31)*K34/'P-1'!part_req,"N.A.") -> N.A. | N35: Printer | O35: Labor | P35: =G25 -> 0.37037037 | S35: Labor | T35: =SUMIF($O$32:$O$49,S35,$P$32:$P$49) -> 1.5193545 | V35: Builds per furnace run | Y35: =IFERROR(Y34/C19,"N.A.") -> 137.7037
B36: Printer uptime hours / year | C36: ='P-1'!avail_hours_yr*uptime -> 3840 | F36: Depreciation $ / part | G36: =G33/('P-1'!total_hours_yr*G32)*G35/'P-1'!part_req -> #N/A | J36: Consumables / part | K36: =IF('P-1'!furnace_sel="Continuous",furnace_power_cons*'P-1'!total_hours_yr/'P-1'!part_req,0) -> 0 | N36: Printer | O36: Utilities | P36: =G26 -> 0.019810502 | S36: Utilities | T36: =SUMIF($O$32:$O$49,S36,$P$32:$P$49) -> 0.046043691 | V36: Parts per week | Y36: =Y37/'P-1'!weeks_yr -> 2852.7917
B37: Good parts / printer / year | C37: =ROUND('P-1'!good_parts_job/'P-1'!print_time_trn*uptime_hours_yr,0) -> 136934 | F37: Labor $ / part | G37: =('P-1'!xlink_trnaround/G29*'P-1'!labor_rate*'P-1'!total_builds_yr)/'P-1'!part_req -> 0.061728395 | J37: Labor $ / part | K37: =IF('P-1'!furnace_sel="Continuous",'P-1'!labor_rate*'P-1'!part_req/K26,'P-1'!labor_rate*K30*(K27-C113))/'P-1'!part_req -> 0.083717947 | N37: Crosslink | O37: Depreciation | P37: =G36 -> #N/A | S37: Total | T37: =SUM(T32:T36) -> #N/A | V37: Parts per year | Y37: ='P-1'!part_req -> 136934
B38: Parts required / year | C38: ='P-1'!part_capacity -> 136934 | F38: Utilities $ / part | G38: =('P-1'!power_rate*5*G33+'P-1'!nitrogen_rate*120*G33)/'P-1'!part_req -> 0.013662222 | J38: Utilities / part | K38: =IF('P-1'!furnace_sel="Continuous",furnace_gas_cons*'P-1'!total_hours_yr,(argon_rate*furnace_gas_cons+'P-1'!power_rate*furnace_power_cons)*(K27-K25/K26*2)*K30)/'P-1'!part_req -> 0.015653432 | N38: Crosslink | O38: Labor | P38: =G37 -> 0.061728395 | V38: Operating part cost | Y38: =P11 -> #N/A
N39: Crosslink | O39: Utilities | P39: =G38 -> 0.013662222 | R39: Total | S39: Raw Materials | T39: =P32 -> 1.2798953 | V39: Operating cost / cc | Y39: =P13 -> #N/A
A40: x | B40: Cost & other inputs | E40: x | F40: Depowder part cost calculation | I40: x | J40: Powder blender part cost calculation | N40: Depowder | O40: Depreciation | P40: =G48 -> #N/A | S40: Printer | T40: =SUMIF($N$33:$N$49,S40,$P$33:$P$49) -> #N/A | V40: Fully burdened part cost | Y40: =P17 -> #N/A
B41: Material selection | C41: Cu | F41: Depowdered parts / hour | G41: =C50 -> 50 | J41: Powder blender capacity | K41: 35 | L41: kg | N41: Depowder | O41: Labor | P41: =G49 -> 0.77037037 | S41: Crosslink | T41: =SUMIF($N$33:$N$49,S41,$P$33:$P$49) -> #N/A | V41: Fully burdened cost / cc | Y41: =P19 -> #N/A
B42: Powder MSRP | D42: $/kg | F42: ="Depowder time + "&'P-1'!depowder_trnaround&"hrs turnaround" -> Depowder time + 0.5hrs turnaround | G42: ='P-1'!parts_job/G41+'P-1'!depowder_trnaround -> 1.04 | H42: hrs | J42: ="Blend time + "&'P-1'!powder_trnaround&"hrs turnaround" -> Blend time + 0.5hrs turnaround | K42: =1+'P-1'!powder_trnaround -> 1.5 | L42: hrs | N42: Depowder | O42: Utilities | P42: =G50 -> 0.023688889 | S42: Depowder | T42: =SUMIF($N$33:$N$49,S42,$P$33:$P$49) -> #N/A | V42: Printer utilization | Y42: =T14 -> 1.0000033
B43: Powder MSRP default | C43: {=+INDEX(C154:C163,VLOOKUP(C41,B141:F151,5,0))} -> 38 | D43: $/kg | F43: Build capacity / year | G43: =ROUNDDOWN(uptime_hours_yr/G42,0) -> 3692 | J43: Powder capacity / year | K43: =K41*uptime_hours_yr/K42 -> 89600 | L43: kg | N43: Furnace | O43: Consumables | P43: =IF(C15="No",0,IF(C16="Continuous",K36,)) | S43: Furnace | T43: =SUMIF($N$33:$N$49,S43,$P$33:$P$49) -> #N/A | V43: Furnace utilization | Y43: =T17 -> 0.16284619
B44: Binder MSRP | C44: =IF(binder_per_yr>F166,C168,IF(binder_per_yr>F165,C167,C166)) -> 150 | D44: $/L | F44: Depowders required (rounded) | G44: =ROUNDUP('P-1'!total_builds_yr/G43,0) -> 2 | J44: Loose powder / build | K44: =('P-1'!build_vol*'P-1'!bed_density*'P-1'!powder_ratio*density_selected-G7) -> 14.122976 | L44: kg | N44: Furnace | O44: Depreciation | P44: =IF(C15="No",0,K35+IF($C$16<>"Continuous",K16,0)) -> #N/A | S44: Blender | T44: =SUMIF($N$33:$N$49,S44,$P$33:$P$49) -> #N/A
B45: Printheads MSRP | C45: =VLOOKUP(B45,Inputs!$B$6:$M$311,Inputs!L$1,0) -> 13230 | F45: Depowder utilization | G45: ='P-1'!total_builds_yr*G42 -> 5274.4948 | H45: hrs | J45: Blenders required (rounded) | K45: =ROUNDUP('P-1'!total_builds_yr*K44/K43,0) -> 1 | N45: Furnace | O45: Labor | P45: =IF(C15="No",0,K37+IF($C$16<>"Continuous",K17,0)) -> 0.16743589 | S45: Total | T45: =SUM(T39:T44) -> #N/A
B46: Region | C46: NAM | F46: Depowder investment | G46: =G44*'P-1'!depowder_msrp -> #N/A | J46: Powder blender utilization (hrs) | K46: ='P-1'!total_builds_yr*K44/K41*K42 -> 3069.7074 | L46: hrs | N46: Furnace | O46: Utilities | P46: =IF(C15="No",0,K38+IF($C$16<>"Continuous",K18,0)) -> -0.012301562
F47: ="Annual depreciation (@ "&dm_depr&" yrs)" -> Annual depreciation (@ 7 yrs) | G47: =G46/dm_depr+(2.7*1.2)*G44*floor_rate -> #N/A | J47: Powder blender investment | K47: ='P-1'!blender_msrp*K45 -> #N/A | N47: Blender | O47: Depreciation | P47: =K49 -> #N/A
A48: x | B48: Labor & equipment inputs | F48: Depreciation $ / part | G48: =G45/('P-1'!avail_hours_yr*G44)*G47/'P-1'!part_req -> #N/A | J48: ="Annual depreciation (@ "&dm_depr&" yrs)" -> Annual depreciation (@ 7 yrs) | K48: =K47/dm_depr+(0.8*0.8)*K45*floor_rate -> #N/A | N48: Blender | O48: Labor | P48: =K50 -> 0.14944948
B49: Labor rate | C49: 20 | D49: $/hr | F49: Labor $ / part | G49: =G42*'P-1'!labor_rate*'P-1'!total_builds_yr/'P-1'!part_req -> 0.77037037 | J49: Depreciation $ / part | K49: =K46/('P-1'!avail_hours_yr*K45)*K48/'P-1'!part_req -> #N/A | N49: Blender | O49: Utilities | P49: =K51 -> 0.0011836399
B50: Depowdering parts / hour | C50: 50 | F50: Utilities $ / part | G50: ='P-1'!power_rate*5*G45/'P-1'!part_req+'P-1'!nitrogen_rate*15*G42/'P-1'!good_parts_job -> 0.023688889 | J50: Labor $ / part | K50: ='P-1'!total_builds_yr*K44/K41*'P-1'!powder_trnaround*'P-1'!labor_rate/'P-1'!part_req -> 0.14944948
B51: Furnace loading parts / hour | C51: =IF('P-1'!p_model="P-50",600,240) -> 240 | J51: Utilities / part | K51: =0.66*'P-1'!power_rate*('P-1'!total_builds_yr*K44/K41)/'P-1'!part_req -> 0.0011836399
B52: DM equipment depreciation | C52: 7 | D52: yrs
B53: MIM furnace depreciation | C53: 10 | D53: yrs
B54: Nitrogen rate | C54: 0.001 | D54: $/L
B55: Argon rate | C55: 0.0025 | D55: $/L
B56: Power rate | C56: 0.12 | D56: $/kWh
B57: Floorspace rate / year | C57: 160 | D57: $/m2
A60: x | B60: Parts required / year | C60: =IF(C18="No",IF(C38<>"",C38,'P-1'!part_capacity),MIN('P-1'!part_capacity,K29*'P-1'!good_parts_job)) -> 136934
B61: X-scale | C61: =VLOOKUP($B61,Inputs!$B$6:$M$309,Inputs!L$1,0) -> 1.16
B62: Y-scale | C62: =VLOOKUP($B62,Inputs!$B$6:$M$309,Inputs!L$1,0) -> 1.165
B63: Z-scale | C63: =VLOOKUP($B63,Inputs!$B$6:$M$309,Inputs!L$1,0) -> 1.18
B64: Layer speed | C64: =VLOOKUP($B64,Inputs!$B$6:$M$309,Inputs!L$1,0) -> 2.63 | D64: sec
B65: X-dim scaled | C65: ='P-1'!part_x*'P-1'!x_scale -> 25.636 | D65: mm
B66: Y-dim scaled | C66: ='P-1'!part_y*'P-1'!y_scale -> 18.64 | D66: mm
B67: Z-dim scaled | C67: ='P-1'!part_z*'P-1'!z_scale -> 18.88 | D67: mm
B68: Volume scaled | C68: ='P-1'!part_vol*'P-1'!x_scale*'P-1'!y_scale*'P-1'!z_scale -> 3902.1134 | D68: mm3
B69: Parts / job | C69: =IF('P-1'!override_nesting="Yes",IF(OR(C22=0,C23=0),C19,C22),C19) -> 27
B70: Bed density | C70: =VLOOKUP($B70,Inputs!$B$6:$M$309,Inputs!L$1,0) -> 0.6
B71: Build box X-dim | C71: =VLOOKUP($B71,Inputs!$B$6:$M$309,Inputs!L$1,0) -> 200 | D71: mm
B72: Build box Y-dim | C72: =VLOOKUP($B72,Inputs!$B$6:$M$309,Inputs!L$1,0) -> 100 | D72: mm
B73: Build box Z-dim | C73: =VLOOKUP($B73,Inputs!$B$6:$M$309,Inputs!L$1,0) -> 40 | D73: mm
B74: Build height | C74: =IF('P-1'!override_nesting="Yes",IF(OR(C22=0,C23=0),C20,C23),C20) -> 22.88 | D74: mm
B75: Build box volume | C75: ='P-1'!build_x*'P-1'!build_y*'P-1'!build_height -> 457600 | D75: mm3
B76: Print turnaround time | C76: =VLOOKUP($B76,Inputs!$B$6:$M$309,Inputs!L$1,0) -> 0.5 | D76: hrs
B77: Crosslink turnaround time | C77: =VLOOKUP($B77,Inputs!$B$6:$M$309,Inputs!L$1,0) -> 0.5 | D77: hrs
B78: Depowder turnaround time | C78: =VLOOKUP($B78,Inputs!$B$6:$M$309,Inputs!L$1,0) -> 0.5 | D78: hrs
B79: Powder blender turnaround time | C79: =VLOOKUP($B79,Inputs!$B$6:$M$309,Inputs!L$1,0) -> 0.5 | D79: hrs
B80: Powder + overflow ratio | C80: =VLOOKUP($B80,Inputs!$B$6:$M$309,Inputs!L$1,0) -> 6
B81: Powder loss percentage | C81: =VLOOKUP($B81,Inputs!$B$6:$M$309,Inputs!L$1,0) -> 0.005
B82: Binder void ratio | C82: =VLOOKUP($B82,Inputs!$B$6:$M$309,Inputs!L$1,0) -> 0.8
B83: Binder purge volume | C83: =VLOOKUP($B83,Inputs!$B$6:$M$309,Inputs!L$1,0) -> 5 | D83: mL
B84: Purge frequency | C84: =VLOOKUP($B84,Inputs!$B$6:$M$309,Inputs!L$1,0) -> 50 | D84: layers
B85: Printhead life | C85: =VLOOKUP($B85,Inputs!$B$6:$M$309,Inputs!L$1,0) -> 2500 | D85: L
B88: Printer XY border | C88: =VLOOKUP($B88,Inputs!$B$6:$M$309,Inputs!L$1,0) -> 8.5 | D88: mm
B89: Printer Z base plate | C89: =VLOOKUP($B89,Inputs!$B$6:$M$309,Inputs!L$1,0) -> 4 | D89: mm
B90: Printer XY spacing | C90: =VLOOKUP($B90,Inputs!$B$6:$M$309,Inputs!L$1,0) -> 1 | D90: mm
B91: Printer Z spacing | C91: =VLOOKUP($B91,Inputs!$B$6:$M$309,Inputs!L$1,0) -> 0.4 | D91: mm
B92: Crosslink time | C92: =VLOOKUP($B92,Inputs!$B$6:$M$309,Inputs!L$1,0) -> 4.5 | D92: hrs
B93: Printer builds / oven run | C93: =VLOOKUP($B93,Inputs!$B$6:$M$309,Inputs!L$1,0) -> 6
B97: Furnace X-dim scaled | C97: =IF('P-1'!furnace_sel="Shop",IF(OR('P-1'!part_scale_x>dm_furnace_x,'P-1'!part_scale_y>dm_furnace_y),IF(AND('P-1'!part_scale_y<=dm_furnace_x,'P-1'!part_scale_x<=dm_furnace_y),'P-1'!part_scale_y,"N.A."),'P-1'!part_scale_x),IF(OR('P-1'!part_scale_x>'P-1'!mim_furnace_x,'P-1'!part_scale_y>'P-1'!mim_furnace_y),IF(AND('P-1'!part_scale_y<='P-1'!mim_furnace_x,'P-1'!part_scale_x<='P-1'!mim_furnace_y),'P-1'!part_scale_y,"N.A."),'P-1'!part_scale_x)) -> 25.636
B98: Furnace Y-dim scaled | C98: =IF(C97='P-1'!part_scale_x,'P-1'!part_scale_y,IF(C97='P-1'!part_scale_y,'P-1'!part_scale_x,"N.A.")) -> 18.64
B99: Furnace Z-dim scaled | C99: =IF(OR(C97="N.A.",C98="N.A."),"N.A.",'P-1'!part_scale_z) -> 18.88 | G99: 5 ovens for 24/7 on Flex
B100: Furnace XY spacing | C100: =VLOOKUP($B100,Inputs!$B$6:$M$309,Inputs!L$1,0) -> 5 | D100: mm | G100: 3 people for depowder + ppu + printer - 24/7
B101: Furnace Z spacing | C101: =VLOOKUP($B101,Inputs!$B$6:$M$309,Inputs!L$1,0) -> 2 | D101: mm
B102: Furnace rack + setter thickness | C102: =VLOOKUP($B102,Inputs!$B$6:$M$309,Inputs!L$1,0) -> 2.6 | D102: mm
B106: Total hours / year | C106: =24*7*'P-1'!weeks_yr -> 8064
A108: x | B108: MIM furnace index | C108: =VLOOKUP('P-1'!furnace_sel,$B$126:$E$130,3,0) -> 2
B109: MIM furnace X-dim | C109: =CHOOSE(C$108,305,420,420,420,999999,"N.A.") -> 420 | D109: mm
B110: MIM furnace Y-dim | C110: =CHOOSE(C$108,610,610,915,1524,999999,"N.A.") -> 610 | D110: mm
B111: MIM furnace Z-dim | C111: =CHOOSE(C$108,305,460,460,460,999999,"N.A.") -> 460 | D111: mm
B112: MIM furnace shelves | C112: 11
...

Sheet P-50 Base
A2: x | B2: =Shop!B2 -> #VALUE! | F2: PRODUCTION SYSTEM | K2: Privileged & DM Confidential | M2: x | N2: Production System part cost outputs
N3: DM equipment MSRP | P3: =G19+G34+G46+K41*'P-50 Base'!ppu_msrp -> 2050000 | R3: ="Printed parts / "&C14&" build" -> Printed parts / P-50 build | T3: ='P-50 Base'!parts_job -> 819
A4: x | B4: Part inputs (pre-scaling) | E4: x | F4: Printer usage calculation | I4: x | J4: Debind furnace part cost calculation | N4: =IF(C16="Shop","DM",IF('P-50 Base'!furnace_sel<>"Continuous",C16&" cu ft MIM","Continuous"))&" furnace MSRP" -> 6 cu ft MIM furnace MSRP | P4: =K33+K14 -> 3200000 | R4: Part nesting density | T4: =G16 -> 0.15656663
B5: X-dim (incl. supports) | C5: 40 | D5: mm | F5: Powder volume / part | G5: ='P-50 Base'!part_vol_scale*'P-50 Base'!bed_density -> 5230.4015 | H5: mm3 | J5: Debind furnace selection | K5: =K21 -> 6 | L5: ft3 | N5: Total equipment MSRP | P5: =SUM(P3:P4) -> 5250000
B6: Y-dim (incl. supports) | C6: 40 | D6: mm | F6: Powder mass / part | G6: =G5*'P-50 Base'!density_selected*1000 -> 41.843212 | H6: g | J6: Furnace parts / run | K6: =K25 -> 1496 | N6: =C14&" printers required" -> P-50 printers required | P6: =G10 -> 1 | R6: Printer builds / week | T6: =T8/'P-50 Base'!weeks_yr -> 46.420813
B7: Z-dim (incl. supports) | C7: 15 | D7: mm | F7: Powder mass / build | G7: =(G6*'P-50 Base'!parts_job)/1000+(('P-50 Base'!build_vol*'P-50 Base'!bed_density*'P-50 Base'!density_selected*'P-50 Base'!powder_ratio)-(G6*'P-50 Base'!parts_job)/1000)*'P-50 Base'!powder_loss_percentage -> 35.548612 | H7: kg | J7: Furnace loading parts / hour | K7: =K26 -> 600 | N7: Furnaces required | P7: =IF('P-50 Base'!furnace_sel="Shop",K11,K31) -> 4 | R7: Printer builds / month | T7: =T6*4 -> 185.68325
B8: Part volume | C8: 5466.607 | D8: mm3 | F8: Binder volume / part | G8: ='P-50 Base'!part_vol_scale*(1-'P-50 Base'!bed_density)*'P-50 Base'!binder_void_ratio -> 2440.854 | H8: mm3 | J8: Run time + turnaround | K8: =6+K6/K7*1 -> 8.4933333 | L8: hrs | R8: Printer builds / year | T8: ='P-50 Base'!total_builds_yr -> 2228.199
B9: Support volume | D9: mm3 | F9: Binder volume / build | G9: =G8*'P-50 Base'!parts_job/10^6+('P-50 Base'!build_layers/C84)*'P-50 Base'!binder_purge_vol/1000 -> 2.7526594 | H9: L | J9: Time per printer build | K9: =('P-50 Base'!good_parts_job/K6*K8) -> 4.6497594 | L9: hrs | N9: Operating part costs
B10: Part + support volume | C10: ='P-50 Base'!part_only_vol+'P-50 Base'!support_vol -> 5466.607 | D10: mm3 | F10: Printers required (rounded) | G10: =ROUNDUP('P-50 Base'!part_req/'P-50 Base'!part_capacity,0) -> 1 | J10: Build capacity / year | K10: =ROUNDDOWN('P-50 Base'!total_hours_yr/K9,0) -> 1734 | N10: Printed part cost | P10: =P32+P33+P35+P36 -> 1.2670551 | R10: =IF($C$15="Yes","Sintered","Green")&" parts / week" -> Sintered parts / week | T10: =T12/'P-50 Base'!weeks_yr -> 38018.646
F11: Printer utilization | G11: ='P-50 Base'!part_req/'P-50 Base'!good_parts_job*'P-50 Base'!print_time_trn -> 8064.0008 | H11: hrs | J11: Runs / year | K11: =K30 -> 1220 | N11: =IF(C15="Yes","Sintered","Green")&" part cost" -> Sintered part cost | P11: =T37-T34 -> 1.7308368 | R11: =IF($C$15="Yes","Sintered","Green")&" parts / month" -> Sintered parts / month | T11: =T10*4 -> 152074.58
A12: x | B12: Build inputs & process capacity | F12: Builds / year | G12: ='P-50 Base'!part_req/'P-50 Base'!good_parts_job -> 2228.199 | J12: Debind furnaces required (rounded) | K12: =ROUNDUP('P-50 Base'!total_builds_yr/K10,0) -> 2 | N12: =N10&" / cc" -> Printed part cost / cc | P12: =P10/'P-50 Base'!part_only_vol*10^3 -> 0.23178091 | R12: =IF($C$15="Yes","Sintered","Green")&" parts / year" -> Sintered parts / year | T12: ='P-50 Base'!part_req -> 1824895
B13: Configuration | C13: Flex | F13: Builds / month | G13: =G12/12 -> 185.68325 | J13: Debind furnace utilization | K13: =K8*K11 -> 10361.867 | L13: hrs | N13: =N11&" / cc" -> Sintered part cost / cc | P13: =P11/'P-50 Base'!part_only_vol*10^3 -> 0.31661995
B14: Build box size | C14: P-50 | F14: Printer utilization (% of available) | G14: =G11/('P-50 Base'!avail_hours_yr*G10) -> 1.0000001 | J14: Debind furnace investment | K14: =OFFSET(C131,'P-50 Base'!furnace_index-1,)*K12 -> 400000 | R14: ="Printer util (QTY: "&G10&")" -> Printer util (QTY: 1) | T14: =G14 -> 1.0000001
B15: Include sintering? | C15: Yes | F15: Printer utilization (% 24x7) | G15: =G11/(24*7*52*G10) -> 0.92307702 | J15: Annual depreciation (@ 7 yrs) | K15: =K14/'P-50 Base'!furnace_depr+OFFSET(C136,'P-50 Base'!furnace_index-1,)*K12*'P-50 Base'!floor_rate -> 41600 | N15: Fully burdened part costs | R15: ="Crosslink util (QTY: "&1&")" -> Crosslink util (QTY: 1) | T15: =G33/('P-50 Base'!total_hours_yr*'P-50 Base'!uptime) -> 5.2744161
B16: Furnace selection | C16: 6 | D16: =IF(C16="Shop",,"ft3") -> ft3 | F16: Nesting density | G16: ='P-50 Base'!part_vol_scale*'P-50 Base'!parts_job/'P-50 Base'!build_vol -> 0.15656663 | J16: Depreciation $ / part | K16: =IF('P-50 Base'!furnace_sel="Continuous",0,K13/('P-50 Base'!total_hours_yr*K12)*K15/'P-50 Base'!part_req) -> 0.014645794 | N16: Printed part cost | P16: =SUM(P32:P36) -> 1.3365079 | R16: ="Depowder util (QTY: "&G44&")" -> Depowder util (QTY: 1) | T16: =G45/('P-50 Base'!avail_hours_yr*G44*'P-50 Base'!uptime) -> 0.89249539
B17: Debind | C17: Integrated | J17: Labor $ / part | K17: =IF('P-50 Base'!furnace_sel="Continuous",0,'P-50 Base'!labor_rate*K11*(K8-6)/'P-50 Base'!part_req) -> 0.033337443 | N17: =IF(C15="Yes","Sintered","Green")&" part cost" -> Sintered part cost | P17: =T45 -> 2.0005041 | R17: ="Furnace util (QTY: "&IF('P-50 Base'!furnace_sel="Shop",K11,K31)&")" -> Furnace util (QTY: 4) | T17: =K32/('P-50 Base'!total_hours_yr*K31*'P-50 Base'!uptime) -> 0.92639716
B18: Limit furnace to QTY 1 | C18: No | E18: x | F18: Printer part cost calculation | J18: Utilities / part | K18: =IF('P-50 Base'!furnace_sel="Continuous",0,('P-50 Base'!furnace_gas_cons*'P-50 Base'!nitrogen_rate+'P-50 Base'!furnace_power_cons*'P-50 Base'!power_rate)*(K13-K6/K7*2*K11))/'P-50 Base'!part_req -> 0.03211715 | N18: Printed part cost / cc | P18: =P16/'P-50 Base'!part_only_vol*10^3 -> 0.24448582
B19: Nested parts / job | C19: =MAX(ROUNDDOWN(('P-50 Base'!build_x-'P-50 Base'!printer_xy_border*2+'P-50 Base'!printer_xy_spacing)/('P-50 Base'!part_scale_x+'P-50 Base'!printer_xy_spacing),0)*ROUNDDOWN(('P-50 Base'!build_y-'P-50 Base'!printer_xy_border*2+'P-50 Base'!printer_xy_spacing)/('P-50 Base'!part_scale_y+'P-50 Base'!printer_xy_spacing),0),ROUNDDOWN(('P-50 Base'!build_x-'P-50 Base'!printer_xy_border*2+'P-50 Base'!printer_xy_spacing)/('P-50 Base'!part_scale_y+'P-50 Base'!printer_xy_spacing),0)*ROUNDDOWN(('P-50 Base'!build_y-'P-50 Base'!printer_xy_border*2+'P-50 Base'!printer_xy_spacing)/('P-50 Base'!part_scale_x+'P-50 Base'!printer_xy_spacing),0))*ROUNDDOWN(('P-50 Base'!build_z-'P-50 Base'!printer_z_base+'P-50 Base'!printer_z_spacing)/('P-50 Base'!part_scale_z+'P-50 Base'!printer_z_spacing),0) -> 819 | F19: Printer investment (incl. build box) | G19: =G10*'P-50 Base'!printer_msrp+ROUNDUP(('P-50 Base'!print_time_trn+G30+G42)/('P-50 Base'!avail_hours_yr/'P-50 Base'!total_builds_yr),0)*'P-50 Base'!buildbox_msrp -> 1250000 | N19: =IF(C15="Yes","Sintered","Green")&" part cost / cc" -> Sintered part cost / cc | P19: =P17/'P-50 Base'!part_only_vol*10^3 -> 0.36594987 | R19: Labor hrs / year | T19: =print_trnaround*'P-50 Base'!total_builds_yr+0.5*'P-50 Base'!total_builds_yr/2+G45+(K27-'P-50 Base'!furnace_time_cycle)*K30+IF('P-50 Base'!furnace_sel<>"Continuous",(K8-6)*K11,0) -> 14951.965
B20: Build height | C20: ='P-50 Base'!printer_z_base+('P-50 Base'!part_scale_z)*ROUNDDOWN(('P-50 Base'!build_z-'P-50 Base'!printer_z_base+'P-50 Base'!printer_z_spacing)/('P-50 Base'!part_scale_z+'P-50 Base'!printer_z_spacing),0)+'P-50 Base'!printer_z_spacing*(ROUNDDOWN(('P-50 Base'!build_z-'P-50 Base'!printer_z_base+'P-50 Base'!printer_z_spacing)/('P-50 Base'!part_scale_z+'P-50 Base'!printer_z_spacing),0)-1) -> 244.9 | D20: mm | F20: ="Annual depreciation (@ "&'P-50 Base'!dm_depr&" yrs)" -> Annual depreciation (@ 10 yrs) | G20: =G19/'P-50 Base'!dm_depr+(5*1.9+1.4*1)*G10*'P-50 Base'!floor_rate -> 126744 | I20: x | J20: MIM furnace part cost calculation | N20: Notes & assumptions:
B21: Override nesting | C21: No | F21: Powder $ / part | G21: =(G7*IF(OR('P-50 Base'!powder_price="",'P-50 Base'!powder_price=0),'P-50 Base'!powder_default_price,'P-50 Base'!powder_price)/'P-50 Base'!good_parts_job) -> 0.78128817 | J21: MIM furnace selection | K21: =C16 -> 6 | L21: =IF(OR('P-50 Base'!furnace_sel="Shop",'P-50 Base'!furnace_sel="Continuous"),,"ft3") -> ft3 | N21: 1. Pricing is not final unless on an official DM quote and is subject to change. Does not include installation, training, shipping, or taxes.
B22: Override parts / job | C22: 0 | F22: Binder $ / part | G22: =G9*'P-50 Base'!binder_weighted_price/'P-50 Base'!good_parts_job -> 0.39927629 | J22: Furnace X-dim | K22: =IF('P-50 Base'!furnace_sel="Continuous","N.A.",C109) -> 420 | L22: mm | N22: ="2. DM Equipment MSRP includes "&ROUNDUP(('P-50 Base'!print_time_trn+G30+G42)/('P-50 Base'!avail_hours_yr/'P-50 Base'!total_builds_yr),0)&" build boxes & transfer cart." -> 2. DM Equipment MSRP includes 13 build boxes & transfer cart.
B23: Override build height | C23: 0 | D23: mm | F23: Depreciation $ / part | G23: =G11/('P-50 Base'!avail_hours_yr*G10)*G20/'P-50 Base'!part_req -> 0.06945277 | J23: Furnace Y-dim | K23: =IF('P-50 Base'!furnace_sel="Continuous","N.A.",C110) -> 915 | L23: mm | N23: ="3. Consumables includes printheads"&IF('P-50 Base'!furnace_sel="Continuous"," and continuous furnace items.",".") -> 3. Consumables includes printheads.
B24: Layer thickness | C24: 0.065 | D24: mm | F24: Consumables $ / part | G24: =(G9/'P-50 Base'!printhead_life*'P-50 Base'!printhead_msrp)/'P-50 Base'!good_parts_job -> 0.06453121 | J24: Furnace Z-dim | K24: =IF('P-50 Base'!furnace_sel="Continuous","N.A.",C111) -> 460 | L24: mm | N24: 4. Includes utilities costs for gas (as required), electricity, and floorspace.
B25: Layers | C25: =ROUNDUP('P-50 Base'!build_height/C24,0) -> 3768 | F25: Labor $ / part | G25: =print_trnaround*'P-50 Base'!labor_rate/'P-50 Base'!good_parts_job -> 0.012210012 | J25: Furnace parts / run | K25: =IF('P-50 Base'!furnace_sel="Continuous",'P-50 Base'!part_req,ROUNDDOWN(('P-50 Base'!mim_furnace_x+'P-50 Base'!furnace_xy_spacing)/('P-50 Base'!furnace_part_scale_x+'P-50 Base'!furnace_xy_spacing),0)*ROUNDDOWN(('P-50 Base'!mim_furnace_y+'P-50 Base'!furnace_xy_spacing)/('P-50 Base'!furnace_part_scale_y+'P-50 Base'!furnace_xy_spacing),0)*MIN('P-50 Base'!furnace_shelves,ROUNDDOWN('P-50 Base'!mim_furnace_z/('P-50 Base'!furnace_part_scale_z+'P-50 Base'!furnace_rack_thickness+'P-50 Base'!furnace_z_spacing),0))) -> 1496 | N25: ="5. "&C41&" powder priced at "&TEXT(IF('P-50 Base'!powder_price="",C43,'P-50 Base'!powder_price),"$0.00")&"/kg and binder priced at "&TEXT('P-50 Base'!binder_price,"$0.00")&"/L. Pricing may be volume dependent." -> 5. 316L SS powder priced at $18.00/kg and binder priced at $100.00/L. Pricing may be volume dependent.
B26: ="Print time + "&print_trnaround&"hrs turnaround" -> Print time + 0.5hrs turnaround | C26: =C25*'P-50 Base'!layer_speed/(60*60)+print_trnaround -> 3.6190667 | D26: hrs | F26: Utilities $ / part | G26: =('P-50 Base'!power_rate*IF('P-50 Base'!p_model="P-1",9,13)*('P-50 Base'!print_time_trn-print_trnaround))/'P-50 Base'!good_parts_job+'P-50 Base'!nitrogen_rate*1000*('P-50 Base'!print_time_trn-print_trnaround)/'P-50 Base'!good_parts_job -> 0.0097494636 | J26: Furnace loading parts / hour | K26: =C51 -> 600 | N26: ="6. Key process assumptions: (i) "&C24*1000&" micron printed layer height; (ii) $"&'P-50 Base'!labor_rate&"/hr labor rate; (iii) Printer, depowdering, and powder handling equipment @ "&C31&" x "&C32&" x "&'P-50 Base'!weeks_yr&" x "&'P-50 Base'!uptime*100&"% uptime" -> 6. Key process assumptions: (i) 65 micron printed layer height; (ii) $20/hr labor rate; (iii) Printer, depowdering, and powder handling equipment @ 24 x 7 x 48 x 100% uptime
B27: Overall process yield | C27: 1 | J27: Run time + turnaround | K27: =IF('P-50 Base'!furnace_sel="Continuous",'P-50 Base'!furnace_time_cycle+K25/K26*2,'P-50 Base'!furnace_time_cycle+K25/K26*1) -> 24.493333 | L27: hrs | O27: =" (iv) "&G41&" parts/hr depowdering rate; (v) "&'P-50 Base'!total_yield*100&"% overall process yield; (vi) "&'P-50 Base'!dm_depr&"yr DM equipment depreciation;" -> (iv) 300 parts/hr depowdering rate; (v) 100% overall process yield; (vi) 10yr DM equipment depreciation;
B28: Good parts / job | C28: =IF('P-50 Base'!override_nesting="Yes",IF(C22=0,C19,C22),C19)*C27 -> 819 | E28: x | F28: Crosslink part cost calculation | J28: Time per printer build | K28: ='P-50 Base'!good_parts_job/K25*K27 -> 13.409118 | L28: hrs | O28: =" (vii) Crosslink station "&IF(C15="Yes","& sintering ",)&"equipment @ 24 x 7 x "&'P-50 Base'!weeks_yr&" x "&'P-50 Base'!uptime*100&"% uptime; (viii) "&IF(C15="Yes",'P-50 Base'!furnace_depr&"yr MIM furnace depreciation; (iv) ",)&'P-50 Base'!total_yield*100&"% overall process yield" -> (vii) Crosslink station & sintering equipment @ 24 x 7 x 48 x 100% uptime; (viii) 10yr MIM furnace depreciation; (iv) 100% overall process yield
F29: Printer builds / oven run | G29: =C93 -> 2 | J29: Build capacity / year | K29: =IF('P-50 Base'!furnace_sel="Continuous",(240000/2.2)/('P-50 Base'!good_parts_job*'P-50 Base'!part_vol*'P-50 Base'!density_selected),ROUNDDOWN('P-50 Base'!total_hours_yr/K28,0)) -> 601
A30: x | B30: Printer operations inputs | F30: Run time + 30min turnaround | G30: =C92*'P-50 Base'!build_height/'P-50 Base'!build_z+0.5 -> 38.176923 | H30: hrs | J30: Runs / year | K30: =ROUNDUP('P-50 Base'!part_req/K25,0) -> 1220
B31: Hours / day | C31: 24 | F31: Build capacity / year | G31: =ROUNDDOWN(G29*'P-50 Base'!total_hours_yr/G30,0) -> 422 | J31: MIM furnaces required (rounded) | K31: =ROUNDUP('P-50 Base'!total_builds_yr/K29,0) -> 4 | N31: ="Production System "&'P-50 Base'!p_model&" "&LOWER(N11)&" allocation" -> Production System P-50 sintered part cost allocation | V31: Cost model template output
B32: Days / week | C32: 7 | F32: Ovens required (rounded) | G32: =ROUNDUP('P-50 Base'!total_builds_yr/G31,0) -> 6 | J32: MIM furnace utilization | K32: =IF('P-50 Base'!furnace_sel="Continuous",'P-50 Base'!total_hours_yr*'P-50 Base'!total_builds_yr/K29,K27*K30) -> 29881.867 | L32: hrs | N32: Printer | O32: Raw materials | P32: =G21+G22 -> 1.1805645 | R32: Total | S32: Raw Materials | T32: =SUMIF($O$32:$O$49,S32,$P$32:$P$49) -> 1.1805645 | V32: Parts per build | Y32: ='P-50 Base'!parts_job -> 819
B33: Weeks / year | C33: 48 | F33: Crosslink utilization | G33: ='P-50 Base'!total_builds_yr*G30/G29 -> 42532.891 | H33: hrs | J33: MIM furnace investment | K33: =IFERROR(OFFSET(C126,'P-50 Base'!furnace_index-1,)*K31,"N.A.") -> 2800000 | N33: Printer | O33: Consumables | P33: =G24 -> 0.06453121 | S33: Consumables | T33: =SUMIF($O$32:$O$49,S33,$P$32:$P$49) -> 0.06453121 | V33: Nesting density | Y33: =G16 -> 0.15656663
B34: Printer available hours / year | C34: =C31*C32*'P-50 Base'!weeks_yr -> 8064 | F34: Crosslink investment | G34: =G32*'P-50 Base'!xlink_msrp -> 300000 | J34: ="Annual depreciation (@ "&'P-50 Base'!furnace_depr&" yrs)" -> Annual depreciation (@ 10 yrs) | K34: =IFERROR(K33/'P-50 Base'!furnace_depr+OFFSET(C136,'P-50 Base'!furnace_index-1,)*K31*'P-50 Base'!floor_rate,"N.A.") -> 283200 | N34: Printer | O34: Depreciation | P34: =G23 -> 0.06945277 | S34: Depreciation | T34: =SUMIF($O$32:$O$49,S34,$P$32:$P$49) -> 0.2696673 | V34: Parts per furnace run | Y34: =IF('P-50 Base'!furnace_sel="Continuous","N.A.",K25) -> 1496
B35: Printer & furnace uptime | C35: 1 | F35: ="Annual depreciation (@ "&'P-50 Base'!dm_depr&" yrs)" -> Annual depreciation (@ 10 yrs) | G35: =G34/'P-50 Base'!dm_depr -> 30000 | J35: Depreciation / part | K35: =IFERROR(K32/('P-50 Base'!total_hours_yr*K31)*K34/'P-50 Base'!part_req,"N.A.") -> 0.14376481 | N35: Printer | O35: Labor | P35: =G25 -> 0.012210012 | S35: Labor | T35: =SUMIF($O$32:$O$49,S35,$P$32:$P$49) -> 0.16386658 | V35: Builds per furnace run | Y35: =IFERROR(Y34/C19,"N.A.") -> 1.8266178
B36: Printer uptime hours / year | C36: ='P-50 Base'!avail_hours_yr*'P-50 Base'!uptime -> 8064 | F36: Depreciation $ / part | G36: =G33/('P-50 Base'!total_hours_yr*G32)*G35/'P-50 Base'!part_req -> 0.014451286 | J36: Consumables / part | K36: =IF('P-50 Base'!furnace_sel="Continuous",'P-50 Base'!furnace_power_cons*'P-50 Base'!total_hours_yr/'P-50 Base'!part_req,0) -> 0 | N36: Printer | O36: Utilities | P36: =G26 -> 0.0097494636 | S36: Utilities | T36: =SUMIF($O$32:$O$49,S36,$P$32:$P$49) -> 0.32187458 | V36: Parts per week | Y36: =Y37/'P-50 Base'!weeks_yr -> 38018.646
B37: Good parts / printer / year | C37: =ROUND('P-50 Base'!good_parts_job/'P-50 Base'!print_time_trn*'P-50 Base'!uptime_hours_yr,0) -> 1824895 | F37: Labor $ / part | G37: =(0.5/G29*'P-50 Base'!labor_rate*'P-50 Base'!total_builds_yr)/'P-50 Base'!part_req -> 0.0061050061 | J37: Labor $ / part | K37: =IF('P-50 Base'!furnace_sel="Continuous",'P-50 Base'!labor_rate*'P-50 Base'!part_req/K26,'P-50 Base'!labor_rate*K30*(K27-C113))/'P-50 Base'!part_req -> 0.033337443 | N37: Crosslink | O37: Depreciation | P37: =G36 -> 0.014451286 | S37: Total | T37: =SUM(T32:T36) -> 2.0005041 | V37: Parts per year | Y37: ='P-50 Base'!part_req -> 1824895
B38: Parts required / year | C38: =+'P-50 Base'!part_capacity -> 1824895 | F38: Utilities $ / part | G38: =('P-50 Base'!power_rate*5*G33+'P-50 Base'!nitrogen_rate*18*60*G33)/'P-50 Base'!part_req -> 0.039155819 | J38: Utilities / part | K38: =IF('P-50 Base'!furnace_sel="Continuous",'P-50 Base'!furnace_gas_cons*'P-50 Base'!total_hours_yr,('P-50 Base'!argon_rate*'P-50 Base'!furnace_gas_cons+'P-50 Base'!power_rate*'P-50 Base'!furnace_power_cons)*(K27-K25/K26*2)*K30)/'P-50 Base'!part_req -> 0.21191338 | N38: Crosslink | O38: Labor | P38: =G37 -> 0.0061050061 | V38: Operating part cost | Y38: =P11 -> 1.7308368
N39: Crosslink | O39: Utilities | P39: =G38 -> 0.039155819 | R39: Total | S39: Raw Materials | T39: =P32 -> 1.1805645 | V39: Operating cost / cc | Y39: =P13 -> 0.31661995
A40: x | B40: Cost & other inputs | E40: x | F40: Depowder part cost calculation | I40: x | J40: PPU part cost calculation | N40: Depowder | O40: Depreciation | P40: =G48 -> 0.0075895328 | S40: Printer | T40: =SUMIF($N$33:$N$49,S40,$P$33:$P$49) -> 0.15594346 | V40: Fully burdened part cost | Y40: =P17 -> 2.0005041
B41: Material selection | C41: 316L SS | F41: Depowdered parts / hour | G41: =C50 -> 300 | J41: PPU required (rounded) | K41: =ROUNDUP(G10/2,0) -> 1 | N41: Depowder | O41: Labor | P41: =G49 -> 0.078876679 | S41: Crosslink | T41: =SUMIF($N$33:$N$49,S41,$P$33:$P$49) -> 0.059712111 | V41: Fully burdened cost / cc | Y41: =P19 -> 0.36594987
B42: Powder MSRP | D42: $/kg | F42: Run time + 30 min turnaround | G42: ='P-50 Base'!parts_job/G41+0.5 -> 3.23 | H42: hrs | J42: PPU utilization (hrs) | K42: =MAX(G11/G10*ROUNDUP(G10/2,0),G45) -> 8064.0008 | L42: hrs | N42: Depowder | O42: Utilities | P42: =G50 -> 0.0024254579 | S42: Depowder | T42: =SUMIF($N$33:$N$49,S42,$P$33:$P$49) -> 0.08889167 | V42: Printer utilization | Y42: =T14 -> 1.0000001
B43: Powder MSRP default | C43: {=+INDEX(C154:C163,VLOOKUP(C41,B141:F151,5,0))} -> 18 | D43: $/kg | F43: Build capacity / year | G43: =ROUNDDOWN('P-50 Base'!uptime_hours_yr/G42,0) -> 2496 | J43: PPU investment | K43: ='P-50 Base'!ppu_msrp*K41 -> 350000 | N43: Furnace | O43: Consumables | P43: =IF(C15="No",0,IF(C16="Continuous",K36,)) | S43: Furnace | T43: =SUMIF($N$33:$N$49,S43,$P$33:$P$49) -> 0.46911602 | V43: Furnace utilization | Y43: =T17 -> 0.92639716
B44: Binder MSRP | C44: =IF('P-50 Base'!binder_per_yr>F166,C168,IF('P-50 Base'!binder_per_yr>F165,C167,C166)) -> 100 | D44: $/L | F44: Depowders required (rounded) | G44: =ROUNDUP('P-50 Base'!total_builds_yr/G43,0) -> 1 | J44: ="Annual depreciation (@ "&'P-50 Base'!dm_depr&" yrs)" -> Annual depreciation (@ 10 yrs) | K44: =K43/'P-50 Base'!dm_depr+(3.7*1.8)*K41*'P-50 Base'!floor_rate -> 36065.6 | N44: Furnace | O44: Depreciation | P44: =IF(C15="No",0,K35+IF($C$16<>"Continuous",K16,0)) -> 0.1584106 | S44: PPU | T44: =SUMIF($N$33:$N$49,S44,$P$33:$P$49) -> 0.046276418
B45: Printheads MSRP | C45: =VLOOKUP(B45,Inputs!$B$6:$M$311,Inputs!M$1,0) -> 48000 | F45: Depowder utilization | G45: ='P-50 Base'!total_builds_yr*G42 -> 7197.0828 | H45: hrs | J45: Depreciation $ / part | K45: =K42/('P-50 Base'!avail_hours_yr*K41)*K44/'P-50 Base'!part_req -> 0.019763112 | N45: Furnace | O45: Labor | P45: =IF(C15="No",0,K37+IF($C$16<>"Continuous",K17,0)) -> 0.066674886 | S45: Total | T45: =SUM(T39:T44) -> 2.0005041
B46: Region | C46: NAM | F46: Depowder investment | G46: =G44*'P-50 Base'!depowder_msrp -> 150000 | J46: Labor $ / part | K46: 0 | N46: Furnace | O46: Utilities | P46: =IF(C15="No",0,K38+IF($C$16<>"Continuous",K18,0)) -> 0.24403053
F47: ="Annual depreciation (@ "&'P-50 Base'!dm_depr&" yrs)" -> Annual depreciation (@ 10 yrs) | G47: =G46/'P-50 Base'!dm_depr+(2.7*1.2)*G44*'P-50 Base'!floor_rate -> 15518.4 | J47: Utilities / part | K47: =50*'P-50 Base'!uptime_hours_yr*'P-50 Base'!power_rate/'P-50 Base'!part_req -> 0.026513306 | N47: PPU | O47: Depreciation | P47: =K45 -> 0.019763112
A48: x | B48: Labor & equipment inputs | F48: Depreciation $ / part | G48: =G45/('P-50 Base'!avail_hours_yr*G44)*G47/'P-50 Base'!part_req -> 0.0075895328 | N48: PPU | O48: Labor | P48: =K46 -> 0
B49: Labor rate | C49: 20 | D49: $/hr | F49: Labor $ / part | G49: =G42*'P-50 Base'!labor_rate*'P-50 Base'!total_builds_yr/'P-50 Base'!part_req -> 0.078876679 | N49: PPU | O49: Utilities | P49: =K47 -> 0.026513306
B50: Depowdered parts / hour | C50: =IF('P-50 Base'!p_model="P-50",300,30) -> 300 | F50: Utilities $ / part | G50: ='P-50 Base'!power_rate*5*G45/'P-50 Base'!part_req+'P-50 Base'!nitrogen_rate*15*G42/'P-50 Base'!good_parts_job -> 0.0024254579
B51: Furnace loading parts / hour | C51: =IF('P-50 Base'!p_model="P-50",600,240) -> 600
B52: DM equipment depreciation | C52: 10 | D52: yrs
B53: MIM furnace depreciation | C53: 10 | D53: yrs
B54: Nitrogen rate | C54: 0.001 | D54: $/L
B55: Argon rate | C55: 0.0025 | D55: $/L
B56: Power rate | C56: 0.12 | D56: $/kWh
B57: Floorspace rate / year | C57: 160 | D57: $/m2
A60: x | B60: Parts required / year | C60: =IF(C18="No",IF(C38<>"",C38,'P-50 Base'!part_capacity),MIN('P-50 Base'!part_capacity,K29*'P-50 Base'!good_parts_job)) -> 1824895
B61: X-scale | C61: =VLOOKUP($B61,Inputs!$B$6:$M$309,Inputs!M$1,0) -> 1.16
B62: Y-scale | C62: =VLOOKUP($B62,Inputs!$B$6:$M$309,Inputs!M$1,0) -> 1.165
B63: Z-scale | C63: =VLOOKUP($B63,Inputs!$B$6:$M$309,Inputs!M$1,0) -> 1.18
B64: Layer speed | C64: =VLOOKUP($B64,Inputs!$B$6:$M$309,Inputs!M$1,0) -> 2.98 | D64: sec
B65: X-dim scaled | C65: ='P-50 Base'!part_x*'P-50 Base'!x_scale -> 46.4 | D65: mm
B66: Y-dim scaled | C66: ='P-50 Base'!part_y*'P-50 Base'!y_scale -> 46.6 | D66: mm
B67: Z-dim scaled | C67: ='P-50 Base'!part_z*'P-50 Base'!z_scale -> 17.7 | D67: mm
B68: Volume scaled | C68: ='P-50 Base'!part_vol*'P-50 Base'!x_scale*'P-50 Base'!y_scale*'P-50 Base'!z_scale -> 8717.3358 | D68: mm3
B69: Parts / job | C69: =IF('P-50 Base'!override_nesting="Yes",IF(OR(C22=0,C23=0),C19,C22),C19) -> 819
B70: Bed density | C70: =VLOOKUP($B70,Inputs!$B$6:$M$309,Inputs!M$1,0) -> 0.6
B71: Build box X-dim | C71: =VLOOKUP($B71,Inputs!$B$6:$M$309,Inputs!M$1,0) -> 490 | D71: mm
B72: Build box Y-dim | C72: =VLOOKUP($B72,Inputs!$B$6:$M$309,Inputs!M$1,0) -> 380 | D72: mm
B73: Build box Z-dim | C73: =VLOOKUP($B73,Inputs!$B$6:$M$309,Inputs!M$1,0) -> 260 | D73: mm
B74: Build height | C74: =IF('P-50 Base'!override_nesting="Yes",IF(OR(C22=0,C23=0),C20,C23),C20) -> 244.9 | D74: mm
B75: Build box volume | C75: ='P-50 Base'!build_x*'P-50 Base'!build_y*'P-50 Base'!build_height -> 45600380 | D75: mm3
B76: Print turnaround time | C76: =VLOOKUP($B76,Inputs!$B$6:$M$309,Inputs!M$1,0) -> 0.5 | D76: hrs
B77: Crosslink turnaround time | C77: =VLOOKUP($B77,Inputs!$B$6:$M$309,Inputs!M$1,0) -> 0.5 | D77: hrs
B78: Depowder turnaround time | C78: =VLOOKUP($B78,Inputs!$B$6:$M$309,Inputs!M$1,0) -> 0.5 | D78: hrs
B79: Powder blender turnaround time | C79: =VLOOKUP($B79,Inputs!$B$6:$M$309,Inputs!M$1,0) -> 1 | D79: hrs
B80: Powder + overflow ratio | C80: =VLOOKUP($B80,Inputs!$B$6:$M$309,Inputs!M$1,0) -> 6
B81: Powder loss percentage | C81: =VLOOKUP($B81,Inputs!$B$6:$M$309,Inputs!M$1,0) -> 0.001
B82: Binder void ratio | C82: =VLOOKUP($B82,Inputs!$B$6:$M$309,Inputs!M$1,0) -> 0.7
B83: Binder purge volume | C83: =VLOOKUP($B83,Inputs!$B$6:$M$309,Inputs!M$1,0) -> 20 | D83: mL
B84: Purge frequency | C84: =VLOOKUP($B84,Inputs!$B$6:$M$309,Inputs!M$1,0) -> 100 | D84: layers
B85: Printhead life | C85: =VLOOKUP($B85,Inputs!$B$6:$M$309,Inputs!M$1,0) -> 2500 | D85: L
B88: Printer XY border | C88: =IF('P-50 Base'!p_model="P-50",20,8.5) -> 20 | D88: mm
B89: Printer Z base plate | C89: =IF('P-50 Base'!p_model="P-50",10,4) -> 10 | D89: mm
B90: Printer XY spacing | C90: 1 | D90: mm
B91: Printer Z spacing | C91: 0.4 | D91: mm
B92: Crosslink time | C92: =VLOOKUP($B92,Inputs!$B$6:$M$309,Inputs!M$1,0) -> 40 | D92: hrs
B93: Printer builds / oven run | C93: =VLOOKUP($B93,Inputs!$B$6:$M$309,Inputs!M$1,0) -> 2
B97: Furnace X-dim scaled | C97: =IF('P-50 Base'!furnace_sel="Shop",IF(OR('P-50 Base'!part_scale_x>dm_furnace_x,'P-50 Base'!part_scale_y>dm_furnace_y),IF(AND('P-50 Base'!part_scale_y<=dm_furnace_x,'P-50 Base'!part_scale_x<=dm_furnace_y),'P-50 Base'!part_scale_y,"N.A."),'P-50 Base'!part_scale_x),IF(OR('P-50 Base'!part_scale_x>'P-50 Base'!mim_furnace_x,'P-50 Base'!part_scale_y>'P-50 Base'!mim_furnace_y),IF(AND('P-50 Base'!part_scale_y<='P-50 Base'!mim_furnace_x,'P-50 Base'!part_scale_x<='P-50 Base'!mim_furnace_y),'P-50 Base'!part_scale_y,"N.A."),'P-50 Base'!part_scale_x)) -> 46.4
B98: Furnace Y-dim scaled | C98: =IF(C97='P-50 Base'!part_scale_x,'P-50 Base'!part_scale_y,IF(C97='P-50 Base'!part_scale_y,'P-50 Base'!part_scale_x,"N.A.")) -> 46.6
B99: Furnace Z-dim scaled | C99: =IF(OR(C97="N.A.",C98="N.A."),"N.A.",'P-50 Base'!part_scale_z) -> 17.7 | G99: 5 ovens for 24/7 on Flex
B100: Furnace XY spacing | C100: 5 | D100: mm | G100: 3 people for depowder + ppu + printer - 24/7
B101: Furnace Z spacing | C101: 2 | D101: mm
B102: Furnace rack + setter thickness | C102: 2.6 | D102: mm
B106: Total hours / year | C106: =24*7*'P-50 Base'!weeks_yr -> 8064
A108: x | B108: MIM furnace index | C108: =VLOOKUP('P-50 Base'!furnace_sel,$B$126:$E$130,3,0) -> 3
B109: MIM furnace X-dim | C109: =CHOOSE(C$108,305,420,420,420,999999,"N.A.") -> 420 | D109: mm
B110: MIM furnace Y-dim | C110: =CHOOSE(C$108,610,610,915,1524,999999,"N.A.") -> 915 | D110: mm
B111: MIM furnace Z-dim | C111: =CHOOSE(C$108,305,460,460,460,999999,"N.A.") -> 460 | D111: mm
B112: MIM furnace shelves | C112: 11
...

Sheet P-50 Auto
A2: x | B2: =Shop!B2 -> #VALUE! | F2: PRODUCTION SYSTEM | K2: Privileged & DM Confidential | M2: x | N2: Production System part cost outputs
N3: DM equipment MSRP | P3: =G19+G34+G46+K41*'P-50 Auto'!ppu_msrp -> 4930000 | R3: ="Printed parts / "&C14&" build" -> Printed parts / P-50 build | T3: ='P-50 Auto'!parts_job -> 819
A4: x | B4: Part inputs (pre-scaling) | E4: x | F4: Printer usage calculation | I4: x | J4: Debind furnace part cost calculation | N4: =IF(C16="Shop","DM",IF('P-50 Auto'!furnace_sel<>"Continuous",C16&" cu ft MIM","Continuous"))&" furnace MSRP" -> Continuous furnace MSRP | P4: =K33+K14 -> 3000000 | R4: Part nesting density | T4: =G16 -> 0.15656663
B5: X-dim (incl. supports) | C5: 40 | D5: mm | F5: Powder volume / part | G5: ='P-50 Auto'!part_vol_scale*'P-50 Auto'!bed_density -> 5230.4015 | H5: mm3 | J5: Debind furnace selection | K5: =K21 -> Continuous | L5: ft3 | N5: Total equipment MSRP | P5: =SUM(P3:P4) -> 7930000
B6: Y-dim (incl. supports) | C6: 40 | D6: mm | F6: Powder mass / part | G6: =G5*'P-50 Auto'!density_selected*1000 -> 40.483307 | H6: g | J6: Furnace parts / run | K6: =K25 -> 5474685 | N6: =C14&" printers required" -> P-50 printers required | P6: =G10 -> 3 | R6: Printer builds / week | T6: =T8/'P-50 Auto'!weeks_yr -> 139.26244
B7: Z-dim (incl. supports) | C7: 15 | D7: mm | F7: Powder mass / build | G7: =(G6*'P-50 Auto'!parts_job)/1000+(('P-50 Auto'!build_vol*'P-50 Auto'!bed_density*'P-50 Auto'!density_selected*'P-50 Auto'!powder_ratio)-(G6*'P-50 Auto'!parts_job)/1000)*'P-50 Auto'!powder_loss_percentage -> 34.393282 | H7: kg | J7: Furnace loading parts / hour | K7: =K26 -> 600 | N7: Furnaces required | P7: =IF('P-50 Auto'!furnace_sel="Shop",K11,K31) -> 3 | R7: Printer builds / month | T7: =T6*4 -> 557.04976
B8: Part volume | C8: 5466.607 | D8: mm3 | F8: Binder volume / part | G8: ='P-50 Auto'!part_vol_scale*(1-'P-50 Auto'!bed_density)*'P-50 Auto'!binder_void_ratio -> 2440.854 | H8: mm3 | J8: Run time + turnaround | K8: =6+K6/K7*1 -> 9130.475 | L8: hrs | R8: Printer builds / year | T8: ='P-50 Auto'!total_builds_yr -> 6684.5971
B9: Support volume | D9: mm3 | F9: Binder volume / build | G9: =G8*'P-50 Auto'!parts_job/10^6+('P-50 Auto'!build_layers/C80)*'P-50 Auto'!binder_purge_vol/1000 -> 2.7526594 | H9: L | J9: Time per printer build | K9: =('P-50 Auto'!good_parts_job/K6*K8) -> 1.3658976 | L9: hrs | N9: Operating part costs
B10: Part + support volume | C10: ='P-50 Auto'!part_only_vol+'P-50 Auto'!support_vol -> 5466.607 | D10: mm3 | F10: Printers required (rounded) | G10: =ROUNDUP('P-50 Auto'!part_req/'P-50 Auto'!part_capacity,0) -> 3 | J10: Build capacity / year | K10: =ROUNDDOWN('P-50 Auto'!total_hours_yr/K9,0) -> 5903 | N10: Printed part cost | P10: =P32+P33+P35+P36 -> 0.96017863 | R10: =IF($C$15="Yes","Sintered","Green")&" parts / week" -> Sintered parts / week | T10: =T12/'P-50 Auto'!weeks_yr -> 114055.94
F11: Printer utilization | G11: ='P-50 Auto'!part_req/'P-50 Auto'!good_parts_job*'P-50 Auto'!print_time_trn -> 24192.002 | H11: hrs | J11: Runs / year | K11: =K30 -> 1 | N11: =IF(C15="Yes","Sintered","Green")&" part cost" -> Sintered part cost | P11: =T37-T34 -> 1.1450471 | R11: =IF($C$15="Yes","Sintered","Green")&" parts / month" -> Sintered parts / month | T11: =T10*4 -> 456223.75
A12: x | B12: Build inputs & process capacity | F12: Builds / year | G12: ='P-50 Auto'!part_req/'P-50 Auto'!good_parts_job -> 6684.5971 | J12: Debind furnaces required (rounded) | K12: =ROUNDUP('P-50 Auto'!total_builds_yr/K10,0) -> 2 | N12: =N10&" / cc" -> Printed part cost / cc | P12: =P10/'P-50 Auto'!part_only_vol*10^3 -> 0.17564435 | R12: =IF($C$15="Yes","Sintered","Green")&" parts / year" -> Sintered parts / year | T12: ='P-50 Auto'!part_req -> 5474685
B13: Configuration | C13: Flex | F13: Builds / month | G13: =G12/12 -> 557.04976 | J13: Debind furnace utilization | K13: =K8*K11 -> 9130.475 | L13: hrs | N13: =N11&" / cc" -> Sintered part cost / cc | P13: =P11/'P-50 Auto'!part_only_vol*10^3 -> 0.20946212
B14: Build box size | C14: P-50 | F14: Printer utilization (% of available) | G14: =G11/('P-50 Auto'!avail_hours_yr*G10) -> 1.0000001 | J14: Debind furnace investment | K14: =OFFSET(C126,'P-50 Auto'!furnace_index-1,)*K12 -> 0 | R14: ="Printer util (QTY: "&G10&")" -> Printer util (QTY: 3) | T14: =G14 -> 1.0000001
B15: Include sintering? | C15: Yes | F15: Printer utilization (% 24x7) | G15: =G11/(24*7*52*G10) -> 0.92307702 | J15: Annual depreciation (@ 7 yrs) | K15: =K14/'P-50 Auto'!furnace_depr+OFFSET(C131,'P-50 Auto'!furnace_index-1,)*K12*'P-50 Auto'!floor_rate -> 6400 | N15: Fully burdened part costs | R15: ="Crosslink util (QTY: "&1&")" -> Crosslink util (QTY: 1) | T15: =G33/('P-50 Auto'!total_hours_yr*'P-50 Auto'!uptime) -> 2.637208
B16: Furnace selection | C16: Continuous | D16: =IF(C16="Shop",,"ft3") -> ft3 | F16: Nesting density | G16: ='P-50 Auto'!part_vol_scale*'P-50 Auto'!parts_job/'P-50 Auto'!build_vol -> 0.15656663 | J16: Depreciation $ / part | K16: =IF('P-50 Auto'!furnace_sel="Continuous",0,K13/('P-50 Auto'!total_hours_yr*K12)*K15/'P-50 Auto'!part_req) -> 0 | N16: Printed part cost | P16: =SUM(P32:P36) -> 1.0292661 | R16: ="Depowder util (QTY: "&G44&")" -> Depowder util (QTY: 3) | T16: =G45/('P-50 Auto'!avail_hours_yr*G44*'P-50 Auto'!uptime) -> 0.89249539
B17: Limit furnace to QTY 1 | C17: No | J17: Labor $ / part | K17: =IF('P-50 Auto'!furnace_sel="Continuous",0,'P-50 Auto'!labor_rate*K11*(K8-6)/'P-50 Auto'!part_req) -> 0 | N17: =IF(C15="Yes","Sintered","Green")&" part cost" -> Sintered part cost | P17: =T45 -> 1.2817978 | R17: ="Furnace util (QTY: "&IF('P-50 Auto'!furnace_sel="Shop",K11,K31)&")" -> Furnace util (QTY: 3) | T17: =K32/('P-50 Auto'!total_hours_yr*K31*'P-50 Auto'!uptime) -> 0.70779605
B18: Nested parts / job | C18: =MAX(ROUNDDOWN(('P-50 Auto'!build_x-'P-50 Auto'!printer_xy_border*2+'P-50 Auto'!printer_xy_spacing)/('P-50 Auto'!part_scale_x+'P-50 Auto'!printer_xy_spacing),0)*ROUNDDOWN(('P-50 Auto'!build_y-'P-50 Auto'!printer_xy_border*2+'P-50 Auto'!printer_xy_spacing)/('P-50 Auto'!part_scale_y+'P-50 Auto'!printer_xy_spacing),0),ROUNDDOWN(('P-50 Auto'!build_x-'P-50 Auto'!printer_xy_border*2+'P-50 Auto'!printer_xy_spacing)/('P-50 Auto'!part_scale_y+'P-50 Auto'!printer_xy_spacing),0)*ROUNDDOWN(('P-50 Auto'!build_y-'P-50 Auto'!printer_xy_border*2+'P-50 Auto'!printer_xy_spacing)/('P-50 Auto'!part_scale_x+'P-50 Auto'!printer_xy_spacing),0))*ROUNDDOWN(('P-50 Auto'!build_z-'P-50 Auto'!printer_z_base+'P-50 Auto'!printer_z_spacing)/('P-50 Auto'!part_scale_z+'P-50 Auto'!printer_z_spacing),0) -> 819 | E18: x | F18: Printer part cost calculation | J18: Utilities / part | K18: =IF('P-50 Auto'!furnace_sel="Continuous",0,('P-50 Auto'!furnace_gas_cons*'P-50 Auto'!nitrogen_rate+'P-50 Auto'!furnace_power_cons*'P-50 Auto'!power_rate)*(K13-K6/K7*2*K11))/'P-50 Auto'!part_req -> 0 | N18: Printed part cost / cc | P18: =P16/'P-50 Auto'!part_only_vol*10^3 -> 0.18828244
B19: Build height | C19: ='P-50 Auto'!printer_z_base+('P-50 Auto'!part_scale_z)*ROUNDDOWN(('P-50 Auto'!build_z-'P-50 Auto'!printer_z_base+'P-50 Auto'!printer_z_spacing)/('P-50 Auto'!part_scale_z+'P-50 Auto'!printer_z_spacing),0)+'P-50 Auto'!printer_z_spacing*(ROUNDDOWN(('P-50 Auto'!build_z-'P-50 Auto'!printer_z_base+'P-50 Auto'!printer_z_spacing)/('P-50 Auto'!part_scale_z+'P-50 Auto'!printer_z_spacing),0)-1) -> 244.9 | D19: mm | F19: Printer investment (incl. build box) | G19: =G10*'P-50 Auto'!printer_msrp+ROUNDUP(('P-50 Auto'!print_time_trn+G30+G42)/('P-50 Auto'!avail_hours_yr/'P-50 Auto'!total_builds_yr),0)*'P-50 Auto'!buildbox_msrp -> 3730000 | N19: =IF(C15="Yes","Sintered","Green")&" part cost / cc" -> Sintered part cost / cc | P19: =P17/'P-50 Auto'!part_only_vol*10^3 -> 0.23447777 | R19: Labor hrs / year | T19: =print_trnaround*'P-50 Auto'!total_builds_yr+0.5*'P-50 Auto'!total_builds_yr/2+G45+(K27-'P-50 Auto'!furnace_time_cycle)*K30+IF('P-50 Auto'!furnace_sel<>"Continuous",(K8-6)*K11,0) -> 44853.646
B20: Override nesting | C20: No | F20: ="Annual depreciation (@ "&'P-50 Auto'!dm_depr&" yrs)" -> Annual depreciation (@ 10 yrs) | G20: =G19/'P-50 Auto'!dm_depr+(5*1.9+1.4*1)*G10*'P-50 Auto'!floor_rate -> 378232 | I20: x | J20: MIM furnace part cost calculation | N20: Notes & assumptions:
B21: Override parts / job | C21: 0 | F21: Powder $ / part | G21: =(G7*IF(OR('P-50 Auto'!powder_price="",'P-50 Auto'!powder_price=0),'P-50 Auto'!powder_default_price,'P-50 Auto'!powder_price)/'P-50 Auto'!good_parts_job) -> 0.51652914 | J21: MIM furnace selection | K21: =C16 -> Continuous | L21: =IF(OR('P-50 Auto'!furnace_sel="Shop",'P-50 Auto'!furnace_sel="Continuous"),,"ft3") | N21: 1. Pricing is not final unless on an official DM quote and is subject to change. Does not include installation, training, shipping, or taxes.
B22: Override build height | C22: 0 | D22: mm | F22: Binder $ / part | G22: =G9*'P-50 Auto'!binder_weighted_price/'P-50 Auto'!good_parts_job -> 0.3571588 | J22: Furnace X-dim | K22: =IF('P-50 Auto'!furnace_sel="Continuous","N.A.",C104) -> N.A. | L22: mm | N22: ="2. DM Equipment MSRP includes "&ROUNDUP(('P-50 Auto'!print_time_trn+G30+G42)/('P-50 Auto'!avail_hours_yr/'P-50 Auto'!total_builds_yr),0)&" build boxes & transfer cart." -> 2. DM Equipment MSRP includes 38 build boxes & transfer cart.
B23: Layer thickness | C23: 0.065 | D23: mm | F23: Depreciation $ / part | G23: =G11/('P-50 Auto'!avail_hours_yr*G10)*G20/'P-50 Auto'!part_req -> 0.069087452 | J23: Furnace Y-dim | K23: =IF('P-50 Auto'!furnace_sel="Continuous","N.A.",C105) -> N.A. | L23: mm | N23: ="3. Consumables includes printheads"&IF('P-50 Auto'!furnace_sel="Continuous"," and continuous furnace items.",".") -> 3. Consumables includes printheads and continuous furnace items.
B24: Layers | C24: =ROUNDUP('P-50 Auto'!build_height/C23,0) -> 3768 | F24: Consumables $ / part | G24: =(G9/'P-50 Auto'!printhead_life*'P-50 Auto'!printhead_msrp)/'P-50 Auto'!good_parts_job -> 0.06453121 | J24: Furnace Z-dim | K24: =IF('P-50 Auto'!furnace_sel="Continuous","N.A.",C106) -> N.A. | L24: mm | N24: 4. Includes utilities costs for gas (as required), electricity, and floorspace.
B25: ="Print time + "&print_trnaround&"hrs turnaround" -> Print time + 0.5hrs turnaround | C25: =C24*'P-50 Auto'!layer_speed/(60*60)+print_trnaround -> 3.6190667 | D25: hrs | F25: Labor $ / part | G25: =print_trnaround*'P-50 Auto'!labor_rate/'P-50 Auto'!good_parts_job -> 0.012210012 | J25: Furnace parts / run | K25: =IF('P-50 Auto'!furnace_sel="Continuous",'P-50 Auto'!part_req,ROUNDDOWN(('P-50 Auto'!mim_furnace_x+'P-50 Auto'!furnace_xy_spacing)/('P-50 Auto'!furnace_part_scale_x+'P-50 Auto'!furnace_xy_spacing),0)*ROUNDDOWN(('P-50 Auto'!mim_furnace_y+'P-50 Auto'!furnace_xy_spacing)/('P-50 Auto'!furnace_part_scale_y+'P-50 Auto'!furnace_xy_spacing),0)*MIN('P-50 Auto'!furnace_shelves,ROUNDDOWN('P-50 Auto'!mim_furnace_z/('P-50 Auto'!furnace_part_scale_z+'P-50 Auto'!furnace_rack_thickness+'P-50 Auto'!furnace_z_spacing),0))) -> 5474685 | N25: ="5. "&C40&" powder priced at "&TEXT(IF('P-50 Auto'!powder_price="",C42,'P-50 Auto'!powder_price),"$0.00")&"/kg and binder priced at "&TEXT('P-50 Auto'!binder_price,"$0.00")&"/L. Pricing may be volume dependent." -> 5. 17-4PH SS powder priced at $12.30/kg and binder priced at $100.00/L. Pricing may be volume dependent.
B26: Overall process yield | C26: 1 | F26: Utilities $ / part | G26: =('P-50 Auto'!power_rate*IF('P-50 Auto'!p_model="P-1",9,13)*('P-50 Auto'!print_time_trn-print_trnaround))/'P-50 Auto'!good_parts_job+'P-50 Auto'!nitrogen_rate*1000*('P-50 Auto'!print_time_trn-print_trnaround)/'P-50 Auto'!good_parts_job -> 0.0097494636 | J26: Furnace loading parts / hour | K26: =C50 -> 600 | N26: ="6. Key process assumptions: (i) "&C23*1000&" micron printed layer height; (ii) $"&'P-50 Auto'!labor_rate&"/hr labor rate; (iii) Printer, depowdering, and powder handling equipment @ "&C30&" x "&C31&" x "&'P-50 Auto'!weeks_yr&" x "&'P-50 Auto'!uptime*100&"% uptime" -> 6. Key process assumptions: (i) 65 micron printed layer height; (ii) $20/hr labor rate; (iii) Printer, depowdering, and powder handling equipment @ 24 x 7 x 48 x 100% uptime
B27: Good parts / job | C27: =IF('P-50 Auto'!override_nesting="Yes",IF(C21=0,C18,C21),C18)*C26 -> 819 | J27: Run time + turnaround | K27: =IF('P-50 Auto'!furnace_sel="Continuous",'P-50 Auto'!furnace_time_cycle+K25/K26*2,'P-50 Auto'!furnace_time_cycle+K25/K26*1) -> 18368.95 | L27: hrs | O27: =" (iv) "&G41&" parts/hr depowdering rate; (v) "&'P-50 Auto'!total_yield*100&"% overall process yield; (vi) "&'P-50 Auto'!dm_depr&"yr DM equipment depreciation;" -> (iv) 300 parts/hr depowdering rate; (v) 100% overall process yield; (vi) 10yr DM equipment depreciation;
E28: x | F28: Crosslink part cost calculation | J28: Time per printer build | K28: ='P-50 Auto'!good_parts_job/K25*K27 -> 2.7479517 | L28: hrs | O28: =" (vii) Crosslink station "&IF(C15="Yes","& sintering ",)&"equipment @ 24 x 7 x "&'P-50 Auto'!weeks_yr&" x "&'P-50 Auto'!uptime*100&"% uptime; (viii) "&IF(C15="Yes",'P-50 Auto'!furnace_depr&"yr MIM furnace depreciation; (iv) ",)&'P-50 Auto'!total_yield*100&"% overall process yield" -> (vii) Crosslink station & sintering equipment @ 24 x 7 x 48 x 100% uptime; (viii) 10yr MIM furnace depreciation; (iv) 100% overall process yield
A29: x | B29: Printer operations inputs | F29: =IF('P-50 Auto'!p_model="P-50","Printer builds / day","Printer builds / oven run") -> Printer builds / day | G29: ='P-50 Auto'!total_builds_yr/(C31*'P-50 Auto'!weeks_yr) -> 19.894634 | J29: Build capacity / year | K29: =IF('P-50 Auto'!furnace_sel="Continuous",(240000/2.2)/('P-50 Auto'!good_parts_job*'P-50 Auto'!part_vol*'P-50 Auto'!density_selected),ROUNDDOWN('P-50 Auto'!total_hours_yr/K28,0)) -> 3148.0806
B30: Hours / day | C30: 24 | F30: Run time + 30min turnaround | G30: =C88*'P-50 Auto'!build_height/'P-50 Auto'!build_z+0.5 -> 38.176923 | H30: hrs | J30: Runs / year | K30: =ROUNDUP('P-50 Auto'!part_req/K25,0) -> 1
B31: Days / week | C31: 7 | F31: =IF('P-50 Auto'!p_model="P-50","Add'l modules required (rounded)", "Ovens required") -> Add'l modules required (rounded) | G31: =IF('P-50 Auto'!p_model="P-50",IF(G29>3,3,IF(G29>2,2,IF(G29>1,1,0))),ROUNDUP('P-50 Auto'!total_builds_yr/G32,0)) -> 3 | J31: MIM furnaces required (rounded) | K31: =ROUNDUP('P-50 Auto'!total_builds_yr/K29,0) -> 3 | N31: ="Production System "&'P-50 Auto'!p_model&" "&LOWER(N11)&" allocation" -> Production System P-50 sintered part cost allocation | V31: Cost model template output
B32: Weeks / year | C32: 48 | F32: Build capacity / year | G32: =ROUNDDOWN((G31+1)*'P-50 Auto'!total_hours_yr/G30*3,0) -> 2534 | J32: MIM furnace utilization | K32: =IF('P-50 Auto'!furnace_sel="Continuous",'P-50 Auto'!total_hours_yr*'P-50 Auto'!total_builds_yr/K29,K27*K30) -> 17123.002 | L32: hrs | N32: Printer | O32: Raw materials | P32: =G21+G22 -> 0.87368794 | R32: Total | S32: Raw Materials | T32: =SUMIF($O$32:$O$49,S32,$P$32:$P$49) -> 0.87368794 | V32: Parts per build | Y32: ='P-50 Auto'!parts_job -> 819
B33: Printer available hours / year | C33: =C30*C31*'P-50 Auto'!weeks_yr -> 8064 | F33: Crosslink utilization | G33: ='P-50 Auto'!total_builds_yr*G30/((G31+1)*3) -> 21266.446 | H33: hrs | J33: MIM furnace investment | K33: =IFERROR(OFFSET(C121,'P-50 Auto'!furnace_index-1,)*K31,"N.A.") -> 3000000 | N33: Printer | O33: Consumables | P33: =G24 -> 0.06453121 | S33: Consumables | T33: =SUMIF($O$32:$O$49,S33,$P$32:$P$49) -> 0.071262644 | V33: Nesting density | Y33: =G16 -> 0.15656663
B34: Printer & furnace uptime | C34: 1 | F34: Crosslink investment | G34: ='P-50 Auto'!xlink_msrp+'P-50 Auto'!xlink_module_msrp*G31 -> 50000 | J34: ="Annual depreciation (@ "&'P-50 Auto'!furnace_depr&" yrs)" -> Annual depreciation (@ 10 yrs) | K34: =IFERROR(K33/'P-50 Auto'!furnace_depr+OFFSET(C131,'P-50 Auto'!furnace_index-1,)*K31*'P-50 Auto'!floor_rate,"N.A.") -> 309600 | N34: Printer | O34: Depreciation | P34: =G23 -> 0.069087452 | S34: Depreciation | T34: =SUMIF($O$32:$O$49,S34,$P$32:$P$49) -> 0.13675073 | V34: Parts per furnace run | Y34: =IF('P-50 Auto'!furnace_sel="Continuous","N.A.",K25) -> N.A.
B35: Printer uptime hours / year | C35: ='P-50 Auto'!avail_hours_yr*'P-50 Auto'!uptime -> 8064 | F35: ="Annual depreciation (@ "&'P-50 Auto'!dm_depr&" yrs)" -> Annual depreciation (@ 10 yrs) | G35: =G34/'P-50 Auto'!dm_depr -> 5000 | J35: Depreciation / part | K35: =IFERROR(K32/('P-50 Auto'!total_hours_yr*K31)*K34/'P-50 Auto'!part_req,"N.A.") -> 0.040026715 | N35: Printer | O35: Labor | P35: =G25 -> 0.012210012 | S35: Labor | T35: =SUMIF($O$32:$O$49,S35,$P$32:$P$49) -> 0.13663004 | V35: Builds per furnace run | Y35: =IFERROR(Y34/C18,"N.A.") -> N.A.
B36: Good parts / printer / year | C36: =ROUND('P-50 Auto'!good_parts_job/'P-50 Auto'!print_time_trn*'P-50 Auto'!uptime_hours_yr,0) -> 1824895 | F36: Depreciation $ / part | G36: =G33/('P-50 Auto'!total_hours_yr*IF('P-50 Auto'!p_model="P-50",1,G31))*G35/'P-50 Auto'!part_req -> 0.0024085477 | J36: Consumables / part | K36: =IF('P-50 Auto'!furnace_sel="Continuous",'P-50 Auto'!furnace_power_cons*'P-50 Auto'!total_hours_yr/'P-50 Auto'!part_req,0) -> 0.0067314339 | N36: Printer | O36: Utilities | P36: =G26 -> 0.0097494636 | S36: Utilities | T36: =SUMIF($O$32:$O$49,S36,$P$32:$P$49) -> 0.063466441 | V36: Parts per week | Y36: =Y37/'P-50 Auto'!weeks_yr -> 114055.94
B37: Parts required / year | C37: ='P-50 Auto'!part_capacity*3 -> 5474685 | F37: Labor $ / part | G37: =(0.5/IF('P-50 Auto'!p_model="P-50",1,G29)*'P-50 Auto'!labor_rate*'P-50 Auto'!total_builds_yr)/'P-50 Auto'!part_req -> 0.012210012 | J37: Labor $ / part | K37: =IF('P-50 Auto'!furnace_sel="Continuous",'P-50 Auto'!labor_rate*'P-50 Auto'!part_req/K26,'P-50 Auto'!labor_rate*K30*(K27-C108))/'P-50 Auto'!part_req -> 0.033333333 | N37: Crosslink | O37: Depreciation | P37: =G36 -> 0.0024085477 | S37: Total | T37: =SUM(T32:T36) -> 1.2817978 | V37: Parts per year | Y37: ='P-50 Auto'!part_req -> 5474685
F38: Utilities $ / part | G38: =IF('P-50 Auto'!p_model="P-50",'P-50 Auto'!power_rate*5*G33*(G31+1)+'P-50 Auto'!nitrogen_rate*18*60*G33*(G31+1),'P-50 Auto'!power_rate*5*G33+'P-50 Auto'!nitrogen_rate*120*G33)/'P-50 Auto'!part_req -> 0.026103879 | J38: Utilities / part | K38: =IF('P-50 Auto'!furnace_sel="Continuous",'P-50 Auto'!furnace_gas_cons*'P-50 Auto'!total_hours_yr,('P-50 Auto'!argon_rate*'P-50 Auto'!furnace_gas_cons+'P-50 Auto'!power_rate*'P-50 Auto'!furnace_power_cons)*(K27-K25/K26*2)*K30)/'P-50 Auto'!part_req -> 0.016349872 | N38: Crosslink | O38: Labor | P38: =G37 -> 0.012210012 | V38: Operating part cost | Y38: =P11 -> 1.1450471
A39: x | B39: Cost & other inputs | N39: Crosslink | O39: Utilities | P39: =G38 -> 0.026103879 | R39: Total | S39: Raw Materials | T39: =P32 -> 0.87368794 | V39: Operating cost / cc | Y39: =P13 -> 0.20946212
B40: Material selection | C40: 17-4PH SS | E40: x | F40: Depowder part cost calculation | I40: x | J40: PPU part cost calculation | N40: Depowder | O40: Depreciation | P40: =G48 -> 0.0075895328 | S40: Printer | T40: =SUMIF($N$33:$N$49,S40,$P$33:$P$49) -> 0.15557814 | V40: Fully burdened part cost | Y40: =P17 -> 1.2817978
B41: Powder MSRP | D41: $/kg | F41: Depowdered parts / hour | G41: =C49 -> 300 | J41: PPU required (rounded) | K41: =ROUNDUP(G10/2,0) -> 2 | N41: Depowder | O41: Labor | P41: =G49 -> 0.078876679 | S41: Crosslink | T41: =SUMIF($N$33:$N$49,S41,$P$33:$P$49) -> 0.040722439 | V41: Fully burdened cost / cc | Y41: =P19 -> 0.23447777
B42: Powder MSRP default | C42: {=+INDEX(C149:C158,VLOOKUP(C40,B137:F147,5,0))} -> 12.3 | D42: $/kg | F42: Run time + 30 min turnaround | G42: ='P-50 Auto'!parts_job/G41+0.5 -> 3.23 | H42: hrs | J42: PPU utilization (hrs) | K42: =MAX(G11/G10*ROUNDUP(G10/2,0),G45) -> 21591.249 | L42: hrs | N42: Depowder | O42: Utilities | P42: =G50 -> 0.0024254579 | S42: Depowder | T42: =SUMIF($N$33:$N$49,S42,$P$33:$P$49) -> 0.08889167 | V42: Printer utilization | Y42: =T14 -> 1.0000001
B43: Binder MSRP | C43: =IF('P-50 Auto'!binder_per_yr>F162,C163,IF('P-50 Auto'!binder_per_yr>F161,C162,C161)) -> 100 | D43: $/L | F43: Build capacity / year | G43: =ROUNDDOWN('P-50 Auto'!uptime_hours_yr/G42,0) -> 2496 | J43: PPU investment | K43: ='P-50 Auto'!ppu_msrp*K41 -> 700000 | N43: Furnace | O43: Consumables | P43: =IF(C15="No",0,IF(C16="Continuous",K36,)) -> 0.0067314339 | S43: Furnace | T43: =SUMIF($N$33:$N$49,S43,$P$33:$P$49) -> 0.096441355 | V43: Furnace utilization | Y43: =T17 -> 0.70779605
B44: Printheads MSRP | C44: =VLOOKUP(B44,Inputs!$B$6:$M$311,Inputs!M$1,0) -> 48000 | F44: Depowders required (rounded) | G44: =ROUNDUP('P-50 Auto'!total_builds_yr/G43,0) -> 3 | J44: ="Annual depreciation (@ "&'P-50 Auto'!dm_depr&" yrs)" -> Annual depreciation (@ 10 yrs) | K44: =K43/'P-50 Auto'!dm_depr+(3.7*1.8)*K41*'P-50 Auto'!floor_rate -> 72131.2 | N44: Furnace | O44: Depreciation | P44: =IF(C15="No",0,K35+IF($C$16<>"Continuous",K16,0)) -> 0.040026715 | S44: PPU | T44: =SUMIF($N$33:$N$49,S44,$P$33:$P$49) -> 0.026476253
B45: Region | C45: NAM | F45: Depowder utilization | G45: ='P-50 Auto'!total_builds_yr*G42 -> 21591.249 | H45: hrs | J45: Depreciation $ / part | K45: =K42/('P-50 Auto'!avail_hours_yr*K41)*K44/'P-50 Auto'!part_req -> 0.017638484 | N45: Furnace | O45: Labor | P45: =IF(C15="No",0,K37+IF($C$16<>"Continuous",K17,0)) -> 0.033333333 | S45: Total | T45: =SUM(T39:T44) -> 1.2817978
F46: Depowder investment | G46: =G44*'P-50 Auto'!depowder_msrp -> 450000 | J46: Labor $ / part | K46: 0 | N46: Furnace | O46: Utilities | P46: =IF(C15="No",0,K38+IF($C$16<>"Continuous",K18,0)) -> 0.016349872
A47: x | B47: Labor & equipment inputs | F47: ="Annual depreciation (@ "&'P-50 Auto'!dm_depr&" yrs)" -> Annual depreciation (@ 10 yrs) | G47: =G46/'P-50 Auto'!dm_depr+(2.7*1.2)*G44*'P-50 Auto'!floor_rate -> 46555.2 | J47: Utilities / part | K47: =50*'P-50 Auto'!uptime_hours_yr*'P-50 Auto'!power_rate/'P-50 Auto'!part_req -> 0.0088377687 | N47: PPU | O47: Depreciation | P47: =K45 -> 0.017638484
B48: Labor rate | C48: 20 | D48: $/hr | F48: Depreciation $ / part | G48: =G45/('P-50 Auto'!avail_hours_yr*G44)*G47/'P-50 Auto'!part_req -> 0.0075895328 | N48: PPU | O48: Labor | P48: =K46 -> 0
B49: Depowdered parts / hour | C49: =IF('P-50 Auto'!p_model="P-50",300,30) -> 300 | F49: Labor $ / part | G49: =G42*'P-50 Auto'!labor_rate*'P-50 Auto'!total_builds_yr/'P-50 Auto'!part_req -> 0.078876679 | N49: PPU | O49: Utilities | P49: =K47 -> 0.0088377687
B50: Furnace loading parts / hour | C50: =IF('P-50 Auto'!p_model="P-50",600,240) -> 600 | F50: Utilities $ / part | G50: ='P-50 Auto'!power_rate*5*G45/'P-50 Auto'!part_req+'P-50 Auto'!nitrogen_rate*15*G42/'P-50 Auto'!good_parts_job -> 0.0024254579
B51: DM equipment depreciation | C51: 10 | D51: yrs
B52: MIM furnace depreciation | C52: 10 | D52: yrs
B53: Nitrogen rate | C53: 0.001 | D53: $/L
B54: Argon rate | C54: 0.0025 | D54: $/L
B55: Power rate | C55: 0.12 | D55: $/kWh
B56: Floorspace rate / year | C56: 160 | D56: $/m2
A59: x | B59: Parts required / year | C59: =IF(C17="No",IF(C37<>"",C37,'P-50 Auto'!part_capacity),MIN('P-50 Auto'!part_capacity,K29*'P-50 Auto'!good_parts_job)) -> 5474685
B60: X-scale | C60: =VLOOKUP($B60,Inputs!$B$6:$M$309,Inputs!M$1,0) -> 1.16
B61: Y-scale | C61: =VLOOKUP($B61,Inputs!$B$6:$M$309,Inputs!M$1,0) -> 1.165
B62: Z-scale | C62: =VLOOKUP($B62,Inputs!$B$6:$M$309,Inputs!M$1,0) -> 1.18
B63: Layer speed | C63: =VLOOKUP($B63,Inputs!$B$6:$M$309,Inputs!M$1,0) -> 2.98 | D63: sec
B64: X-dim scaled | C64: ='P-50 Auto'!part_x*'P-50 Auto'!x_scale -> 46.4 | D64: mm
B65: Y-dim scaled | C65: ='P-50 Auto'!part_y*'P-50 Auto'!y_scale -> 46.6 | D65: mm
B66: Z-dim scaled | C66: ='P-50 Auto'!part_z*'P-50 Auto'!z_scale -> 17.7 | D66: mm
B67: Volume scaled | C67: ='P-50 Auto'!part_vol*'P-50 Auto'!x_scale*'P-50 Auto'!y_scale*'P-50 Auto'!z_scale -> 8717.3358 | D67: mm3
B68: Parts / job | C68: =IF('P-50 Auto'!override_nesting="Yes",IF(OR(C21=0,C22=0),C18,C21),C18) -> 819
B69: Bed density | C69: =VLOOKUP($B69,Inputs!$B$6:$M$309,Inputs!M$1,0) -> 0.6
B70: Build box X-dim | C70: =VLOOKUP($B70,Inputs!$B$6:$M$309,Inputs!M$1,0) -> 490 | D70: mm
B71: Build box Y-dim | C71: =VLOOKUP($B71,Inputs!$B$6:$M$309,Inputs!M$1,0) -> 380 | D71: mm
B72: Build box Z-dim | C72: =VLOOKUP($B72,Inputs!$B$6:$M$309,Inputs!M$1,0) -> 260 | D72: mm
B73: Build height | C73: =IF('P-50 Auto'!override_nesting="Yes",IF(OR(C21=0,C22=0),C19,C22),C19) -> 244.9 | D73: mm
B74: Build box volume | C74: ='P-50 Auto'!build_x*'P-50 Auto'!build_y*'P-50 Auto'!build_height -> 45600380 | D74: mm3
B75: Print turnaround time | C75: =VLOOKUP($B75,Inputs!$B$6:$M$309,Inputs!M$1,0) -> 0.5 | D75: hrs
B76: Powder + overflow ratio | C76: =VLOOKUP($B76,Inputs!$B$6:$M$309,Inputs!M$1,0) -> 6
B77: Powder loss percentage | C77: =VLOOKUP($B77,Inputs!$B$6:$M$309,Inputs!M$1,0) -> 0.001
B78: Binder void ratio | C78: =VLOOKUP($B78,Inputs!$B$6:$M$309,Inputs!M$1,0) -> 0.7
B79: Binder purge volume | C79: =VLOOKUP($B79,Inputs!$B$6:$M$309,Inputs!M$1,0) -> 20 | D79: mL
B80: Purge frequency | C80: =VLOOKUP($B80,Inputs!$B$6:$M$309,Inputs!M$1,0) -> 100 | D80: layers
B81: Printhead life | C81: =VLOOKUP($B81,Inputs!$B$6:$M$309,Inputs!M$1,0) -> 2500 | D81: L
B84: Printer XY border | C84: =IF('P-50 Auto'!p_model="P-50",20,8.5) -> 20 | D84: mm
B85: Printer Z base plate | C85: =IF('P-50 Auto'!p_model="P-50",10,4) -> 10 | D85: mm
B86: Printer XY spacing | C86: 1 | D86: mm
B87: Printer Z spacing | C87: 0.4 | D87: mm
B88: Crosslink time | C88: =VLOOKUP($B88,Inputs!$B$6:$M$309,Inputs!M$1,0) -> 40 | D88: hrs
B92: Furnace X-dim scaled | C92: =IF('P-50 Auto'!furnace_sel="Shop",IF(OR('P-50 Auto'!part_scale_x>dm_furnace_x,'P-50 Auto'!part_scale_y>dm_furnace_y),IF(AND('P-50 Auto'!part_scale_y<=dm_furnace_x,'P-50 Auto'!part_scale_x<=dm_furnace_y),'P-50 Auto'!part_scale_y,"N.A."),'P-50 Auto'!part_scale_x),IF(OR('P-50 Auto'!part_scale_x>'P-50 Auto'!mim_furnace_x,'P-50 Auto'!part_scale_y>'P-50 Auto'!mim_furnace_y),IF(AND('P-50 Auto'!part_scale_y<='P-50 Auto'!mim_furnace_x,'P-50 Auto'!part_scale_x<='P-50 Auto'!mim_furnace_y),'P-50 Auto'!part_scale_y,"N.A."),'P-50 Auto'!part_scale_x)) -> 46.4
B93: Furnace Y-dim scaled | C93: =IF(C92='P-50 Auto'!part_scale_x,'P-50 Auto'!part_scale_y,IF(C92='P-50 Auto'!part_scale_y,'P-50 Auto'!part_scale_x,"N.A.")) -> 46.6
B94: Furnace Z-dim scaled | C94: =IF(OR(C92="N.A.",C93="N.A."),"N.A.",'P-50 Auto'!part_scale_z) -> 17.7
B95: Furnace XY spacing | C95: 5 | D95: mm | G95: 5 ovens for 24/7 on Flex
B96: Furnace Z spacing | C96: 2 | D96: mm | G96: 3 people for depowder + ppu + printer - 24/7
B97: Furnace rack + setter thickness | C97: 2.6 | D97: mm
B101: Total hours / year | C101: =24*7*'P-50 Auto'!weeks_yr -> 8064
A103: x | B103: MIM furnace index | C103: =VLOOKUP('P-50 Auto'!furnace_sel,$B$121:$F$125,5,0) -> 5
B104: MIM furnace X-dim | C104: =CHOOSE(C$103,305,420,420,420,999999,"N.A.") -> 999999 | D104: mm
B105: MIM furnace Y-dim | C105: =CHOOSE(C$103,610,610,915,1524,999999,"N.A.") -> 999999 | D105: mm
B106: MIM furnace Z-dim | C106: =CHOOSE(C$103,305,460,460,460,999999,"N.A.") -> 999999 | D106: mm
B107: MIM furnace shelves | C107: 11
B108: MIM furnace cycle time | C108: =CHOOSE(C$103,18,20,22,26,24*5,"N.A.") -> 120 | D108: hrs
B109: =IF('P-50 Auto'!furnace_sel="Continuous","MIM furnace utilities rate","MIM furnace gas consumption") -> MIM furnace utilities rate | C109: =CHOOSE(C$103,660,1300,1700,2800,11.1,"N.A.") -> 11.1 | D109: =IF('P-50 Auto'!furnace_sel="Continuous","$/hr","L/hr") -> $/hr
B110: =IF('P-50 Auto'!furnace_sel="Continuous","MIM furnace consumables rate","MIM furnace power consumption") -> MIM furnace consumables rate | C110: =CHOOSE(C$103,60,80,100,120,4.57,"N.A.") -> 4.57 | D110: =IF('P-50 Auto'!furnace_sel="Continuous","$/hr","kW") -> $/hr
A112: x | B112: Equipment MSRPs
B113: Printer | C113: =IF('P-50 Auto'!p_model="P-50",990000,442000) -> 990000
...
